Workbook
Name FIN: القوائم!$H$2:$H$2
Name RAW: القوائم!$I$2:$I$5
Name TRN: القوائم!$J$2:$J$4

Sheet إدخال وسجل المنتجات
A1: مطعم بينو — سجل المنتجات والإدخال الذكي (تكويد تلقائي + ترجمة)
A2: ="منتج نهائي: "&COUNTIF($D$5:$D$590,"منتج نهائي") -> منتج نهائي: 109 | D2: ="مواد تحويلية: "&COUNTIF($D$5:$D$590,"مواد تحويلية") -> مواد تحويلية: 50 | F2: ="مواد خام: "&COUNTIF($D$5:$D$590,"مواد خام") -> مواد خام: 278
A3: اكتب الاسم (عربي) واختر النوع؛ الإنجليزي يظهر تلقائيًا من قاموس الترجمة، والكود تلقائي. النهائي حالته «جاهز للبيع». | E3: =HYPERLINK("#'إدخال وسجل المنتجات'!A156","📋 عرض كل الأصناف المسجّلة ("&(COUNTA($B$5:$B$154)+COUNTA($B$157:$B$590))&") ⤵") -> 📋 عرض كل الأصناف المسجّلة (435) ⤵
A4: م | B4: اسم المنتج (عربي) | C4: اسم المنتج (English) | D4: نوع المنتج | E4: حالة المنتج | F4: الكود (تلقائي) | G4: وحدة القياس | R4: السعرات الحرارية | S4: حجم الحصة (جم) | T4: سعرات / جرام | U4: وزن الوحدة (كجم)
A5: =IF($B5="","",COUNTA($B$5:$B5)) | C5: =IF($B5="","",IFERROR(VLOOKUP($B5,'قاموس الترجمة'!$A$2:$B$979,2,0),"")) | D5: مواد خام | E5: =IF($D5="منتج نهائي","جاهز للبيع","") | F5: =IF($B5="","",IF($K5<>"",$K5,IF($H5="","— اختر النوع —",IF(AND($H5<>"FIN",$I5=""),"— اختر الحالة —",$H5&"-"&$I5&"-"&TEXT(SUMPRODUCT(MAX(($H$157:$H$590=$H5)*($I$157:$I$590=$I5)*$J$157:$J$590))+SUMPRODUCT(($H$5:$H5=$H5)*($I$5:$I5=$I5)*($L$5:$L5=1)),"000"))))) | G5: وحدة | H5: =IFERROR(VLOOKUP($D5,القوائم!$A$2:$B$4,2,0),"") -> RAW | I5: =IF($H5="FIN","RTS",IF(ISNUMBER(SEARCH("مجمد",$E5)),"FRZ",IF(ISNUMBER(SEARCH("مبرد",$E5)),"CHL",IF(ISNUMBER(SEARCH("جاف",$E5)),"DRY",IF(ISNUMBER(SEARCH("استهلاك",$E5)),"CNS",IF(ISNUMBER(SEARCH("بيع",$E5)),"RTS","")))))) | K5: =IF($B5="","",IFERROR(INDEX($F$157:$F$590,MATCH($B5,$B$157:$B$590,0)),"")) | L5: =IF($B5="","",IF($K5="",1,0)) | M5: =IF($I5="","",COUNTIF($I$5:$I5,$I5)) | R5: 900 | S5: 300 | T5: =IF(OR($R5="",$S5="",$S5=0),"",ROUND($R5/$S5,2)) -> 3
A6: =IF($B6="","",COUNTA($B$5:$B6)) | C6: =IF($B6="","",IFERROR(VLOOKUP($B6,'قاموس الترجمة'!$A$2:$B$979,2,0),"")) | D6: مواد خام | E6: استهلاكي | F6: =IF($B6="","",IF($K6<>"",$K6,IF($H6="","— اختر النوع —",IF(AND($H6<>"FIN",$I6=""),"— اختر الحالة —",$H6&"-"&$I6&"-"&TEXT(SUMPRODUCT(MAX(($H$157:$H$590=$H6)*($I$157:$I$590=$I6)*$J$157:$J$590))+SUMPRODUCT(($H$5:$H6=$H6)*($I$5:$I6=$I6)*($L$5:$L6=1)),"000"))))) | G6: كيلو | H6: =IFERROR(VLOOKUP($D6,القوائم!$A$2:$B$4,2,0),"") -> RAW | I6: =IF($H6="FIN","RTS",IF(ISNUMBER(SEARCH("مجمد",$E6)),"FRZ",IF(ISNUMBER(SEARCH("مبرد",$E6)),"CHL",IF(ISNUMBER(SEARCH("جاف",$E6)),"DRY",IF(ISNUMBER(SEARCH("استهلاك",$E6)),"CNS",IF(ISNUMBER(SEARCH("بيع",$E6)),"RTS","")))))) -> CNS | K6: =IF($B6="","",IFERROR(INDEX($F$157:$F$590,MATCH($B6,$B$157:$B$590,0)),"")) | L6: =IF($B6="","",IF($K6="",1,0)) | M6: =IF($I6="","",COUNTIF($I$5:$I6,$I6)) -> 1 | T6: =IF(OR($R6="",$S6="",$S6=0),"",ROUND($R6/$S6,2))
A7: =IF($B7="","",COUNTA($B$5:$B7)) -> 1 | B7: طحين دبل زيرو | C7: =IF($B7="","",IFERROR(VLOOKUP($B7,'قاموس الترجمة'!$A$2:$B$979,2,0),"")) -> Flour Double Zero | D7: مواد خام | E7: تخزين جاف | F7: =IF($B7="","",IF($K7<>"",$K7,IF($H7="","— اختر النوع —",IF(AND($H7<>"FIN",$I7=""),"— اختر الحالة —",$H7&"-"&$I7&"-"&TEXT(SUMPRODUCT(MAX(($H$157:$H$590=$H7)*($I$157:$I$590=$I7)*$J$157:$J$590))+SUMPRODUCT(($H$5:$H7=$H7)*($I$5:$I7=$I7)*($L$5:$L7=1)),"000"))))) -> RAW-DRY-082 | G7: كيلو | H7: =IFERROR(VLOOKUP($D7,القوائم!$A$2:$B$4,2,0),"") -> RAW | I7: =IF($H7="FIN","RTS",IF(ISNUMBER(SEARCH("مجمد",$E7)),"FRZ",IF(ISNUMBER(SEARCH("مبرد",$E7)),"CHL",IF(ISNUMBER(SEARCH("جاف",$E7)),"DRY",IF(ISNUMBER(SEARCH("استهلاك",$E7)),"CNS",IF(ISNUMBER(SEARCH("بيع",$E7)),"RTS","")))))) -> DRY | K7: =IF($B7="","",IFERROR(INDEX($F$157:$F$590,MATCH($B7,$B$157:$B$590,0)),"")) -> RAW-DRY-082 | L7: =IF($B7="","",IF($K7="",1,0)) -> 0 | M7: =IF($I7="","",COUNTIF($I$5:$I7,$I7)) -> 1 | R7: 60 | S7: 100 | T7: =IF(OR($R7="",$S7="",$S7=0),"",ROUND($R7/$S7,2)) -> 0.6 | U7: 25
A8: =IF($B8="","",COUNTA($B$5:$B8)) | C8: =IF($B8="","",IFERROR(VLOOKUP($B8,'قاموس الترجمة'!$A$2:$B$979,2,0),"")) | E8: =IF($D8="منتج نهائي","جاهز للبيع","") | F8: =IF($B8="","",IF($K8<>"",$K8,IF($H8="","— اختر النوع —",IF(AND($H8<>"FIN",$I8=""),"— اختر الحالة —",$H8&"-"&$I8&"-"&TEXT(SUMPRODUCT(MAX(($H$157:$H$590=$H8)*($I$157:$I$590=$I8)*$J$157:$J$590))+SUMPRODUCT(($H$5:$H8=$H8)*($I$5:$I8=$I8)*($L$5:$L8=1)),"000"))))) | H8: =IFERROR(VLOOKUP($D8,القوائم!$A$2:$B$4,2,0),"") | I8: =IF($H8="FIN","RTS",IF(ISNUMBER(SEARCH("مجمد",$E8)),"FRZ",IF(ISNUMBER(SEARCH("مبرد",$E8)),"CHL",IF(ISNUMBER(SEARCH("جاف",$E8)),"DRY",IF(ISNUMBER(SEARCH("استهلاك",$E8)),"CNS",IF(ISNUMBER(SEARCH("بيع",$E8)),"RTS","")))))) | K8: =IF($B8="","",IFERROR(INDEX($F$157:$F$590,MATCH($B8,$B$157:$B$590,0)),"")) | L8: =IF($B8="","",IF($K8="",1,0)) | M8: =IF($I8="","",COUNTIF($I$5:$I8,$I8)) | T8: =IF(OR($R8="",$S8="",$S8=0),"",ROUND($R8/$S8,2))
A9: =IF($B9="","",COUNTA($B$5:$B9)) | C9: =IF($B9="","",IFERROR(VLOOKUP($B9,'قاموس الترجمة'!$A$2:$B$979,2,0),"")) | E9: =IF($D9="منتج نهائي","جاهز للبيع","") | F9: =IF($B9="","",IF($K9<>"",$K9,IF($H9="","— اختر النوع —",IF(AND($H9<>"FIN",$I9=""),"— اختر الحالة —",$H9&"-"&$I9&"-"&TEXT(SUMPRODUCT(MAX(($H$157:$H$590=$H9)*($I$157:$I$590=$I9)*$J$157:$J$590))+SUMPRODUCT(($H$5:$H9=$H9)*($I$5:$I9=$I9)*($L$5:$L9=1)),"000"))))) | H9: =IFERROR(VLOOKUP($D9,القوائم!$A$2:$B$4,2,0),"") | I9: =IF($H9="FIN","RTS",IF(ISNUMBER(SEARCH("مجمد",$E9)),"FRZ",IF(ISNUMBER(SEARCH("مبرد",$E9)),"CHL",IF(ISNUMBER(SEARCH("جاف",$E9)),"DRY",IF(ISNUMBER(SEARCH("استهلاك",$E9)),"CNS",IF(ISNUMBER(SEARCH("بيع",$E9)),"RTS","")))))) | K9: =IF($B9="","",IFERROR(INDEX($F$157:$F$590,MATCH($B9,$B$157:$B$590,0)),"")) | L9: =IF($B9="","",IF($K9="",1,0)) | M9: =IF($I9="","",COUNTIF($I$5:$I9,$I9)) | T9: =IF(OR($R9="",$S9="",$S9=0),"",ROUND($R9/$S9,2))
A10: =IF($B10="","",COUNTA($B$5:$B10)) | C10: =IF($B10="","",IFERROR(VLOOKUP($B10,'قاموس الترجمة'!$A$2:$B$979,2,0),"")) | E10: =IF($D10="منتج نهائي","جاهز للبيع","") | F10: =IF($B10="","",IF($K10<>"",$K10,IF($H10="","— اختر النوع —",IF(AND($H10<>"FIN",$I10=""),"— اختر الحالة —",$H10&"-"&$I10&"-"&TEXT(SUMPRODUCT(MAX(($H$157:$H$590=$H10)*($I$157:$I$590=$I10)*$J$157:$J$590))+SUMPRODUCT(($H$5:$H10=$H10)*($I$5:$I10=$I10)*($L$5:$L10=1)),"000"))))) | H10: =IFERROR(VLOOKUP($D10,القوائم!$A$2:$B$4,2,0),"") | I10: =IF($H10="FIN","RTS",IF(ISNUMBER(SEARCH("مجمد",$E10)),"FRZ",IF(ISNUMBER(SEARCH("مبرد",$E10)),"CHL",IF(ISNUMBER(SEARCH("جاف",$E10)),"DRY",IF(ISNUMBER(SEARCH("استهلاك",$E10)),"CNS",IF(ISNUMBER(SEARCH("بيع",$E10)),"RTS","")))))) | K10: =IF($B10="","",IFERROR(INDEX($F$157:$F$590,MATCH($B10,$B$157:$B$590,0)),"")) | L10: =IF($B10="","",IF($K10="",1,0)) | M10: =IF($I10="","",COUNTIF($I$5:$I10,$I10)) | T10: =IF(OR($R10="",$S10="",$S10=0),"",ROUND($R10/$S10,2))
A11: =IF($B11="","",COUNTA($B$5:$B11)) | C11: =IF($B11="","",IFERROR(VLOOKUP($B11,'قاموس الترجمة'!$A$2:$B$979,2,0),"")) | E11: =IF($D11="منتج نهائي","جاهز للبيع","") | F11: =IF($B11="","",IF($K11<>"",$K11,IF($H11="","— اختر النوع —",IF(AND($H11<>"FIN",$I11=""),"— اختر الحالة —",$H11&"-"&$I11&"-"&TEXT(SUMPRODUCT(MAX(($H$157:$H$590=$H11)*($I$157:$I$590=$I11)*$J$157:$J$590))+SUMPRODUCT(($H$5:$H11=$H11)*($I$5:$I11=$I11)*($L$5:$L11=1)),"000"))))) | H11: =IFERROR(VLOOKUP($D11,القوائم!$A$2:$B$4,2,0),"") | I11: =IF($H11="FIN","RTS",IF(ISNUMBER(SEARCH("مجمد",$E11)),"FRZ",IF(ISNUMBER(SEARCH("مبرد",$E11)),"CHL",IF(ISNUMBER(SEARCH("جاف",$E11)),"DRY",IF(ISNUMBER(SEARCH("استهلاك",$E11)),"CNS",IF(ISNUMBER(SEARCH("بيع",$E11)),"RTS","")))))) | K11: =IF($B11="","",IFERROR(INDEX($F$157:$F$590,MATCH($B11,$B$157:$B$590,0)),"")) | L11: =IF($B11="","",IF($K11="",1,0)) | M11: =IF($I11="","",COUNTIF($I$5:$I11,$I11)) | T11: =IF(OR($R11="",$S11="",$S11=0),"",ROUND($R11/$S11,2))
A12: =IF($B12="","",COUNTA($B$5:$B12)) | C12: =IF($B12="","",IFERROR(VLOOKUP($B12,'قاموس الترجمة'!$A$2:$B$979,2,0),"")) | E12: =IF($D12="منتج نهائي","جاهز للبيع","") | F12: =IF($B12="","",IF($K12<>"",$K12,IF($H12="","— اختر النوع —",IF(AND($H12<>"FIN",$I12=""),"— اختر الحالة —",$H12&"-"&$I12&"-"&TEXT(SUMPRODUCT(MAX(($H$157:$H$590=$H12)*($I$157:$I$590=$I12)*$J$157:$J$590))+SUMPRODUCT(($H$5:$H12=$H12)*($I$5:$I12=$I12)*($L$5:$L12=1)),"000"))))) | H12: =IFERROR(VLOOKUP($D12,القوائم!$A$2:$B$4,2,0),"") | I12: =IF($H12="FIN","RTS",IF(ISNUMBER(SEARCH("مجمد",$E12)),"FRZ",IF(ISNUMBER(SEARCH("مبرد",$E12)),"CHL",IF(ISNUMBER(SEARCH("جاف",$E12)),"DRY",IF(ISNUMBER(SEARCH("استهلاك",$E12)),"CNS",IF(ISNUMBER(SEARCH("بيع",$E12)),"RTS","")))))) | K12: =IF($B12="","",IFERROR(INDEX($F$157:$F$590,MATCH($B12,$B$157:$B$590,0)),"")) | L12: =IF($B12="","",IF($K12="",1,0)) | M12: =IF($I12="","",COUNTIF($I$5:$I12,$I12)) | T12: =IF(OR($R12="",$S12="",$S12=0),"",ROUND($R12/$S12,2))
A13: =IF($B13="","",COUNTA($B$5:$B13)) | C13: =IF($B13="","",IFERROR(VLOOKUP($B13,'قاموس الترجمة'!$A$2:$B$979,2,0),"")) | E13: =IF($D13="منتج نهائي","جاهز للبيع","") | F13: =IF($B13="","",IF($K13<>"",$K13,IF($H13="","— اختر النوع —",IF(AND($H13<>"FIN",$I13=""),"— اختر الحالة —",$H13&"-"&$I13&"-"&TEXT(SUMPRODUCT(MAX(($H$157:$H$590=$H13)*($I$157:$I$590=$I13)*$J$157:$J$590))+SUMPRODUCT(($H$5:$H13=$H13)*($I$5:$I13=$I13)*($L$5:$L13=1)),"000"))))) | H13: =IFERROR(VLOOKUP($D13,القوائم!$A$2:$B$4,2,0),"") | I13: =IF($H13="FIN","RTS",IF(ISNUMBER(SEARCH("مجمد",$E13)),"FRZ",IF(ISNUMBER(SEARCH("مبرد",$E13)),"CHL",IF(ISNUMBER(SEARCH("جاف",$E13)),"DRY",IF(ISNUMBER(SEARCH("استهلاك",$E13)),"CNS",IF(ISNUMBER(SEARCH("بيع",$E13)),"RTS","")))))) | K13: =IF($B13="","",IFERROR(INDEX($F$157:$F$590,MATCH($B13,$B$157:$B$590,0)),"")) | L13: =IF($B13="","",IF($K13="",1,0)) | M13: =IF($I13="","",COUNTIF($I$5:$I13,$I13)) | T13: =IF(OR($R13="",$S13="",$S13=0),"",ROUND($R13/$S13,2))
A14: =IF($B14="","",COUNTA($B$5:$B14)) | C14: =IF($B14="","",IFERROR(VLOOKUP($B14,'قاموس الترجمة'!$A$2:$B$979,2,0),"")) | E14: =IF($D14="منتج نهائي","جاهز للبيع","") | F14: =IF($B14="","",IF($K14<>"",$K14,IF($H14="","— اختر النوع —",IF(AND($H14<>"FIN",$I14=""),"— اختر الحالة —",$H14&"-"&$I14&"-"&TEXT(SUMPRODUCT(MAX(($H$157:$H$590=$H14)*($I$157:$I$590=$I14)*$J$157:$J$590))+SUMPRODUCT(($H$5:$H14=$H14)*($I$5:$I14=$I14)*($L$5:$L14=1)),"000"))))) | H14: =IFERROR(VLOOKUP($D14,القوائم!$A$2:$B$4,2,0),"") | I14: =IF($H14="FIN","RTS",IF(ISNUMBER(SEARCH("مجمد",$E14)),"FRZ",IF(ISNUMBER(SEARCH("مبرد",$E14)),"CHL",IF(ISNUMBER(SEARCH("جاف",$E14)),"DRY",IF(ISNUMBER(SEARCH("استهلاك",$E14)),"CNS",IF(ISNUMBER(SEARCH("بيع",$E14)),"RTS","")))))) | K14: =IF($B14="","",IFERROR(INDEX($F$157:$F$590,MATCH($B14,$B$157:$B$590,0)),"")) | L14: =IF($B14="","",IF($K14="",1,0)) | M14: =IF($I14="","",COUNTIF($I$5:$I14,$I14)) | T14: =IF(OR($R14="",$S14="",$S14=0),"",ROUND($R14/$S14,2))
A15: =IF($B15="","",COUNTA($B$5:$B15)) | C15: =IF($B15="","",IFERROR(VLOOKUP($B15,'قاموس الترجمة'!$A$2:$B$979,2,0),"")) | E15: =IF($D15="منتج نهائي","جاهز للبيع","") | F15: =IF($B15="","",IF($K15<>"",$K15,IF($H15="","— اختر النوع —",IF(AND($H15<>"FIN",$I15=""),"— اختر الحالة —",$H15&"-"&$I15&"-"&TEXT(SUMPRODUCT(MAX(($H$157:$H$590=$H15)*($I$157:$I$590=$I15)*$J$157:$J$590))+SUMPRODUCT(($H$5:$H15=$H15)*($I$5:$I15=$I15)*($L$5:$L15=1)),"000"))))) | H15: =IFERROR(VLOOKUP($D15,القوائم!$A$2:$B$4,2,0),"") | I15: =IF($H15="FIN","RTS",IF(ISNUMBER(SEARCH("مجمد",$E15)),"FRZ",IF(ISNUMBER(SEARCH("مبرد",$E15)),"CHL",IF(ISNUMBER(SEARCH("جاف",$E15)),"DRY",IF(ISNUMBER(SEARCH("استهلاك",$E15)),"CNS",IF(ISNUMBER(SEARCH("بيع",$E15)),"RTS","")))))) | K15: =IF($B15="","",IFERROR(INDEX($F$157:$F$590,MATCH($B15,$B$157:$B$590,0)),"")) | L15: =IF($B15="","",IF($K15="",1,0)) | M15: =IF($I15="","",COUNTIF($I$5:$I15,$I15)) | T15: =IF(OR($R15="",$S15="",$S15=0),"",ROUND($R15/$S15,2))
A16: =IF($B16="","",COUNTA($B$5:$B16)) | C16: =IF($B16="","",IFERROR(VLOOKUP($B16,'قاموس الترجمة'!$A$2:$B$979,2,0),"")) | E16: =IF($D16="منتج نهائي","جاهز للبيع","") | F16: =IF($B16="","",IF($K16<>"",$K16,IF($H16="","— اختر النوع —",IF(AND($H16<>"FIN",$I16=""),"— اختر الحالة —",$H16&"-"&$I16&"-"&TEXT(SUMPRODUCT(MAX(($H$157:$H$590=$H16)*($I$157:$I$590=$I16)*$J$157:$J$590))+SUMPRODUCT(($H$5:$H16=$H16)*($I$5:$I16=$I16)*($L$5:$L16=1)),"000"))))) | H16: =IFERROR(VLOOKUP($D16,القوائم!$A$2:$B$4,2,0),"") | I16: =IF($H16="FIN","RTS",IF(ISNUMBER(SEARCH("مجمد",$E16)),"FRZ",IF(ISNUMBER(SEARCH("مبرد",$E16)),"CHL",IF(ISNUMBER(SEARCH("جاف",$E16)),"DRY",IF(ISNUMBER(SEARCH("استهلاك",$E16)),"CNS",IF(ISNUMBER(SEARCH("بيع",$E16)),"RTS","")))))) | K16: =IF($B16="","",IFERROR(INDEX($F$157:$F$590,MATCH($B16,$B$157:$B$590,0)),"")) | L16: =IF($B16="","",IF($K16="",1,0)) | M16: =IF($I16="","",COUNTIF($I$5:$I16,$I16)) | T16: =IF(OR($R16="",$S16="",$S16=0),"",ROUND($R16/$S16,2))
A17: =IF($B17="","",COUNTA($B$5:$B17)) | C17: =IF($B17="","",IFERROR(VLOOKUP($B17,'قاموس الترجمة'!$A$2:$B$979,2,0),"")) | E17: =IF($D17="منتج نهائي","جاهز للبيع","") | F17: =IF($B17="","",IF($K17<>"",$K17,IF($H17="","— اختر النوع —",IF(AND($H17<>"FIN",$I17=""),"— اختر الحالة —",$H17&"-"&$I17&"-"&TEXT(SUMPRODUCT(MAX(($H$157:$H$590=$H17)*($I$157:$I$590=$I17)*$J$157:$J$590))+SUMPRODUCT(($H$5:$H17=$H17)*($I$5:$I17=$I17)*($L$5:$L17=1)),"000"))))) | H17: =IFERROR(VLOOKUP($D17,القوائم!$A$2:$B$4,2,0),"") | I17: =IF($H17="FIN","RTS",IF(ISNUMBER(SEARCH("مجمد",$E17)),"FRZ",IF(ISNUMBER(SEARCH("مبرد",$E17)),"CHL",IF(ISNUMBER(SEARCH("جاف",$E17)),"DRY",IF(ISNUMBER(SEARCH("استهلاك",$E17)),"CNS",IF(ISNUMBER(SEARCH("بيع",$E17)),"RTS","")))))) | K17: =IF($B17="","",IFERROR(INDEX($F$157:$F$590,MATCH($B17,$B$157:$B$590,0)),"")) | L17: =IF($B17="","",IF($K17="",1,0)) | M17: =IF($I17="","",COUNTIF($I$5:$I17,$I17)) | T17: =IF(OR($R17="",$S17="",$S17=0),"",ROUND($R17/$S17,2))
A18: =IF($B18="","",COUNTA($B$5:$B18)) | C18: =IF($B18="","",IFERROR(VLOOKUP($B18,'قاموس الترجمة'!$A$2:$B$979,2,0),"")) | E18: =IF($D18="منتج نهائي","جاهز للبيع","") | F18: =IF($B18="","",IF($K18<>"",$K18,IF($H18="","— اختر النوع —",IF(AND($H18<>"FIN",$I18=""),"— اختر الحالة —",$H18&"-"&$I18&"-"&TEXT(SUMPRODUCT(MAX(($H$157:$H$590=$H18)*($I$157:$I$590=$I18)*$J$157:$J$590))+SUMPRODUCT(($H$5:$H18=$H18)*($I$5:$I18=$I18)*($L$5:$L18=1)),"000"))))) | H18: =IFERROR(VLOOKUP($D18,القوائم!$A$2:$B$4,2,0),"") | I18: =IF($H18="FIN","RTS",IF(ISNUMBER(SEARCH("مجمد",$E18)),"FRZ",IF(ISNUMBER(SEARCH("مبرد",$E18)),"CHL",IF(ISNUMBER(SEARCH("جاف",$E18)),"DRY",IF(ISNUMBER(SEARCH("استهلاك",$E18)),"CNS",IF(ISNUMBER(SEARCH("بيع",$E18)),"RTS","")))))) | K18: =IF($B18="","",IFERROR(INDEX($F$157:$F$590,MATCH($B18,$B$157:$B$590,0)),"")) | L18: =IF($B18="","",IF($K18="",1,0)) | M18: =IF($I18="","",COUNTIF($I$5:$I18,$I18)) | T18: =IF(OR($R18="",$S18="",$S18=0),"",ROUND($R18/$S18,2))
A19: =IF($B19="","",COUNTA($B$5:$B19)) | C19: =IF($B19="","",IFERROR(VLOOKUP($B19,'قاموس الترجمة'!$A$2:$B$979,2,0),"")) | E19: =IF($D19="منتج نهائي","جاهز للبيع","") | F19: =IF($B19="","",IF($K19<>"",$K19,IF($H19="","— اختر النوع —",IF(AND($H19<>"FIN",$I19=""),"— اختر الحالة —",$H19&"-"&$I19&"-"&TEXT(SUMPRODUCT(MAX(($H$157:$H$590=$H19)*($I$157:$I$590=$I19)*$J$157:$J$590))+SUMPRODUCT(($H$5:$H19=$H19)*($I$5:$I19=$I19)*($L$5:$L19=1)),"000"))))) | H19: =IFERROR(VLOOKUP($D19,القوائم!$A$2:$B$4,2,0),"") | I19: =IF($H19="FIN","RTS",IF(ISNUMBER(SEARCH("مجمد",$E19)),"FRZ",IF(ISNUMBER(SEARCH("مبرد",$E19)),"CHL",IF(ISNUMBER(SEARCH("جاف",$E19)),"DRY",IF(ISNUMBER(SEARCH("استهلاك",$E19)),"CNS",IF(ISNUMBER(SEARCH("بيع",$E19)),"RTS","")))))) | K19: =IF($B19="","",IFERROR(INDEX($F$157:$F$590,MATCH($B19,$B$157:$B$590,0)),"")) | L19: =IF($B19="","",IF($K19="",1,0)) | M19: =IF($I19="","",COUNTIF($I$5:$I19,$I19)) | T19: =IF(OR($R19="",$S19="",$S19=0),"",ROUND($R19/$S19,2))
... A154: =IF($B154="","",COUNTA($B$5:$B154)) | C154: =IF($B154="","",IFERROR(VLOOKUP($B154,'قاموس الترجمة'!$A$2:$B$979,2,0),"")) | E154: =IF($D154="منتج نهائي","جاهز للبيع","") | F154: =IF($B154="","",IF($K154<>"",$K154,IF($H154="","— اختر النوع —",IF(AND($H154<>"FIN",$I154=""),"— اختر الحالة —",$H154&"-"&$I154&"-"&TEXT(SUMPRODUCT(MAX(($H$157:$H$590=$H154)*($I$157:$I$590=$I154)*$J$157:$J$590))+SUMPRODUCT(($H$5:$H154=$H154)*($I$5:$I154=$I154)*($L$5:$L154=1)),"000"))))) | H154: =IFERROR(VLOOKUP($D154,القوائم!$A$2:$B$4,2,0),"") | I154: =IF($H154="FIN","RTS",IF(ISNUMBER(SEARCH("مجمد",$E154)),"FRZ",IF(ISNUMBER(SEARCH("مبرد",$E154)),"CHL",IF(ISNUMBER(SEARCH("جاف",$E154)),"DRY",IF(ISNUMBER(SEARCH("استهلاك",$E154)),"CNS",IF(ISNUMBER(SEARCH("بيع",$E154)),"RTS","")))))) | K154: =IF($B154="","",IFERROR(INDEX($F$157:$F$590,MATCH($B154,$B$157:$B$590,0)),"")) | L154: =IF($B154="","",IF($K154="",1,0)) | M154: =IF($I154="","",COUNTIF($I$5:$I154,$I154)) | T154: =IF(OR($R154="",$S154="",$S154=0),"",ROUND($R154/$S154,2))
A155: ▼ السجل الكامل (434) — عدّل أي صنف؛ يأخذ كودًا جديدًا عند تغيير تصنيفه دون المساس بباقي الأكواد ▼ | G155: =HYPERLINK("#'إدخال وسجل المنتجات'!A5","⬆ العودة للإدخال") -> ⬆ العودة للإدخال
A156: م | B156: اسم المنتج (عربي) | C156: اسم المنتج EN | D156: نوع المنتج | E156: حالة المنتج | F156: الكود | G156: وحدة القياس | R156: السعرات الحرارية | S156: حجم الحصة (جم) | T156: سعرات / جرام
A157: 1 | B157: احتفال اعياد ميلاد | C157: Birthday Celebration | D157: مواد خام | E157: استهلاكي | F157: =IF($H157="","",$H157&"-"&$I157&"-"&TEXT($J157,"000")) -> RAW-CNS-001 | G157: وحدة | H157: =IFERROR(VLOOKUP($D157,القوائم!$A$2:$B$4,2,0),"") -> RAW | I157: =IF($H157="FIN","RTS",IF(ISNUMBER(SEARCH("مجمد",$E157)),"FRZ",IF(ISNUMBER(SEARCH("مبرد",$E157)),"CHL",IF(ISNUMBER(SEARCH("جاف",$E157)),"DRY",IF(ISNUMBER(SEARCH("استهلاك",$E157)),"CNS",IF(ISNUMBER(SEARCH("بيع",$E157)),"RTS","")))))) -> CNS | J157: =IF($H157="","",IF($N157=0,$Q157,SUMPRODUCT(($O$157:$O$590=$H157)*($P$157:$P$590=$I157)*$Q$157:$Q$590)+COUNTIFS($H$157:$H157,$H157,$I$157:$I157,$I157,$N$157:$N157,1))) -> 1 | M157: =IF($I157="","",COUNTIF($I$5:$I157,$I157)) -> 2 | N157: =IF($H157="","",IF(OR($H157<>$O157,$I157<>$P157),1,0)) -> 0 | O157: RAW | P157: CNS | Q157: 1 | T157: =IF(OR($R157="",$S157="",$S157=0),"",ROUND($R157/$S157,2))
A158: 2 | B158: ارانشيني ترافل rozetto balls | C158: Truffle Rozetto Balls Arancini | D158: منتج نهائي | E158: جاهز للبيع | F158: =IF($H158="","",$H158&"-"&$I158&"-"&TEXT($J158,"000")) -> FIN-RTS-001 | G158: وحدة | H158: =IFERROR(VLOOKUP($D158,القوائم!$A$2:$B$4,2,0),"") -> FIN | I158: =IF($H158="FIN","RTS",IF(ISNUMBER(SEARCH("مجمد",$E158)),"FRZ",IF(ISNUMBER(SEARCH("مبرد",$E158)),"CHL",IF(ISNUMBER(SEARCH("جاف",$E158)),"DRY",IF(ISNUMBER(SEARCH("استهلاك",$E158)),"CNS",IF(ISNUMBER(SEARCH("بيع",$E158)),"RTS","")))))) -> RTS | J158: =IF($H158="","",IF($N158=0,$Q158,SUMPRODUCT(($O$157:$O$590=$H158)*($P$157:$P$590=$I158)*$Q$157:$Q$590)+COUNTIFS($H$157:$H158,$H158,$I$157:$I158,$I158,$N$157:$N158,1))) -> 1 | M158: =IF($I158="","",COUNTIF($I$5:$I158,$I158)) -> 1 | N158: =IF($H158="","",IF(OR($H158<>$O158,$I158<>$P158),1,0)) -> 0 | O158: FIN | P158: RTS | Q158: 1 | R158: 270 | S158: 100 | T158: =IF(OR($R158="",$S158="",$S158=0),"",ROUND($R158/$S158,2)) -> 2.7
A159: 3 | B159: ارانشيني عادي rozetto balls | C159: Rozetto Balls Arancini | D159: منتج نهائي | E159: جاهز للبيع | F159: =IF($H159="","",$H159&"-"&$I159&"-"&TEXT($J159,"000")) -> FIN-RTS-002 | G159: وحدة | H159: =IFERROR(VLOOKUP($D159,القوائم!$A$2:$B$4,2,0),"") -> FIN | I159: =IF($H159="FIN","RTS",IF(ISNUMBER(SEARCH("مجمد",$E159)),"FRZ",IF(ISNUMBER(SEARCH("مبرد",$E159)),"CHL",IF(ISNUMBER(SEARCH("جاف",$E159)),"DRY",IF(ISNUMBER(SEARCH("استهلاك",$E159)),"CNS",IF(ISNUMBER(SEARCH("بيع",$E159)),"RTS","")))))) -> RTS | J159: =IF($H159="","",IF($N159=0,$Q159,SUMPRODUCT(($O$157:$O$590=$H159)*($P$157:$P$590=$I159)*$Q$157:$Q$590)+COUNTIFS($H$157:$H159,$H159,$I$157:$I159,$I159,$N$157:$N159,1))) -> 2 | M159: =IF($I159="","",COUNTIF($I$5:$I159,$I159)) -> 2 | N159: =IF($H159="","",IF(OR($H159<>$O159,$I159<>$P159),1,0)) -> 0 | O159: FIN | P159: RTS | Q159: 2 | R159: 260 | S159: 100 | T159: =IF(OR($R159="",$S159="",$S159=0),"",ROUND($R159/$S159,2)) -> 2.6
A160: 4 | B160: ارانشيني rozetto balls | C160: Rozetto Balls Arancini | D160: منتج نهائي | E160: جاهز للبيع | F160: =IF($H160="","",$H160&"-"&$I160&"-"&TEXT($J160,"000")) -> FIN-RTS-003 | G160: وحدة | H160: =IFERROR(VLOOKUP($D160,القوائم!$A$2:$B$4,2,0),"") -> FIN | I160: =IF($H160="FIN","RTS",IF(ISNUMBER(SEARCH("مجمد",$E160)),"FRZ",IF(ISNUMBER(SEARCH("مبرد",$E160)),"CHL",IF(ISNUMBER(SEARCH("جاف",$E160)),"DRY",IF(ISNUMBER(SEARCH("استهلاك",$E160)),"CNS",IF(ISNUMBER(SEARCH("بيع",$E160)),"RTS","")))))) -> RTS | J160: =IF($H160="","",IF($N160=0,$Q160,SUMPRODUCT(($O$157:$O$590=$H160)*($P$157:$P$590=$I160)*$Q$157:$Q$590)+COUNTIFS($H$157:$H160,$H160,$I$157:$I160,$I160,$N$157:$N160,1))) -> 3 | M160: =IF($I160="","",COUNTIF($I$5:$I160,$I160)) -> 3 | N160: =IF($H160="","",IF(OR($H160<>$O160,$I160<>$P160),1,0)) -> 0 | O160: FIN | P160: RTS | Q160: 3 | R160: 260 | S160: 100 | T160: =IF(OR($R160="",$S160="",$S160=0),"",ROUND($R160/$S160,2)) -> 2.6
A161: 5 | B161: اضافات جبنة | C161: Cheese Add-on | D161: منتج نهائي | E161: جاهز للبيع | F161: =IF($H161="","",$H161&"-"&$I161&"-"&TEXT($J161,"000")) -> FIN-RTS-004 | G161: وحدة | H161: =IFERROR(VLOOKUP($D161,القوائم!$A$2:$B$4,2,0),"") -> FIN | I161: =IF($H161="FIN","RTS",IF(ISNUMBER(SEARCH("مجمد",$E161)),"FRZ",IF(ISNUMBER(SEARCH("مبرد",$E161)),"CHL",IF(ISNUMBER(SEARCH("جاف",$E161)),"DRY",IF(ISNUMBER(SEARCH("استهلاك",$E161)),"CNS",IF(ISNUMBER(SEARCH("بيع",$E161)),"RTS","")))))) -> RTS | J161: =IF($H161="","",IF($N161=0,$Q161,SUMPRODUCT(($O$157:$O$590=$H161)*($P$157:$P$590=$I161)*$Q$157:$Q$590)+COUNTIFS($H$157:$H161,$H161,$I$157:$I161,$I161,$N$157:$N161,1))) -> 4 | M161: =IF($I161="","",COUNTIF($I$5:$I161,$I161)) -> 4 | N161: =IF($H161="","",IF(OR($H161<>$O161,$I161<>$P161),1,0)) -> 0 | O161: FIN | P161: RTS | Q161: 4 | R161: 300 | S161: 100 | T161: =IF(OR($R161="",$S161="",$S161=0),"",ROUND($R161/$S161,2)) -> 3
A162: 6 | B162: الشوربة الايطالية | C162: Italian Soup | D162: منتج نهائي | E162: جاهز للبيع | F162: =IF($H162="","",$H162&"-"&$I162&"-"&TEXT($J162,"000")) -> FIN-RTS-005 | G162: وحدة | H162: =IFERROR(VLOOKUP($D162,القوائم!$A$2:$B$4,2,0),"") -> FIN | I162: =IF($H162="FIN","RTS",IF(ISNUMBER(SEARCH("مجمد",$E162)),"FRZ",IF(ISNUMBER(SEARCH("مبرد",$E162)),"CHL",IF(ISNUMBER(SEARCH("جاف",$E162)),"DRY",IF(ISNUMBER(SEARCH("استهلاك",$E162)),"CNS",IF(ISNUMBER(SEARCH("بيع",$E162)),"RTS","")))))) -> RTS | J162: =IF($H162="","",IF($N162=0,$Q162,SUMPRODUCT(($O$157:$O$590=$H162)*($P$157:$P$590=$I162)*$Q$157:$Q$590)+COUNTIFS($H$157:$H162,$H162,$I$157:$I162,$I162,$N$157:$N162,1))) -> 5 | M162: =IF($I162="","",COUNTIF($I$5:$I162,$I162)) -> 5 | N162: =IF($H162="","",IF(OR($H162<>$O162,$I162<>$P162),1,0)) -> 0 | O162: FIN | P162: RTS | Q162: 5 | R162: 60 | S162: 100 | T162: =IF(OR($R162="",$S162="",$S162=0),"",ROUND($R162/$S162,2)) -> 0.6
A163: 7 | B163: الشوربة السعودية | C163: Saudi Soup | D163: منتج نهائي | E163: جاهز للبيع | F163: =IF($H163="","",$H163&"-"&$I163&"-"&TEXT($J163,"000")) -> FIN-RTS-006 | G163: وحدة | H163: =IFERROR(VLOOKUP($D163,القوائم!$A$2:$B$4,2,0),"") -> FIN | I163: =IF($H163="FIN","RTS",IF(ISNUMBER(SEARCH("مجمد",$E163)),"FRZ",IF(ISNUMBER(SEARCH("مبرد",$E163)),"CHL",IF(ISNUMBER(SEARCH("جاف",$E163)),"DRY",IF(ISNUMBER(SEARCH("استهلاك",$E163)),"CNS",IF(ISNUMBER(SEARCH("بيع",$E163)),"RTS","")))))) -> RTS | J163: =IF($H163="","",IF($N163=0,$Q163,SUMPRODUCT(($O$157:$O$590=$H163)*($P$157:$P$590=$I163)*$Q$157:$Q$590)+COUNTIFS($H$157:$H163,$H163,$I$157:$I163,$I163,$N$157:$N163,1))) -> 6 | M163: =IF($I163="","",COUNTIF($I$5:$I163,$I163)) -> 6 | N163: =IF($H163="","",IF(OR($H163<>$O163,$I163<>$P163),1,0)) -> 0 | O163: FIN | P163: RTS | Q163: 6 | R163: 65 | S163: 100 | T163: =IF(OR($R163="",$S163="",$S163=0),"",ROUND($R163/$S163,2)) -> 0.65
A164: 8 | B164: الفريدو باستا خالي من الجلوتين | C164: Alfredo Pasta Gluten-Free | D164: منتج نهائي | E164: جاهز للبيع | F164: =IF($H164="","",$H164&"-"&$I164&"-"&TEXT($J164,"000")) -> FIN-RTS-007 | G164: وحدة | H164: =IFERROR(VLOOKUP($D164,القوائم!$A$2:$B$4,2,0),"") -> FIN | I164: =IF($H164="FIN","RTS",IF(ISNUMBER(SEARCH("مجمد",$E164)),"FRZ",IF(ISNUMBER(SEARCH("مبرد",$E164)),"CHL",IF(ISNUMBER(SEARCH("جاف",$E164)),"DRY",IF(ISNUMBER(SEARCH("استهلاك",$E164)),"CNS",IF(ISNUMBER(SEARCH("بيع",$E164)),"RTS","")))))) -> RTS | J164: =IF($H164="","",IF($N164=0,$Q164,SUMPRODUCT(($O$157:$O$590=$H164)*($P$157:$P$590=$I164)*$Q$157:$Q$590)+COUNTIFS($H$157:$H164,$H164,$I$157:$I164,$I164,$N$157:$N164,1))) -> 7 | M164: =IF($I164="","",COUNTIF($I$5:$I164,$I164)) -> 7 | N164: =IF($H164="","",IF(OR($H164<>$O164,$I164<>$P164),1,0)) -> 0 | O164: FIN | P164: RTS | Q164: 7 | R164: 200 | S164: 100 | T164: =IF(OR($R164="",$S164="",$S164=0),"",ROUND($R164/$S164,2)) -> 2
A165: 9 | B165: القسائم الشرائية والباقات | C165: Vouchers & Packages | D165: مواد خام | E165: استهلاكي | F165: =IF($H165="","",$H165&"-"&$I165&"-"&TEXT($J165,"000")) -> RAW-CNS-002 | G165: وحدة | H165: =IFERROR(VLOOKUP($D165,القوائم!$A$2:$B$4,2,0),"") -> RAW | I165: =IF($H165="FIN","RTS",IF(ISNUMBER(SEARCH("مجمد",$E165)),"FRZ",IF(ISNUMBER(SEARCH("مبرد",$E165)),"CHL",IF(ISNUMBER(SEARCH("جاف",$E165)),"DRY",IF(ISNUMBER(SEARCH("استهلاك",$E165)),"CNS",IF(ISNUMBER(SEARCH("بيع",$E165)),"RTS","")))))) -> CNS | J165: =IF($H165="","",IF($N165=0,$Q165,SUMPRODUCT(($O$157:$O$590=$H165)*($P$157:$P$590=$I165)*$Q$157:$Q$590)+COUNTIFS($H$157:$H165,$H165,$I$157:$I165,$I165,$N$157:$N165,1))) -> 2 | M165: =IF($I165="","",COUNTIF($I$5:$I165,$I165)) -> 3 | N165: =IF($H165="","",IF(OR($H165<>$O165,$I165<>$P165),1,0)) -> 0 | O165: RAW | P165: CNS | Q165: 2 | T165: =IF(OR($R165="",$S165="",$S165=0),"",ROUND($R165/$S165,2))
A166: 10 | B166: باركا الحلوم | C166: Borek Halloumi | D166: منتج نهائي | E166: جاهز للبيع | F166: =IF($H166="","",$H166&"-"&$I166&"-"&TEXT($J166,"000")) -> FIN-RTS-008 | G166: وحدة | H166: =IFERROR(VLOOKUP($D166,القوائم!$A$2:$B$4,2,0),"") -> FIN | I166: =IF($H166="FIN","RTS",IF(ISNUMBER(SEARCH("مجمد",$E166)),"FRZ",IF(ISNUMBER(SEARCH("مبرد",$E166)),"CHL",IF(ISNUMBER(SEARCH("جاف",$E166)),"DRY",IF(ISNUMBER(SEARCH("استهلاك",$E166)),"CNS",IF(ISNUMBER(SEARCH("بيع",$E166)),"RTS","")))))) -> RTS | J166: =IF($H166="","",IF($N166=0,$Q166,SUMPRODUCT(($O$157:$O$590=$H166)*($P$157:$P$590=$I166)*$Q$157:$Q$590)+COUNTIFS($H$157:$H166,$H166,$I$157:$I166,$I166,$N$157:$N166,1))) -> 8 | M166: =IF($I166="","",COUNTIF($I$5:$I166,$I166)) -> 8 | N166: =IF($H166="","",IF(OR($H166<>$O166,$I166<>$P166),1,0)) -> 0 | O166: FIN | P166: RTS | Q166: 8 | R166: 300 | S166: 100 | T166: =IF(OR($R166="",$S166="",$S166=0),"",ROUND($R166/$S166,2)) -> 3
A167: 11 | B167: باركا المسخن | C167: Borek Musakhan | D167: منتج نهائي | E167: جاهز للبيع | F167: =IF($H167="","",$H167&"-"&$I167&"-"&TEXT($J167,"000")) -> FIN-RTS-009 | G167: وحدة | H167: =IFERROR(VLOOKUP($D167,القوائم!$A$2:$B$4,2,0),"") -> FIN | I167: =IF($H167="FIN","RTS",IF(ISNUMBER(SEARCH("مجمد",$E167)),"FRZ",IF(ISNUMBER(SEARCH("مبرد",$E167)),"CHL",IF(ISNUMBER(SEARCH("جاف",$E167)),"DRY",IF(ISNUMBER(SEARCH("استهلاك",$E167)),"CNS",IF(ISNUMBER(SEARCH("بيع",$E167)),"RTS","")))))) -> RTS | J167: =IF($H167="","",IF($N167=0,$Q167,SUMPRODUCT(($O$157:$O$590=$H167)*($P$157:$P$590=$I167)*$Q$157:$Q$590)+COUNTIFS($H$157:$H167,$H167,$I$157:$I167,$I167,$N$157:$N167,1))) -> 9 | M167: =IF($I167="","",COUNTIF($I$5:$I167,$I167)) -> 9 | N167: =IF($H167="","",IF(OR($H167<>$O167,$I167<>$P167),1,0)) -> 0 | O167: FIN | P167: RTS | Q167: 9 | R167: 290 | S167: 100 | T167: =IF(OR($R167="",$S167="",$S167=0),"",ROUND($R167/$S167,2)) -> 2.9
A168: 12 | B168: باركا حلوم | C168: Borek Halloumi | D168: منتج نهائي | E168: جاهز للبيع | F168: =IF($H168="","",$H168&"-"&$I168&"-"&TEXT($J168,"000")) -> FIN-RTS-010 | G168: وحدة | H168: =IFERROR(VLOOKUP($D168,القوائم!$A$2:$B$4,2,0),"") -> FIN | I168: =IF($H168="FIN","RTS",IF(ISNUMBER(SEARCH("مجمد",$E168)),"FRZ",IF(ISNUMBER(SEARCH("مبرد",$E168)),"CHL",IF(ISNUMBER(SEARCH("جاف",$E168)),"DRY",IF(ISNUMBER(SEARCH("استهلاك",$E168)),"CNS",IF(ISNUMBER(SEARCH("بيع",$E168)),"RTS","")))))) -> RTS | J168: =IF($H168="","",IF($N168=0,$Q168,SUMPRODUCT(($O$157:$O$590=$H168)*($P$157:$P$590=$I168)*$Q$157:$Q$590)+COUNTIFS($H$157:$H168,$H168,$I$157:$I168,$I168,$N$157:$N168,1))) -> 10 | M168: =IF($I168="","",COUNTIF($I$5:$I168,$I168)) -> 10 | N168: =IF($H168="","",IF(OR($H168<>$O168,$I168<>$P168),1,0)) -> 0 | O168: FIN | P168: RTS | Q168: 10 | R168: 300 | S168: 100 | T168: =IF(OR($R168="",$S168="",$S168=0),"",ROUND($R168/$S168,2)) -> 3
A169: 13 | B169: باركا دجاج | C169: Borek Chicken | D169: منتج نهائي | E169: جاهز للبيع | F169: =IF($H169="","",$H169&"-"&$I169&"-"&TEXT($J169,"000")) -> FIN-RTS-011 | G169: وحدة | H169: =IFERROR(VLOOKUP($D169,القوائم!$A$2:$B$4,2,0),"") -> FIN | I169: =IF($H169="FIN","RTS",IF(ISNUMBER(SEARCH("مجمد",$E169)),"FRZ",IF(ISNUMBER(SEARCH("مبرد",$E169)),"CHL",IF(ISNUMBER(SEARCH("جاف",$E169)),"DRY",IF(ISNUMBER(SEARCH("استهلاك",$E169)),"CNS",IF(ISNUMBER(SEARCH("بيع",$E169)),"RTS","")))))) -> RTS | J169: =IF($H169="","",IF($N169=0,$Q169,SUMPRODUCT(($O$157:$O$590=$H169)*($P$157:$P$590=$I169)*$Q$157:$Q$590)+COUNTIFS($H$157:$H169,$H169,$I$157:$I169,$I169,$N$157:$N169,1))) -> 11 | M169: =IF($I169="","",COUNTIF($I$5:$I169,$I169)) -> 11 | N169: =IF($H169="","",IF(OR($H169<>$O169,$I169<>$P169),1,0)) -> 0 | O169: FIN | P169: RTS | Q169: 11 | R169: 280 | S169: 100 | T169: =IF(OR($R169="",$S169="",$S169=0),"",ROUND($R169/$S169,2)) -> 2.8
A170: 14 | B170: باركا مسخن | C170: Borek Musakhan | D170: منتج نهائي | E170: جاهز للبيع | F170: =IF($H170="","",$H170&"-"&$I170&"-"&TEXT($J170,"000")) -> FIN-RTS-012 | G170: وحدة | H170: =IFERROR(VLOOKUP($D170,القوائم!$A$2:$B$4,2,0),"") -> FIN | I170: =IF($H170="FIN","RTS",IF(ISNUMBER(SEARCH("مجمد",$E170)),"FRZ",IF(ISNUMBER(SEARCH("مبرد",$E170)),"CHL",IF(ISNUMBER(SEARCH("جاف",$E170)),"DRY",IF(ISNUMBER(SEARCH("استهلاك",$E170)),"CNS",IF(ISNUMBER(SEARCH("بيع",$E170)),"RTS","")))))) -> RTS | J170: =IF($H170="","",IF($N170=0,$Q170,SUMPRODUCT(($O$157:$O$590=$H170)*($P$157:$P$590=$I170)*$Q$157:$Q$590)+COUNTIFS($H$157:$H170,$H170,$I$157:$I170,$I170,$N$157:$N170,1))) -> 12 | M170: =IF($I170="","",COUNTIF($I$5:$I170,$I170)) -> 12 | N170: =IF($H170="","",IF(OR($H170<>$O170,$I170<>$P170),1,0)) -> 0 | O170: FIN | P170: RTS | Q170: 12 | R170: 290 | S170: 100 | T170: =IF(OR($R170="",$S170="",$S170=0),"",ROUND($R170/$S170,2)) -> 2.9
A171: 15 | B171: باستا الفريدو | C171: Alfredo Pasta | D171: منتج نهائي | E171: جاهز للبيع | F171: =IF($H171="","",$H171&"-"&$I171&"-"&TEXT($J171,"000")) -> FIN-RTS-013 | G171: وحدة | H171: =IFERROR(VLOOKUP($D171,القوائم!$A$2:$B$4,2,0),"") -> FIN | I171: =IF($H171="FIN","RTS",IF(ISNUMBER(SEARCH("مجمد",$E171)),"FRZ",IF(ISNUMBER(SEARCH("مبرد",$E171)),"CHL",IF(ISNUMBER(SEARCH("جاف",$E171)),"DRY",IF(ISNUMBER(SEARCH("استهلاك",$E171)),"CNS",IF(ISNUMBER(SEARCH("بيع",$E171)),"RTS","")))))) -> RTS | J171: =IF($H171="","",IF($N171=0,$Q171,SUMPRODUCT(($O$157:$O$590=$H171)*($P$157:$P$590=$I171)*$Q$157:$Q$590)+COUNTIFS($H$157:$H171,$H171,$I$157:$I171,$I171,$N$157:$N171,1))) -> 13 | M171: =IF($I171="","",COUNTIF($I$5:$I171,$I171)) -> 13 | N171: =IF($H171="","",IF(OR($H171<>$O171,$I171<>$P171),1,0)) -> 0 | O171: FIN | P171: RTS | Q171: 13 | R171: 200 | S171: 100 | T171: =IF(OR($R171="",$S171="",$S171=0),"",ROUND($R171/$S171,2)) -> 2
A172: 16 | B172: باستا بيستو | C172: Pesto Pasta | D172: منتج نهائي | E172: جاهز للبيع | F172: =IF($H172="","",$H172&"-"&$I172&"-"&TEXT($J172,"000")) -> FIN-RTS-014 | G172: وحدة | H172: =IFERROR(VLOOKUP($D172,القوائم!$A$2:$B$4,2,0),"") -> FIN | I172: =IF($H172="FIN","RTS",IF(ISNUMBER(SEARCH("مجمد",$E172)),"FRZ",IF(ISNUMBER(SEARCH("مبرد",$E172)),"CHL",IF(ISNUMBER(SEARCH("جاف",$E172)),"DRY",IF(ISNUMBER(SEARCH("استهلاك",$E172)),"CNS",IF(ISNUMBER(SEARCH("بيع",$E172)),"RTS","")))))) -> RTS | J172: =IF($H172="","",IF($N172=0,$Q172,SUMPRODUCT(($O$157:$O$590=$H172)*($P$157:$P$590=$I172)*$Q$157:$Q$590)+COUNTIFS($H$157:$H172,$H172,$I$157:$I172,$I172,$N$157:$N172,1))) -> 14 | M172: =IF($I172="","",COUNTIF($I$5:$I172,$I172)) -> 14 | N172: =IF($H172="","",IF(OR($H172<>$O172,$I172<>$P172),1,0)) -> 0 | O172: FIN | P172: RTS | Q172: 14 | R172: 250 | S172: 100 | T172: =IF(OR($R172="",$S172="",$S172=0),"",ROUND($R172/$S172,2)) -> 2.5
A173: 17 | B173: باستا بيستو خالي من الجلوتين | C173: Pesto Gluten-Free Pasta | D173: منتج نهائي | E173: جاهز للبيع | F173: =IF($H173="","",$H173&"-"&$I173&"-"&TEXT($J173,"000")) -> FIN-RTS-015 | G173: وحدة | H173: =IFERROR(VLOOKUP($D173,القوائم!$A$2:$B$4,2,0),"") -> FIN | I173: =IF($H173="FIN","RTS",IF(ISNUMBER(SEARCH("مجمد",$E173)),"FRZ",IF(ISNUMBER(SEARCH("مبرد",$E173)),"CHL",IF(ISNUMBER(SEARCH("جاف",$E173)),"DRY",IF(ISNUMBER(SEARCH("استهلاك",$E173)),"CNS",IF(ISNUMBER(SEARCH("بيع",$E173)),"RTS","")))))) -> RTS | J173: =IF($H173="","",IF($N173=0,$Q173,SUMPRODUCT(($O$157:$O$590=$H173)*($P$157:$P$590=$I173)*$Q$157:$Q$590)+COUNTIFS($H$157:$H173,$H173,$I$157:$I173,$I173,$N$157:$N173,1))) -> 15 | M173: =IF($I173="","",COUNTIF($I$5:$I173,$I173)) -> 15 | N173: =IF($H173="","",IF(OR($H173<>$O173,$I173<>$P173),1,0)) -> 0 | O173: FIN | P173: RTS | Q173: 15 | R173: 250 | S173: 100 | T173: =IF(OR($R173="",$S173="",$S173=0),"",ROUND($R173/$S173,2)) -> 2.5
A174: 18 | B174: باستا بيني روزيه | C174: Penne Rose Pasta | D174: منتج نهائي | E174: جاهز للبيع | F174: =IF($H174="","",$H174&"-"&$I174&"-"&TEXT($J174,"000")) -> FIN-RTS-016 | G174: وحدة | H174: =IFERROR(VLOOKUP($D174,القوائم!$A$2:$B$4,2,0),"") -> FIN | I174: =IF($H174="FIN","RTS",IF(ISNUMBER(SEARCH("مجمد",$E174)),"FRZ",IF(ISNUMBER(SEARCH("مبرد",$E174)),"CHL",IF(ISNUMBER(SEARCH("جاف",$E174)),"DRY",IF(ISNUMBER(SEARCH("استهلاك",$E174)),"CNS",IF(ISNUMBER(SEARCH("بيع",$E174)),"RTS","")))))) -> RTS | J174: =IF($H174="","",IF($N174=0,$Q174,SUMPRODUCT(($O$157:$O$590=$H174)*($P$157:$P$590=$I174)*$Q$157:$Q$590)+COUNTIFS($H$157:$H174,$H174,$I$157:$I174,$I174,$N$157:$N174,1))) -> 16 | M174: =IF($I174="","",COUNTIF($I$5:$I174,$I174)) -> 16 | N174: =IF($H174="","",IF(OR($H174<>$O174,$I174<>$P174),1,0)) -> 0 | O174: FIN | P174: RTS | Q174: 16 | R174: 175 | S174: 100 | T174: =IF(OR($R174="",$S174="",$S174=0),"",ROUND($R174/$S174,2)) -> 1.75
A175: 19 | B175: باستا تاغلتيلي | C175: Tagliatelle Pasta | D175: منتج نهائي | E175: جاهز للبيع | F175: =IF($H175="","",$H175&"-"&$I175&"-"&TEXT($J175,"000")) -> FIN-RTS-017 | G175: وحدة | H175: =IFERROR(VLOOKUP($D175,القوائم!$A$2:$B$4,2,0),"") -> FIN | I175: =IF($H175="FIN","RTS",IF(ISNUMBER(SEARCH("مجمد",$E175)),"FRZ",IF(ISNUMBER(SEARCH("مبرد",$E175)),"CHL",IF(ISNUMBER(SEARCH("جاف",$E175)),"DRY",IF(ISNUMBER(SEARCH("استهلاك",$E175)),"CNS",IF(ISNUMBER(SEARCH("بيع",$E175)),"RTS","")))))) -> RTS | J175: =IF($H175="","",IF($N175=0,$Q175,SUMPRODUCT(($O$157:$O$590=$H175)*($P$157:$P$590=$I175)*$Q$157:$Q$590)+COUNTIFS($H$157:$H175,$H175,$I$157:$I175,$I175,$N$157:$N175,1))) -> 17 | M175: =IF($I175="","",COUNTIF($I$5:$I175,$I175)) -> 17 | N175: =IF($H175="","",IF(OR($H175<>$O175,$I175<>$P175),1,0)) -> 0 | O175: FIN | P175: RTS | Q175: 17 | R175: 200 | S175: 100 | T175: =IF(OR($R175="",$S175="",$S175=0),"",ROUND($R175/$S175,2)) -> 2
A176: 20 | B176: باستا ترافل خالي من الجلوتين | C176: Truffle Gluten-Free Pasta | D176: منتج نهائي | E176: جاهز للبيع | F176: =IF($H176="","",$H176&"-"&$I176&"-"&TEXT($J176,"000")) -> FIN-RTS-018 | G176: وحدة | H176: =IFERROR(VLOOKUP($D176,القوائم!$A$2:$B$4,2,0),"") -> FIN | I176: =IF($H176="FIN","RTS",IF(ISNUMBER(SEARCH("مجمد",$E176)),"FRZ",IF(ISNUMBER(SEARCH("مبرد",$E176)),"CHL",IF(ISNUMBER(SEARCH("جاف",$E176)),"DRY",IF(ISNUMBER(SEARCH("استهلاك",$E176)),"CNS",IF(ISNUMBER(SEARCH("بيع",$E176)),"RTS","")))))) -> RTS | J176: =IF($H176="","",IF($N176=0,$Q176,SUMPRODUCT(($O$157:$O$590=$H176)*($P$157:$P$590=$I176)*$Q$157:$Q$590)+COUNTIFS($H$157:$H176,$H176,$I$157:$I176,$I176,$N$157:$N176,1))) -> 18 | M176: =IF($I176="","",COUNTIF($I$5:$I176,$I176)) -> 18 | N176: =IF($H176="","",IF(OR($H176<>$O176,$I176<>$P176),1,0)) -> 0 | O176: FIN | P176: RTS | Q176: 18 | R176: 220 | S176: 100 | T176: =IF(OR($R176="",$S176="",$S176=0),"",ROUND($R176/$S176,2)) -> 2.2
A177: 21 | B177: باستا روزيه خالي من الجلوتين | C177: Rose Gluten-Free Pasta | D177: منتج نهائي | E177: جاهز للبيع | F177: =IF($H177="","",$H177&"-"&$I177&"-"&TEXT($J177,"000")) -> FIN-RTS-019 | G177: وحدة | H177: =IFERROR(VLOOKUP($D177,القوائم!$A$2:$B$4,2,0),"") -> FIN | I177: =IF($H177="FIN","RTS",IF(ISNUMBER(SEARCH("مجمد",$E177)),"FRZ",IF(ISNUMBER(SEARCH("مبرد",$E177)),"CHL",IF(ISNUMBER(SEARCH("جاف",$E177)),"DRY",IF(ISNUMBER(SEARCH("استهلاك",$E177)),"CNS",IF(ISNUMBER(SEARCH("بيع",$E177)),"RTS","")))))) -> RTS | J177: =IF($H177="","",IF($N177=0,$Q177,SUMPRODUCT(($O$157:$O$590=$H177)*($P$157:$P$590=$I177)*$Q$157:$Q$590)+COUNTIFS($H$157:$H177,$H177,$I$157:$I177,$I177,$N$157:$N177,1))) -> 19 | M177: =IF($I177="","",COUNTIF($I$5:$I177,$I177)) -> 19 | N177: =IF($H177="","",IF(OR($H177<>$O177,$I177<>$P177),1,0)) -> 0 | O177: FIN | P177: RTS | Q177: 19 | R177: 175 | S177: 100 | T177: =IF(OR($R177="",$S177="",$S177=0),"",ROUND($R177/$S177,2)) -> 1.75
... A218: 62 | B218: تمر الافطار | C218: Iftar Dates | D218: مواد خام | E218: استهلاكي | F218: =IF($H218="","",$H218&"-"&$I218&"-"&TEXT($J218,"000")) -> RAW-CNS-003 | G218: وحدة | H218: =IFERROR(VLOOKUP($D218,القوائم!$A$2:$B$4,2,0),"") -> RAW | I218: =IF($H218="FIN","RTS",IF(ISNUMBER(SEARCH("مجمد",$E218)),"FRZ",IF(ISNUMBER(SEARCH("مبرد",$E218)),"CHL",IF(ISNUMBER(SEARCH("جاف",$E218)),"DRY",IF(ISNUMBER(SEARCH("استهلاك",$E218)),"CNS",IF(ISNUMBER(SEARCH("بيع",$E218)),"RTS","")))))) -> CNS | J218: =IF($H218="","",IF($N218=0,$Q218,SUMPRODUCT(($O$157:$O$590=$H218)*($P$157:$P$590=$I218)*$Q$157:$Q$590)+COUNTIFS($H$157:$H218,$H218,$I$157:$I218,$I218,$N$157:$N218,1))) -> 3 | M218: =IF($I218="","",COUNTIF($I$5:$I218,$I218)) -> 4 | N218: =IF($H218="","",IF(OR($H218<>$O218,$I218<>$P218),1,0)) -> 0 | O218: RAW | P218: CNS | Q218: 3 | R218: 282 | S218: 100 | T218: =IF(OR($R218="",$S218="",$S218=0),"",ROUND($R218/$S218,2)) -> 2.82
A219: 63 | B219: توصيل طلبيات | C219: Order Delivery | D219: مواد خام | E219: استهلاكي | F219: =IF($H219="","",$H219&"-"&$I219&"-"&TEXT($J219,"000")) -> RAW-CNS-004 | G219: وحدة | H219: =IFERROR(VLOOKUP($D219,القوائم!$A$2:$B$4,2,0),"") -> RAW | I219: =IF($H219="FIN","RTS",IF(ISNUMBER(SEARCH("مجمد",$E219)),"FRZ",IF(ISNUMBER(SEARCH("مبرد",$E219)),"CHL",IF(ISNUMBER(SEARCH("جاف",$E219)),"DRY",IF(ISNUMBER(SEARCH("استهلاك",$E219)),"CNS",IF(ISNUMBER(SEARCH("بيع",$E219)),"RTS","")))))) -> CNS | J219: =IF($H219="","",IF($N219=0,$Q219,SUMPRODUCT(($O$157:$O$590=$H219)*($P$157:$P$590=$I219)*$Q$157:$Q$590)+COUNTIFS($H$157:$H219,$H219,$I$157:$I219,$I219,$N$157:$N219,1))) -> 4 | M219: =IF($I219="","",COUNTIF($I$5:$I219,$I219)) -> 5 | N219: =IF($H219="","",IF(OR($H219<>$O219,$I219<>$P219),1,0)) -> 0 | O219: RAW | P219: CNS | Q219: 4 | T219: =IF(OR($R219="",$S219="",$S219=0),"",ROUND($R219/$S219,2))
A220: 64 | B220: توصيل عجين فطائر | C220: Pastry Dough Delivery | D220: مواد خام | E220: استهلاكي | F220: =IF($H220="","",$H220&"-"&$I220&"-"&TEXT($J220,"000")) -> RAW-CNS-005 | G220: وحدة | H220: =IFERROR(VLOOKUP($D220,القوائم!$A$2:$B$4,2,0),"") -> RAW | I220: =IF($H220="FIN","RTS",IF(ISNUMBER(SEARCH("مجمد",$E220)),"FRZ",IF(ISNUMBER(SEARCH("مبرد",$E220)),"CHL",IF(ISNUMBER(SEARCH("جاف",$E220)),"DRY",IF(ISNUMBER(SEARCH("استهلاك",$E220)),"CNS",IF(ISNUMBER(SEARCH("بيع",$E220)),"RTS","")))))) -> CNS | J220: =IF($H220="","",IF($N220=0,$Q220,SUMPRODUCT(($O$157:$O$590=$H220)*($P$157:$P$590=$I220)*$Q$157:$Q$590)+COUNTIFS($H$157:$H220,$H220,$I$157:$I220,$I220,$N$157:$N220,1))) -> 5 | M220: =IF($I220="","",COUNTIF($I$5:$I220,$I220)) -> 6 | N220: =IF($H220="","",IF(OR($H220<>$O220,$I220<>$P220),1,0)) -> 0 | O220: RAW | P220: CNS | Q220: 5 | T220: =IF(OR($R220="",$S220="",$S220=0),"",ROUND($R220/$S220,2))
A221: 65 | B221: تيراميسو بينو سفري | C221: Tiramisu Pino Takeaway | D221: منتج نهائي | E221: جاهز للبيع | F221: =IF($H221="","",$H221&"-"&$I221&"-"&TEXT($J221,"000")) -> FIN-RTS-057 | G221: وحدة | H221: =IFERROR(VLOOKUP($D221,القوائم!$A$2:$B$4,2,0),"") -> FIN | I221: =IF($H221="FIN","RTS",IF(ISNUMBER(SEARCH("مجمد",$E221)),"FRZ",IF(ISNUMBER(SEARCH("مبرد",$E221)),"CHL",IF(ISNUMBER(SEARCH("جاف",$E221)),"DRY",IF(ISNUMBER(SEARCH("استهلاك",$E221)),"CNS",IF(ISNUMBER(SEARCH("بيع",$E221)),"RTS","")))))) -> RTS | J221: =IF($H221="","",IF($N221=0,$Q221,SUMPRODUCT(($O$157:$O$590=$H221)*($P$157:$P$590=$I221)*$Q$157:$Q$590)+COUNTIFS($H$157:$H221,$H221,$I$157:$I221,$I221,$N$157:$N221,1))) -> 57 | M221: =IF($I221="","",COUNTIF($I$5:$I221,$I221)) -> 57 | N221: =IF($H221="","",IF(OR($H221<>$O221,$I221<>$P221),1,0)) -> 0 | O221: FIN | P221: RTS | Q221: 57 | R221: 290 | S221: 100 | T221: =IF(OR($R221="",$S221="",$S221=0),"",ROUND($R221/$S221,2)) -> 2.9
A222: 66 | B222: تيراميسو محلي | C222: Tiramisu Local | D222: منتج نهائي | E222: جاهز للبيع | F222: =IF($H222="","",$H222&"-"&$I222&"-"&TEXT($J222,"000")) -> FIN-RTS-058 | G222: وحدة | H222: =IFERROR(VLOOKUP($D222,القوائم!$A$2:$B$4,2,0),"") -> FIN | I222: =IF($H222="FIN","RTS",IF(ISNUMBER(SEARCH("مجمد",$E222)),"FRZ",IF(ISNUMBER(SEARCH("مبرد",$E222)),"CHL",IF(ISNUMBER(SEARCH("جاف",$E222)),"DRY",IF(ISNUMBER(SEARCH("استهلاك",$E222)),"CNS",IF(ISNUMBER(SEARCH("بيع",$E222)),"RTS","")))))) -> RTS | J222: =IF($H222="","",IF($N222=0,$Q222,SUMPRODUCT(($O$157:$O$590=$H222)*($P$157:$P$590=$I222)*$Q$157:$Q$590)+COUNTIFS($H$157:$H222,$H222,$I$157:$I222,$I222,$N$157:$N222,1))) -> 58 | M222: =IF($I222="","",COUNTIF($I$5:$I222,$I222)) -> 58 | N222: =IF($H222="","",IF(OR($H222<>$O222,$I222<>$P222),1,0)) -> 0 | O222: FIN | P222: RTS | Q222: 58 | R222: 290 | S222: 100 | T222: =IF(OR($R222="",$S222="",$S222=0),"",ROUND($R222/$S222,2)) -> 2.9
A223: 67 | B223: تين | C223: Fig | D223: مواد خام | E223: تخزين مبرد | F223: =IF($H223="","",$H223&"-"&$I223&"-"&TEXT($J223,"000")) -> RAW-CHL-001 | G223: كيلو | H223: =IFERROR(VLOOKUP($D223,القوائم!$A$2:$B$4,2,0),"") -> RAW | I223: =IF($H223="FIN","RTS",IF(ISNUMBER(SEARCH("مجمد",$E223)),"FRZ",IF(ISNUMBER(SEARCH("مبرد",$E223)),"CHL",IF(ISNUMBER(SEARCH("جاف",$E223)),"DRY",IF(ISNUMBER(SEARCH("استهلاك",$E223)),"CNS",IF(ISNUMBER(SEARCH("بيع",$E223)),"RTS","")))))) -> CHL | J223: =IF($H223="","",IF($N223=0,$Q223,SUMPRODUCT(($O$157:$O$590=$H223)*($P$157:$P$590=$I223)*$Q$157:$Q$590)+COUNTIFS($H$157:$H223,$H223,$I$157:$I223,$I223,$N$157:$N223,1))) -> 1 | M223: =IF($I223="","",COUNTIF($I$5:$I223,$I223)) -> 4 | N223: =IF($H223="","",IF(OR($H223<>$O223,$I223<>$P223),1,0)) -> 0 | O223: RAW | P223: CHL | Q223: 1 | R223: 74 | S223: 100 | T223: =IF(OR($R223="",$S223="",$S223=0),"",ROUND($R223/$S223,2)) -> 0.74
A224: 68 | B224: خبز الشباتا | C224: Ciabatta Bread | D224: منتج نهائي | E224: جاهز للبيع | F224: =IF($H224="","",$H224&"-"&$I224&"-"&TEXT($J224,"000")) -> FIN-RTS-059 | G224: وحدة | H224: =IFERROR(VLOOKUP($D224,القوائم!$A$2:$B$4,2,0),"") -> FIN | I224: =IF($H224="FIN","RTS",IF(ISNUMBER(SEARCH("مجمد",$E224)),"FRZ",IF(ISNUMBER(SEARCH("مبرد",$E224)),"CHL",IF(ISNUMBER(SEARCH("جاف",$E224)),"DRY",IF(ISNUMBER(SEARCH("استهلاك",$E224)),"CNS",IF(ISNUMBER(SEARCH("بيع",$E224)),"RTS","")))))) -> RTS | J224: =IF($H224="","",IF($N224=0,$Q224,SUMPRODUCT(($O$157:$O$590=$H224)*($P$157:$P$590=$I224)*$Q$157:$Q$590)+COUNTIFS($H$157:$H224,$H224,$I$157:$I224,$I224,$N$157:$N224,1))) -> 59 | M224: =IF($I224="","",COUNTIF($I$5:$I224,$I224)) -> 59 | N224: =IF($H224="","",IF(OR($H224<>$O224,$I224<>$P224),1,0)) -> 0 | O224: FIN | P224: RTS | Q224: 59 | R224: 270 | S224: 100 | T224: =IF(OR($R224="",$S224="",$S224=0),"",ROUND($R224/$S224,2)) -> 2.7
A225: 69 | B225: خليط الكينوا | C225: Quinoa Mix | D225: مواد تحويلية | E225: تخزين مبرد | F225: =IF($H225="","",$H225&"-"&$I225&"-"&TEXT($J225,"000")) -> TRN-CHL-004 | G225: كيلو | H225: =IFERROR(VLOOKUP($D225,القوائم!$A$2:$B$4,2,0),"") -> TRN | I225: =IF($H225="FIN","RTS",IF(ISNUMBER(SEARCH("مجمد",$E225)),"FRZ",IF(ISNUMBER(SEARCH("مبرد",$E225)),"CHL",IF(ISNUMBER(SEARCH("جاف",$E225)),"DRY",IF(ISNUMBER(SEARCH("استهلاك",$E225)),"CNS",IF(ISNUMBER(SEARCH("بيع",$E225)),"RTS","")))))) -> CHL | J225: =IF($H225="","",IF($N225=0,$Q225,SUMPRODUCT(($O$157:$O$590=$H225)*($P$157:$P$590=$I225)*$Q$157:$Q$590)+COUNTIFS($H$157:$H225,$H225,$I$157:$I225,$I225,$N$157:$N225,1))) -> 4 | M225: =IF($I225="","",COUNTIF($I$5:$I225,$I225)) -> 5 | N225: =IF($H225="","",IF(OR($H225<>$O225,$I225<>$P225),1,0)) -> 0 | O225: TRN | P225: CHL | Q225: 4 | R225: 120 | S225: 100 | T225: =IF(OR($R225="",$S225="",$S225=0),"",ROUND($R225/$S225,2)) -> 1.2
A226: 70 | B226: ريجاتوني باستا خالي من الجلوتين | C226: Pasta Gluten-Free Rigatoni | D226: منتج نهائي | E226: جاهز للبيع | F226: =IF($H226="","",$H226&"-"&$I226&"-"&TEXT($J226,"000")) -> FIN-RTS-060 | G226: وحدة | H226: =IFERROR(VLOOKUP($D226,القوائم!$A$2:$B$4,2,0),"") -> FIN | I226: =IF($H226="FIN","RTS",IF(ISNUMBER(SEARCH("مجمد",$E226)),"FRZ",IF(ISNUMBER(SEARCH("مبرد",$E226)),"CHL",IF(ISNUMBER(SEARCH("جاف",$E226)),"DRY",IF(ISNUMBER(SEARCH("استهلاك",$E226)),"CNS",IF(ISNUMBER(SEARCH("بيع",$E226)),"RTS","")))))) -> RTS | J226: =IF($H226="","",IF($N226=0,$Q226,SUMPRODUCT(($O$157:$O$590=$H226)*($P$157:$P$590=$I226)*$Q$157:$Q$590)+COUNTIFS($H$157:$H226,$H226,$I$157:$I226,$I226,$N$157:$N226,1))) -> 60 | M226: =IF($I226="","",COUNTIF($I$5:$I226,$I226)) -> 60 | N226: =IF($H226="","",IF(OR($H226<>$O226,$I226<>$P226),1,0)) -> 0 | O226: FIN | P226: RTS | Q226: 60 | R226: 180 | S226: 100 | T226: =IF(OR($R226="",$S226="",$S226=0),"",ROUND($R226/$S226,2)) -> 1.8
A227: 71 | B227: ريجاتوني ترافل | C227: Truffle Rigatoni | D227: منتج نهائي | E227: جاهز للبيع | F227: =IF($H227="","",$H227&"-"&$I227&"-"&TEXT($J227,"000")) -> FIN-RTS-061 | G227: وحدة | H227: =IFERROR(VLOOKUP($D227,القوائم!$A$2:$B$4,2,0),"") -> FIN | I227: =IF($H227="FIN","RTS",IF(ISNUMBER(SEARCH("مجمد",$E227)),"FRZ",IF(ISNUMBER(SEARCH("مبرد",$E227)),"CHL",IF(ISNUMBER(SEARCH("جاف",$E227)),"DRY",IF(ISNUMBER(SEARCH("استهلاك",$E227)),"CNS",IF(ISNUMBER(SEARCH("بيع",$E227)),"RTS","")))))) -> RTS | J227: =IF($H227="","",IF($N227=0,$Q227,SUMPRODUCT(($O$157:$O$590=$H227)*($P$157:$P$590=$I227)*$Q$157:$Q$590)+COUNTIFS($H$157:$H227,$H227,$I$157:$I227,$I227,$N$157:$N227,1))) -> 61 | M227: =IF($I227="","",COUNTIF($I$5:$I227,$I227)) -> 61 | N227: =IF($H227="","",IF(OR($H227<>$O227,$I227<>$P227),1,0)) -> 0 | O227: FIN | P227: RTS | Q227: 61 | R227: 220 | S227: 100 | T227: =IF(OR($R227="",$S227="",$S227=0),"",ROUND($R227/$S227,2)) -> 2.2
A228: 72 | B228: ريجاتوني روزيه باستا | C228: Rose Pasta Rigatoni | D228: منتج نهائي | E228: جاهز للبيع | F228: =IF($H228="","",$H228&"-"&$I228&"-"&TEXT($J228,"000")) -> FIN-RTS-062 | G228: وحدة | H228: =IFERROR(VLOOKUP($D228,القوائم!$A$2:$B$4,2,0),"") -> FIN | I228: =IF($H228="FIN","RTS",IF(ISNUMBER(SEARCH("مجمد",$E228)),"FRZ",IF(ISNUMBER(SEARCH("مبرد",$E228)),"CHL",IF(ISNUMBER(SEARCH("جاف",$E228)),"DRY",IF(ISNUMBER(SEARCH("استهلاك",$E228)),"CNS",IF(ISNUMBER(SEARCH("بيع",$E228)),"RTS","")))))) -> RTS | J228: =IF($H228="","",IF($N228=0,$Q228,SUMPRODUCT(($O$157:$O$590=$H228)*($P$157:$P$590=$I228)*$Q$157:$Q$590)+COUNTIFS($H$157:$H228,$H228,$I$157:$I228,$I228,$N$157:$N228,1))) -> 62 | M228: =IF($I228="","",COUNTIF($I$5:$I228,$I228)) -> 62 | N228: =IF($H228="","",IF(OR($H228<>$O228,$I228<>$P228),1,0)) -> 0 | O228: FIN | P228: RTS | Q228: 62 | R228: 175 | S228: 100 | T228: =IF(OR($R228="",$S228="",$S228=0),"",ROUND($R228/$S228,2)) -> 1.75
A229: 73 | B229: ساوردو الحبة الكاملة | C229: Whole Sourdough | D229: منتج نهائي | E229: جاهز للبيع | F229: =IF($H229="","",$H229&"-"&$I229&"-"&TEXT($J229,"000")) -> FIN-RTS-063 | G229: وحدة | H229: =IFERROR(VLOOKUP($D229,القوائم!$A$2:$B$4,2,0),"") -> FIN | I229: =IF($H229="FIN","RTS",IF(ISNUMBER(SEARCH("مجمد",$E229)),"FRZ",IF(ISNUMBER(SEARCH("مبرد",$E229)),"CHL",IF(ISNUMBER(SEARCH("جاف",$E229)),"DRY",IF(ISNUMBER(SEARCH("استهلاك",$E229)),"CNS",IF(ISNUMBER(SEARCH("بيع",$E229)),"RTS","")))))) -> RTS | J229: =IF($H229="","",IF($N229=0,$Q229,SUMPRODUCT(($O$157:$O$590=$H229)*($P$157:$P$590=$I229)*$Q$157:$Q$590)+COUNTIFS($H$157:$H229,$H229,$I$157:$I229,$I229,$N$157:$N229,1))) -> 63 | M229: =IF($I229="","",COUNTIF($I$5:$I229,$I229)) -> 63 | N229: =IF($H229="","",IF(OR($H229<>$O229,$I229<>$P229),1,0)) -> 0 | O229: FIN | P229: RTS | Q229: 63 | R229: 250 | S229: 100 | T229: =IF(OR($R229="",$S229="",$S229=0),"",ROUND($R229/$S229,2)) -> 2.5
A230: 74 | B230: ساوردو الزيتون مع الجبنة | C230: Olive Cheese Sourdough | D230: منتج نهائي | E230: جاهز للبيع | F230: =IF($H230="","",$H230&"-"&$I230&"-"&TEXT($J230,"000")) -> FIN-RTS-064 | G230: وحدة | H230: =IFERROR(VLOOKUP($D230,القوائم!$A$2:$B$4,2,0),"") -> FIN | I230: =IF($H230="FIN","RTS",IF(ISNUMBER(SEARCH("مجمد",$E230)),"FRZ",IF(ISNUMBER(SEARCH("مبرد",$E230)),"CHL",IF(ISNUMBER(SEARCH("جاف",$E230)),"DRY",IF(ISNUMBER(SEARCH("استهلاك",$E230)),"CNS",IF(ISNUMBER(SEARCH("بيع",$E230)),"RTS","")))))) -> RTS | J230: =IF($H230="","",IF($N230=0,$Q230,SUMPRODUCT(($O$157:$O$590=$H230)*($P$157:$P$590=$I230)*$Q$157:$Q$590)+COUNTIFS($H$157:$H230,$H230,$I$157:$I230,$I230,$N$157:$N230,1))) -> 64 | M230: =IF($I230="","",COUNTIF($I$5:$I230,$I230)) -> 64 | N230: =IF($H230="","",IF(OR($H230<>$O230,$I230<>$P230),1,0)) -> 0 | O230: FIN | P230: RTS | Q230: 64 | R230: 290 | S230: 100 | T230: =IF(OR($R230="",$S230="",$S230=0),"",ROUND($R230/$S230,2)) -> 2.9
A231: 75 | B231: ساوردو الطماطم المجففة | C231: Tomato Sourdough | D231: منتج نهائي | E231: جاهز للبيع | F231: =IF($H231="","",$H231&"-"&$I231&"-"&TEXT($J231,"000")) -> FIN-RTS-065 | G231: وحدة | H231: =IFERROR(VLOOKUP($D231,القوائم!$A$2:$B$4,2,0),"") -> FIN | I231: =IF($H231="FIN","RTS",IF(ISNUMBER(SEARCH("مجمد",$E231)),"FRZ",IF(ISNUMBER(SEARCH("مبرد",$E231)),"CHL",IF(ISNUMBER(SEARCH("جاف",$E231)),"DRY",IF(ISNUMBER(SEARCH("استهلاك",$E231)),"CNS",IF(ISNUMBER(SEARCH("بيع",$E231)),"RTS","")))))) -> RTS | J231: =IF($H231="","",IF($N231=0,$Q231,SUMPRODUCT(($O$157:$O$590=$H231)*($P$157:$P$590=$I231)*$Q$157:$Q$590)+COUNTIFS($H$157:$H231,$H231,$I$157:$I231,$I231,$N$157:$N231,1))) -> 65 | M231: =IF($I231="","",COUNTIF($I$5:$I231,$I231)) -> 65 | N231: =IF($H231="","",IF(OR($H231<>$O231,$I231<>$P231),1,0)) -> 0 | O231: FIN | P231: RTS | Q231: 65 | R231: 260 | S231: 100 | T231: =IF(OR($R231="",$S231="",$S231=0),"",ROUND($R231/$S231,2)) -> 2.6
A232: 76 | B232: ساوردو الفلفل الحار | C232: Pepper Spicy Sourdough | D232: منتج نهائي | E232: جاهز للبيع | F232: =IF($H232="","",$H232&"-"&$I232&"-"&TEXT($J232,"000")) -> FIN-RTS-066 | G232: وحدة | H232: =IFERROR(VLOOKUP($D232,القوائم!$A$2:$B$4,2,0),"") -> FIN | I232: =IF($H232="FIN","RTS",IF(ISNUMBER(SEARCH("مجمد",$E232)),"FRZ",IF(ISNUMBER(SEARCH("مبرد",$E232)),"CHL",IF(ISNUMBER(SEARCH("جاف",$E232)),"DRY",IF(ISNUMBER(SEARCH("استهلاك",$E232)),"CNS",IF(ISNUMBER(SEARCH("بيع",$E232)),"RTS","")))))) -> RTS | J232: =IF($H232="","",IF($N232=0,$Q232,SUMPRODUCT(($O$157:$O$590=$H232)*($P$157:$P$590=$I232)*$Q$157:$Q$590)+COUNTIFS($H$157:$H232,$H232,$I$157:$I232,$I232,$N$157:$N232,1))) -> 66 | M232: =IF($I232="","",COUNTIF($I$5:$I232,$I232)) -> 66 | N232: =IF($H232="","",IF(OR($H232<>$O232,$I232<>$P232),1,0)) -> 0 | O232: FIN | P232: RTS | Q232: 66 | R232: 260 | S232: 100 | T232: =IF(OR($R232="",$S232="",$S232=0),"",ROUND($R232/$S232,2)) -> 2.6
... A266: 110 | B266: ماري مونتي باستا خالي من الجلوتين | C266: Mari Monti Pasta Gluten-Free | D266: منتج نهائي | E266: جاهز للبيع | F266: =IF($H266="","",$H266&"-"&$I266&"-"&TEXT($J266,"000")) -> FIN-RTS-096 | G266: وحدة | H266: =IFERROR(VLOOKUP($D266,القوائم!$A$2:$B$4,2,0),"") -> FIN | I266: =IF($H266="FIN","RTS",IF(ISNUMBER(SEARCH("مجمد",$E266)),"FRZ",IF(ISNUMBER(SEARCH("مبرد",$E266)),"CHL",IF(ISNUMBER(SEARCH("جاف",$E266)),"DRY",IF(ISNUMBER(SEARCH("استهلاك",$E266)),"CNS",IF(ISNUMBER(SEARCH("بيع",$E266)),"RTS","")))))) -> RTS | J266: =IF($H266="","",IF($N266=0,$Q266,SUMPRODUCT(($O$157:$O$590=$H266)*($P$157:$P$590=$I266)*$Q$157:$Q$590)+COUNTIFS($H$157:$H266,$H266,$I$157:$I266,$I266,$N$157:$N266,1))) -> 96 | M266: =IF($I266="","",COUNTIF($I$5:$I266,$I266)) -> 96 | N266: =IF($H266="","",IF(OR($H266<>$O266,$I266<>$P266),1,0)) -> 0 | O266: FIN | P266: RTS | Q266: 96 | R266: 180 | S266: 100 | T266: =IF(OR($R266="",$S266="",$S266=0),"",ROUND($R266/$S266,2)) -> 1.8
A267: 111 | B267: مبيعات عجين فطائر | C267: Pastry Dough Sales | D267: مواد خام | E267: استهلاكي | F267: =IF($H267="","",$H267&"-"&$I267&"-"&TEXT($J267,"000")) -> RAW-CNS-006 | G267: وحدة | H267: =IFERROR(VLOOKUP($D267,القوائم!$A$2:$B$4,2,0),"") -> RAW | I267: =IF($H267="FIN","RTS",IF(ISNUMBER(SEARCH("مجمد",$E267)),"FRZ",IF(ISNUMBER(SEARCH("مبرد",$E267)),"CHL",IF(ISNUMBER(SEARCH("جاف",$E267)),"DRY",IF(ISNUMBER(SEARCH("استهلاك",$E267)),"CNS",IF(ISNUMBER(SEARCH("بيع",$E267)),"RTS","")))))) -> CNS | J267: =IF($H267="","",IF($N267=0,$Q267,SUMPRODUCT(($O$157:$O$590=$H267)*($P$157:$P$590=$I267)*$Q$157:$Q$590)+COUNTIFS($H$157:$H267,$H267,$I$157:$I267,$I267,$N$157:$N267,1))) -> 6 | M267: =IF($I267="","",COUNTIF($I$5:$I267,$I267)) -> 7 | N267: =IF($H267="","",IF(OR($H267<>$O267,$I267<>$P267),1,0)) -> 0 | O267: RAW | P267: CNS | Q267: 6 | T267: =IF(OR($R267="",$S267="",$S267=0),"",ROUND($R267/$S267,2))
A268: 112 | B268: مبيعات مشروات | C268: Beverage Sales | D268: مواد خام | E268: استهلاكي | F268: =IF($H268="","",$H268&"-"&$I268&"-"&TEXT($J268,"000")) -> RAW-CNS-007 | G268: وحدة | H268: =IFERROR(VLOOKUP($D268,القوائم!$A$2:$B$4,2,0),"") -> RAW | I268: =IF($H268="FIN","RTS",IF(ISNUMBER(SEARCH("مجمد",$E268)),"FRZ",IF(ISNUMBER(SEARCH("مبرد",$E268)),"CHL",IF(ISNUMBER(SEARCH("جاف",$E268)),"DRY",IF(ISNUMBER(SEARCH("استهلاك",$E268)),"CNS",IF(ISNUMBER(SEARCH("بيع",$E268)),"RTS","")))))) -> CNS | J268: =IF($H268="","",IF($N268=0,$Q268,SUMPRODUCT(($O$157:$O$590=$H268)*($P$157:$P$590=$I268)*$Q$157:$Q$590)+COUNTIFS($H$157:$H268,$H268,$I$157:$I268,$I268,$N$157:$N268,1))) -> 7 | M268: =IF($I268="","",COUNTIF($I$5:$I268,$I268)) -> 8 | N268: =IF($H268="","",IF(OR($H268<>$O268,$I268<>$P268),1,0)) -> 0 | O268: RAW | P268: CNS | Q268: 7 | T268: =IF(OR($R268="",$S268="",$S268=0),"",ROUND($R268/$S268,2))
A269: 113 | B269: مشروب كريز مع ليمون واناناس | C269: Drink Lemon | D269: منتج نهائي | E269: جاهز للبيع | F269: =IF($H269="","",$H269&"-"&$I269&"-"&TEXT($J269,"000")) -> FIN-RTS-097 | G269: وحدة | H269: =IFERROR(VLOOKUP($D269,القوائم!$A$2:$B$4,2,0),"") -> FIN | I269: =IF($H269="FIN","RTS",IF(ISNUMBER(SEARCH("مجمد",$E269)),"FRZ",IF(ISNUMBER(SEARCH("مبرد",$E269)),"CHL",IF(ISNUMBER(SEARCH("جاف",$E269)),"DRY",IF(ISNUMBER(SEARCH("استهلاك",$E269)),"CNS",IF(ISNUMBER(SEARCH("بيع",$E269)),"RTS","")))))) -> RTS | J269: =IF($H269="","",IF($N269=0,$Q269,SUMPRODUCT(($O$157:$O$590=$H269)*($P$157:$P$590=$I269)*$Q$157:$Q$590)+COUNTIFS($H$157:$H269,$H269,$I$157:$I269,$I269,$N$157:$N269,1))) -> 97 | M269: =IF($I269="","",COUNTIF($I$5:$I269,$I269)) -> 97 | N269: =IF($H269="","",IF(OR($H269<>$O269,$I269<>$P269),1,0)) -> 0 | O269: FIN | P269: RTS | Q269: 97 | R269: 45 | S269: 100 | T269: =IF(OR($R269="",$S269="",$S269=0),"",ROUND($R269/$S269,2)) -> 0.45
A270: 114 | B270: ادماتيك | C270: Admatic | D270: مواد خام | E270: استهلاكي | F270: =IF($H270="","",$H270&"-"&$I270&"-"&TEXT($J270,"000")) -> RAW-CNS-008 | G270: وحدة | H270: =IFERROR(VLOOKUP($D270,القوائم!$A$2:$B$4,2,0),"") -> RAW | I270: =IF($H270="FIN","RTS",IF(ISNUMBER(SEARCH("مجمد",$E270)),"FRZ",IF(ISNUMBER(SEARCH("مبرد",$E270)),"CHL",IF(ISNUMBER(SEARCH("جاف",$E270)),"DRY",IF(ISNUMBER(SEARCH("استهلاك",$E270)),"CNS",IF(ISNUMBER(SEARCH("بيع",$E270)),"RTS","")))))) -> CNS | J270: =IF($H270="","",IF($N270=0,$Q270,SUMPRODUCT(($O$157:$O$590=$H270)*($P$157:$P$590=$I270)*$Q$157:$Q$590)+COUNTIFS($H$157:$H270,$H270,$I$157:$I270,$I270,$N$157:$N270,1))) -> 8 | M270: =IF($I270="","",COUNTIF($I$5:$I270,$I270)) -> 9 | N270: =IF($H270="","",IF(OR($H270<>$O270,$I270<>$P270),1,0)) -> 0 | O270: RAW | P270: CNS | Q270: 8 | T270: =IF(OR($R270="",$S270="",$S270=0),"",ROUND($R270/$S270,2))
A271: 115 | B271: اسفنج غسيل مربع نحيف | C271: Thin Square Sponge | D271: مواد خام | E271: استهلاكي | F271: =IF($H271="","",$H271&"-"&$I271&"-"&TEXT($J271,"000")) -> RAW-CNS-009 | G271: وحدة | H271: =IFERROR(VLOOKUP($D271,القوائم!$A$2:$B$4,2,0),"") -> RAW | I271: =IF($H271="FIN","RTS",IF(ISNUMBER(SEARCH("مجمد",$E271)),"FRZ",IF(ISNUMBER(SEARCH("مبرد",$E271)),"CHL",IF(ISNUMBER(SEARCH("جاف",$E271)),"DRY",IF(ISNUMBER(SEARCH("استهلاك",$E271)),"CNS",IF(ISNUMBER(SEARCH("بيع",$E271)),"RTS","")))))) -> CNS | J271: =IF($H271="","",IF($N271=0,$Q271,SUMPRODUCT(($O$157:$O$590=$H271)*($P$157:$P$590=$I271)*$Q$157:$Q$590)+COUNTIFS($H$157:$H271,$H271,$I$157:$I271,$I271,$N$157:$N271,1))) -> 9 | M271: =IF($I271="","",COUNTIF($I$5:$I271,$I271)) -> 10 | N271: =IF($H271="","",IF(OR($H271<>$O271,$I271<>$P271),1,0)) -> 0 | O271: RAW | P271: CNS | Q271: 9 | T271: =IF(OR($R271="",$S271="",$S271=0),"",ROUND($R271/$S271,2))
A272: 116 | B272: اغطية ساعد | C272: Sleeve Covers | D272: مواد خام | E272: استهلاكي | F272: =IF($H272="","",$H272&"-"&$I272&"-"&TEXT($J272,"000")) -> RAW-CNS-010 | G272: وحدة | H272: =IFERROR(VLOOKUP($D272,القوائم!$A$2:$B$4,2,0),"") -> RAW | I272: =IF($H272="FIN","RTS",IF(ISNUMBER(SEARCH("مجمد",$E272)),"FRZ",IF(ISNUMBER(SEARCH("مبرد",$E272)),"CHL",IF(ISNUMBER(SEARCH("جاف",$E272)),"DRY",IF(ISNUMBER(SEARCH("استهلاك",$E272)),"CNS",IF(ISNUMBER(SEARCH("بيع",$E272)),"RTS","")))))) -> CNS | J272: =IF($H272="","",IF($N272=0,$Q272,SUMPRODUCT(($O$157:$O$590=$H272)*($P$157:$P$590=$I272)*$Q$157:$Q$590)+COUNTIFS($H$157:$H272,$H272,$I$157:$I272,$I272,$N$157:$N272,1))) -> 10 | M272: =IF($I272="","",COUNTIF($I$5:$I272,$I272)) -> 11 | N272: =IF($H272="","",IF(OR($H272<>$O272,$I272<>$P272),1,0)) -> 0 | O272: RAW | P272: CNS | Q272: 10 | T272: =IF(OR($R272="",$S272="",$S272=0),"",ROUND($R272/$S272,2))
A273: 117 | B273: اغطية شعر زرقاء | C273: Hair Covers | D273: مواد خام | E273: استهلاكي | F273: =IF($H273="","",$H273&"-"&$I273&"-"&TEXT($J273,"000")) -> RAW-CNS-011 | G273: وحدة | H273: =IFERROR(VLOOKUP($D273,القوائم!$A$2:$B$4,2,0),"") -> RAW | I273: =IF($H273="FIN","RTS",IF(ISNUMBER(SEARCH("مجمد",$E273)),"FRZ",IF(ISNUMBER(SEARCH("مبرد",$E273)),"CHL",IF(ISNUMBER(SEARCH("جاف",$E273)),"DRY",IF(ISNUMBER(SEARCH("استهلاك",$E273)),"CNS",IF(ISNUMBER(SEARCH("بيع",$E273)),"RTS","")))))) -> CNS | J273: =IF($H273="","",IF($N273=0,$Q273,SUMPRODUCT(($O$157:$O$590=$H273)*($P$157:$P$590=$I273)*$Q$157:$Q$590)+COUNTIFS($H$157:$H273,$H273,$I$157:$I273,$I273,$N$157:$N273,1))) -> 11 | M273: =IF($I273="","",COUNTIF($I$5:$I273,$I273)) -> 12 | N273: =IF($H273="","",IF(OR($H273<>$O273,$I273<>$P273),1,0)) -> 0 | O273: RAW | P273: CNS | Q273: 11 | T273: =IF(OR($R273="",$S273="",$S273=0),"",ROUND($R273/$S273,2))
A274: 118 | B274: اغطية شعر سوداء | C274: Hair Covers | D274: مواد خام | E274: استهلاكي | F274: =IF($H274="","",$H274&"-"&$I274&"-"&TEXT($J274,"000")) -> RAW-CNS-012 | G274: وحدة | H274: =IFERROR(VLOOKUP($D274,القوائم!$A$2:$B$4,2,0),"") -> RAW | I274: =IF($H274="FIN","RTS",IF(ISNUMBER(SEARCH("مجمد",$E274)),"FRZ",IF(ISNUMBER(SEARCH("مبرد",$E274)),"CHL",IF(ISNUMBER(SEARCH("جاف",$E274)),"DRY",IF(ISNUMBER(SEARCH("استهلاك",$E274)),"CNS",IF(ISNUMBER(SEARCH("بيع",$E274)),"RTS","")))))) -> CNS | J274: =IF($H274="","",IF($N274=0,$Q274,SUMPRODUCT(($O$157:$O$590=$H274)*($P$157:$P$590=$I274)*$Q$157:$Q$590)+COUNTIFS($H$157:$H274,$H274,$I$157:$I274,$I274,$N$157:$N274,1))) -> 12 | M274: =IF($I274="","",COUNTIF($I$5:$I274,$I274)) -> 13 | N274: =IF($H274="","",IF(OR($H274<>$O274,$I274<>$P274),1,0)) -> 0 | O274: RAW | P274: CNS | Q274: 12 | T274: =IF(OR($R274="",$S274="",$S274=0),"",ROUND($R274/$S274,2))
A275: 119 | B275: اقراص الكلور | C275: Chlorine Tablets | D275: مواد خام | E275: استهلاكي | F275: =IF($H275="","",$H275&"-"&$I275&"-"&TEXT($J275,"000")) -> RAW-CNS-013 | G275: وحدة | H275: =IFERROR(VLOOKUP($D275,القوائم!$A$2:$B$4,2,0),"") -> RAW | I275: =IF($H275="FIN","RTS",IF(ISNUMBER(SEARCH("مجمد",$E275)),"FRZ",IF(ISNUMBER(SEARCH("مبرد",$E275)),"CHL",IF(ISNUMBER(SEARCH("جاف",$E275)),"DRY",IF(ISNUMBER(SEARCH("استهلاك",$E275)),"CNS",IF(ISNUMBER(SEARCH("بيع",$E275)),"RTS","")))))) -> CNS | J275: =IF($H275="","",IF($N275=0,$Q275,SUMPRODUCT(($O$157:$O$590=$H275)*($P$157:$P$590=$I275)*$Q$157:$Q$590)+COUNTIFS($H$157:$H275,$H275,$I$157:$I275,$I275,$N$157:$N275,1))) -> 13 | M275: =IF($I275="","",COUNTIF($I$5:$I275,$I275)) -> 14 | N275: =IF($H275="","",IF(OR($H275<>$O275,$I275<>$P275),1,0)) -> 0 | O275: RAW | P275: CNS | Q275: 13 | T275: =IF(OR($R275="",$S275="",$S275=0),"",ROUND($R275/$S275,2))
A276: 120 | B276: اكليل الجبل | C276: Rosemary | D276: مواد خام | E276: تخزين جاف | F276: =IF($H276="","",$H276&"-"&$I276&"-"&TEXT($J276,"000")) -> RAW-DRY-001 | G276: كيلو | H276: =IFERROR(VLOOKUP($D276,القوائم!$A$2:$B$4,2,0),"") -> RAW | I276: =IF($H276="FIN","RTS",IF(ISNUMBER(SEARCH("مجمد",$E276)),"FRZ",IF(ISNUMBER(SEARCH("مبرد",$E276)),"CHL",IF(ISNUMBER(SEARCH("جاف",$E276)),"DRY",IF(ISNUMBER(SEARCH("استهلاك",$E276)),"CNS",IF(ISNUMBER(SEARCH("بيع",$E276)),"RTS","")))))) -> DRY | J276: =IF($H276="","",IF($N276=0,$Q276,SUMPRODUCT(($O$157:$O$590=$H276)*($P$157:$P$590=$I276)*$Q$157:$Q$590)+COUNTIFS($H$157:$H276,$H276,$I$157:$I276,$I276,$N$157:$N276,1))) -> 1 | M276: =IF($I276="","",COUNTIF($I$5:$I276,$I276)) -> 2 | N276: =IF($H276="","",IF(OR($H276<>$O276,$I276<>$P276),1,0)) -> 0 | O276: RAW | P276: DRY | Q276: 1 | R276: 131 | S276: 100 | T276: =IF(OR($R276="",$S276="",$S276=0),"",ROUND($R276/$S276,2)) -> 1.31
A277: 121 | B277: اكياس بينو سفري | C277: Pino Takeaway Bags | D277: مواد خام | E277: استهلاكي | F277: =IF($H277="","",$H277&"-"&$I277&"-"&TEXT($J277,"000")) -> RAW-CNS-014 | G277: وحدة | H277: =IFERROR(VLOOKUP($D277,القوائم!$A$2:$B$4,2,0),"") -> RAW | I277: =IF($H277="FIN","RTS",IF(ISNUMBER(SEARCH("مجمد",$E277)),"FRZ",IF(ISNUMBER(SEARCH("مبرد",$E277)),"CHL",IF(ISNUMBER(SEARCH("جاف",$E277)),"DRY",IF(ISNUMBER(SEARCH("استهلاك",$E277)),"CNS",IF(ISNUMBER(SEARCH("بيع",$E277)),"RTS","")))))) -> CNS | J277: =IF($H277="","",IF($N277=0,$Q277,SUMPRODUCT(($O$157:$O$590=$H277)*($P$157:$P$590=$I277)*$Q$157:$Q$590)+COUNTIFS($H$157:$H277,$H277,$I$157:$I277,$I277,$N$157:$N277,1))) -> 14 | M277: =IF($I277="","",COUNTIF($I$5:$I277,$I277)) -> 15 | N277: =IF($H277="","",IF(OR($H277<>$O277,$I277<>$P277),1,0)) -> 0 | O277: RAW | P277: CNS | Q277: 14 | T277: =IF(OR($R277="",$S277="",$S277=0),"",ROUND($R277/$S277,2))
A278: 122 | B278: اكياس نفايات | C278: Garbage Bags | D278: مواد خام | E278: استهلاكي | F278: =IF($H278="","",$H278&"-"&$I278&"-"&TEXT($J278,"000")) -> RAW-CNS-015 | G278: وحدة | H278: =IFERROR(VLOOKUP($D278,القوائم!$A$2:$B$4,2,0),"") -> RAW | I278: =IF($H278="FIN","RTS",IF(ISNUMBER(SEARCH("مجمد",$E278)),"FRZ",IF(ISNUMBER(SEARCH("مبرد",$E278)),"CHL",IF(ISNUMBER(SEARCH("جاف",$E278)),"DRY",IF(ISNUMBER(SEARCH("استهلاك",$E278)),"CNS",IF(ISNUMBER(SEARCH("بيع",$E278)),"RTS","")))))) -> CNS | J278: =IF($H278="","",IF($N278=0,$Q278,SUMPRODUCT(($O$157:$O$590=$H278)*($P$157:$P$590=$I278)*$Q$157:$Q$590)+COUNTIFS($H$157:$H278,$H278,$I$157:$I278,$I278,$N$157:$N278,1))) -> 15 | M278: =IF($I278="","",COUNTIF($I$5:$I278,$I278)) -> 16 | N278: =IF($H278="","",IF(OR($H278<>$O278,$I278<>$P278),1,0)) -> 0 | O278: RAW | P278: CNS | Q278: 15 | T278: =IF(OR($R278="",$S278="",$S278=0),"",ROUND($R278/$S278,2))
A279: 123 | B279: الكينوا | C279: Quinoa | D279: مواد خام | E279: تخزين جاف | F279: =IF($H279="","",$H279&"-"&$I279&"-"&TEXT($J279,"000")) -> RAW-DRY-002 | G279: كيلو | H279: =IFERROR(VLOOKUP($D279,القوائم!$A$2:$B$4,2,0),"") -> RAW | I279: =IF($H279="FIN","RTS",IF(ISNUMBER(SEARCH("مجمد",$E279)),"FRZ",IF(ISNUMBER(SEARCH("مبرد",$E279)),"CHL",IF(ISNUMBER(SEARCH("جاف",$E279)),"DRY",IF(ISNUMBER(SEARCH("استهلاك",$E279)),"CNS",IF(ISNUMBER(SEARCH("بيع",$E279)),"RTS","")))))) -> DRY | J279: =IF($H279="","",IF($N279=0,$Q279,SUMPRODUCT(($O$157:$O$590=$H279)*($P$157:$P$590=$I279)*$Q$157:$Q$590)+COUNTIFS($H$157:$H279,$H279,$I$157:$I279,$I279,$N$157:$N279,1))) -> 2 | M279: =IF($I279="","",COUNTIF($I$5:$I279,$I279)) -> 3 | N279: =IF($H279="","",IF(OR($H279<>$O279,$I279<>$P279),1,0)) -> 0 | O279: RAW | P279: DRY | Q279: 2 | R279: 368 | S279: 100 | T279: =IF(OR($R279="",$S279="",$S279=0),"",ROUND($R279/$S279,2)) -> 3.68
A280: 124 | B280: انتاج ريزوتو زعفران | C280: Production Risotto Saffron | D280: مواد تحويلية | E280: تخزين مبرد | F280: =IF($H280="","",$H280&"-"&$I280&"-"&TEXT($J280,"000")) -> TRN-CHL-007 | G280: كيلو | H280: =IFERROR(VLOOKUP($D280,القوائم!$A$2:$B$4,2,0),"") -> TRN | I280: =IF($H280="FIN","RTS",IF(ISNUMBER(SEARCH("مجمد",$E280)),"FRZ",IF(ISNUMBER(SEARCH("مبرد",$E280)),"CHL",IF(ISNUMBER(SEARCH("جاف",$E280)),"DRY",IF(ISNUMBER(SEARCH("استهلاك",$E280)),"CNS",IF(ISNUMBER(SEARCH("بيع",$E280)),"RTS","")))))) -> CHL | J280: =IF($H280="","",IF($N280=0,$Q280,SUMPRODUCT(($O$157:$O$590=$H280)*($P$157:$P$590=$I280)*$Q$157:$Q$590)+COUNTIFS($H$157:$H280,$H280,$I$157:$I280,$I280,$N$157:$N280,1))) -> 7 | M280: =IF($I280="","",COUNTIF($I$5:$I280,$I280)) -> 9 | N280: =IF($H280="","",IF(OR($H280<>$O280,$I280<>$P280),1,0)) -> 0 | O280: TRN | P280: CHL | Q280: 7 | R280: 160 | S280: 100 | T280: =IF(OR($R280="",$S280="",$S280=0),"",ROUND($R280/$S280,2)) -> 1.6
A281: 125 | B281: انتاج كرات الارانشيني | C281: Production Arancini Balls | D281: مواد تحويلية | E281: تخزين مبرد | F281: =IF($H281="","",$H281&"-"&$I281&"-"&TEXT($J281,"000")) -> TRN-CHL-008 | G281: كيلو | H281: =IFERROR(VLOOKUP($D281,القوائم!$A$2:$B$4,2,0),"") -> TRN | I281: =IF($H281="FIN","RTS",IF(ISNUMBER(SEARCH("مجمد",$E281)),"FRZ",IF(ISNUMBER(SEARCH("مبرد",$E281)),"CHL",IF(ISNUMBER(SEARCH("جاف",$E281)),"DRY",IF(ISNUMBER(SEARCH("استهلاك",$E281)),"CNS",IF(ISNUMBER(SEARCH("بيع",$E281)),"RTS","")))))) -> CHL | J281: =IF($H281="","",IF($N281=0,$Q281,SUMPRODUCT(($O$157:$O$590=$H281)*($P$157:$P$590=$I281)*$Q$157:$Q$590)+COUNTIFS($H$157:$H281,$H281,$I$157:$I281,$I281,$N$157:$N281,1))) -> 8 | M281: =IF($I281="","",COUNTIF($I$5:$I281,$I281)) -> 10 | N281: =IF($H281="","",IF(OR($H281<>$O281,$I281<>$P281),1,0)) -> 0 | O281: TRN | P281: CHL | Q281: 8 | R281: 250 | S281: 100 | T281: =IF(OR($R281="",$S281="",$S281=0),"",ROUND($R281/$S281,2)) -> 2.5
A282: 126 | B282: انتاج كرات الباستا | C282: Production Pasta Balls | D282: مواد تحويلية | E282: تخزين مبرد | F282: =IF($H282="","",$H282&"-"&$I282&"-"&TEXT($J282,"000")) -> TRN-CHL-009 | G282: كيلو | H282: =IFERROR(VLOOKUP($D282,القوائم!$A$2:$B$4,2,0),"") -> TRN | I282: =IF($H282="FIN","RTS",IF(ISNUMBER(SEARCH("مجمد",$E282)),"FRZ",IF(ISNUMBER(SEARCH("مبرد",$E282)),"CHL",IF(ISNUMBER(SEARCH("جاف",$E282)),"DRY",IF(ISNUMBER(SEARCH("استهلاك",$E282)),"CNS",IF(ISNUMBER(SEARCH("بيع",$E282)),"RTS","")))))) -> CHL | J282: =IF($H282="","",IF($N282=0,$Q282,SUMPRODUCT(($O$157:$O$590=$H282)*($P$157:$P$590=$I282)*$Q$157:$Q$590)+COUNTIFS($H$157:$H282,$H282,$I$157:$I282,$I282,$N$157:$N282,1))) -> 9 | M282: =IF($I282="","",COUNTIF($I$5:$I282,$I282)) -> 11 | N282: =IF($H282="","",IF(OR($H282<>$O282,$I282<>$P282),1,0)) -> 0 | O282: TRN | P282: CHL | Q282: 9 | R282: 250 | S282: 100 | T282: =IF(OR($R282="",$S282="",$S282=0),"",ROUND($R282/$S282,2)) -> 2.5
A283: 127 | B283: اوراق كرنب | C283: Cabbage | D283: مواد خام | E283: تخزين مبرد | F283: =IF($H283="","",$H283&"-"&$I283&"-"&TEXT($J283,"000")) -> RAW-CHL-003 | G283: كيلو | H283: =IFERROR(VLOOKUP($D283,القوائم!$A$2:$B$4,2,0),"") -> RAW | I283: =IF($H283="FIN","RTS",IF(ISNUMBER(SEARCH("مجمد",$E283)),"FRZ",IF(ISNUMBER(SEARCH("مبرد",$E283)),"CHL",IF(ISNUMBER(SEARCH("جاف",$E283)),"DRY",IF(ISNUMBER(SEARCH("استهلاك",$E283)),"CNS",IF(ISNUMBER(SEARCH("بيع",$E283)),"RTS","")))))) -> CHL | J283: =IF($H283="","",IF($N283=0,$Q283,SUMPRODUCT(($O$157:$O$590=$H283)*($P$157:$P$590=$I283)*$Q$157:$Q$590)+COUNTIFS($H$157:$H283,$H283,$I$157:$I283,$I283,$N$157:$N283,1))) -> 3 | M283: =IF($I283="","",COUNTIF($I$5:$I283,$I283)) -> 12 | N283: =IF($H283="","",IF(OR($H283<>$O283,$I283<>$P283),1,0)) -> 0 | O283: RAW | P283: CHL | Q283: 3 | R283: 25 | S283: 100 | T283: =IF(OR($R283="",$S283="",$S283=0),"",ROUND($R283/$S283,2)) -> 0.25
A284: 128 | B284: ايكولار ecolar | C284: Ecolar | D284: مواد خام | E284: استهلاكي | F284: =IF($H284="","",$H284&"-"&$I284&"-"&TEXT($J284,"000")) -> RAW-CNS-016 | G284: وحدة | H284: =IFERROR(VLOOKUP($D284,القوائم!$A$2:$B$4,2,0),"") -> RAW | I284: =IF($H284="FIN","RTS",IF(ISNUMBER(SEARCH("مجمد",$E284)),"FRZ",IF(ISNUMBER(SEARCH("مبرد",$E284)),"CHL",IF(ISNUMBER(SEARCH("جاف",$E284)),"DRY",IF(ISNUMBER(SEARCH("استهلاك",$E284)),"CNS",IF(ISNUMBER(SEARCH("بيع",$E284)),"RTS","")))))) -> CNS | J284: =IF($H284="","",IF($N284=0,$Q284,SUMPRODUCT(($O$157:$O$590=$H284)*($P$157:$P$590=$I284)*$Q$157:$Q$590)+COUNTIFS($H$157:$H284,$H284,$I$157:$I284,$I284,$N$157:$N284,1))) -> 16 | M284: =IF($I284="","",COUNTIF($I$5:$I284,$I284)) -> 17 | N284: =IF($H284="","",IF(OR($H284<>$O284,$I284<>$P284),1,0)) -> 0 | O284: RAW | P284: CNS | Q284: 16 | T284: =IF(OR($R284="",$S284="",$S284=0),"",ROUND($R284/$S284,2))
A285: 129 | B285: بابريكا فلفل حلو | C285: Paprika Pepper | D285: مواد خام | E285: تخزين جاف | F285: =IF($H285="","",$H285&"-"&$I285&"-"&TEXT($J285,"000")) -> RAW-DRY-003 | G285: كيلو | H285: =IFERROR(VLOOKUP($D285,القوائم!$A$2:$B$4,2,0),"") -> RAW | I285: =IF($H285="FIN","RTS",IF(ISNUMBER(SEARCH("مجمد",$E285)),"FRZ",IF(ISNUMBER(SEARCH("مبرد",$E285)),"CHL",IF(ISNUMBER(SEARCH("جاف",$E285)),"DRY",IF(ISNUMBER(SEARCH("استهلاك",$E285)),"CNS",IF(ISNUMBER(SEARCH("بيع",$E285)),"RTS","")))))) -> DRY | J285: =IF($H285="","",IF($N285=0,$Q285,SUMPRODUCT(($O$157:$O$590=$H285)*($P$157:$P$590=$I285)*$Q$157:$Q$590)+COUNTIFS($H$157:$H285,$H285,$I$157:$I285,$I285,$N$157:$N285,1))) -> 3 | M285: =IF($I285="","",COUNTIF($I$5:$I285,$I285)) -> 4 | N285: =IF($H285="","",IF(OR($H285<>$O285,$I285<>$P285),1,0)) -> 0 | O285: RAW | P285: DRY | Q285: 3 | R285: 282 | S285: 100 | T285: =IF(OR($R285="",$S285="",$S285=0),"",ROUND($R285/$S285,2)) -> 2.82
A286: 130 | B286: بابريكا مدخنة | C286: Paprika Smoked | D286: مواد خام | E286: تخزين جاف | F286: =IF($H286="","",$H286&"-"&$I286&"-"&TEXT($J286,"000")) -> RAW-DRY-004 | G286: كيلو | H286: =IFERROR(VLOOKUP($D286,القوائم!$A$2:$B$4,2,0),"") -> RAW | I286: =IF($H286="FIN","RTS",IF(ISNUMBER(SEARCH("مجمد",$E286)),"FRZ",IF(ISNUMBER(SEARCH("مبرد",$E286)),"CHL",IF(ISNUMBER(SEARCH("جاف",$E286)),"DRY",IF(ISNUMBER(SEARCH("استهلاك",$E286)),"CNS",IF(ISNUMBER(SEARCH("بيع",$E286)),"RTS","")))))) -> DRY | J286: =IF($H286="","",IF($N286=0,$Q286,SUMPRODUCT(($O$157:$O$590=$H286)*($P$157:$P$590=$I286)*$Q$157:$Q$590)+COUNTIFS($H$157:$H286,$H286,$I$157:$I286,$I286,$N$157:$N286,1))) -> 4 | M286: =IF($I286="","",COUNTIF($I$5:$I286,$I286)) -> 5 | N286: =IF($H286="","",IF(OR($H286<>$O286,$I286<>$P286),1,0)) -> 0 | O286: RAW | P286: DRY | Q286: 4 | R286: 282 | S286: 100 | T286: =IF(OR($R286="",$S286="",$S286=0),"",ROUND($R286/$S286,2)) -> 2.82
A287: 131 | B287: باذنجان | C287: Eggplant | D287: مواد خام | E287: تخزين مبرد | F287: =IF($H287="","",$H287&"-"&$I287&"-"&TEXT($J287,"000")) -> RAW-CHL-004 | G287: كيلو | H287: =IFERROR(VLOOKUP($D287,القوائم!$A$2:$B$4,2,0),"") -> RAW | I287: =IF($H287="FIN","RTS",IF(ISNUMBER(SEARCH("مجمد",$E287)),"FRZ",IF(ISNUMBER(SEARCH("مبرد",$E287)),"CHL",IF(ISNUMBER(SEARCH("جاف",$E287)),"DRY",IF(ISNUMBER(SEARCH("استهلاك",$E287)),"CNS",IF(ISNUMBER(SEARCH("بيع",$E287)),"RTS","")))))) -> CHL | J287: =IF($H287="","",IF($N287=0,$Q287,SUMPRODUCT(($O$157:$O$590=$H287)*($P$157:$P$590=$I287)*$Q$157:$Q$590)+COUNTIFS($H$157:$H287,$H287,$I$157:$I287,$I287,$N$157:$N287,1))) -> 4 | M287: =IF($I287="","",COUNTIF($I$5:$I287,$I287)) -> 13 | N287: =IF($H287="","",IF(OR($H287<>$O287,$I287<>$P287),1,0)) -> 0 | O287: RAW | P287: CHL | Q287: 4 | R287: 25 | S287: 100 | T287: =IF(OR($R287="",$S287="",$S287=0),"",ROUND($R287/$S287,2)) -> 0.25
A288: 132 | B288: ببروني | C288: Pepperoni | D288: مواد خام | E288: تخزين مجمد | F288: =IF($H288="","",$H288&"-"&$I288&"-"&TEXT($J288,"000")) -> RAW-FRZ-002 | G288: كيلو | H288: =IFERROR(VLOOKUP($D288,القوائم!$A$2:$B$4,2,0),"") -> RAW | I288: =IF($H288="FIN","RTS",IF(ISNUMBER(SEARCH("مجمد",$E288)),"FRZ",IF(ISNUMBER(SEARCH("مبرد",$E288)),"CHL",IF(ISNUMBER(SEARCH("جاف",$E288)),"DRY",IF(ISNUMBER(SEARCH("استهلاك",$E288)),"CNS",IF(ISNUMBER(SEARCH("بيع",$E288)),"RTS","")))))) -> FRZ | J288: =IF($H288="","",IF($N288=0,$Q288,SUMPRODUCT(($O$157:$O$590=$H288)*($P$157:$P$590=$I288)*$Q$157:$Q$590)+COUNTIFS($H$157:$H288,$H288,$I$157:$I288,$I288,$N$157:$N288,1))) -> 2 | M288: =IF($I288="","",COUNTIF($I$5:$I288,$I288)) -> 2 | N288: =IF($H288="","",IF(OR($H288<>$O288,$I288<>$P288),1,0)) -> 0 | O288: RAW | P288: FRZ | Q288: 2 | R288: 490 | S288: 100 | T288: =IF(OR($R288="",$S288="",$S288=0),"",ROUND($R288/$S288,2)) -> 4.9
A289: 133 | B289: بذور الشيا | C289: Chia Seeds | D289: مواد خام | E289: تخزين جاف | F289: =IF($H289="","",$H289&"-"&$I289&"-"&TEXT($J289,"000")) -> RAW-DRY-005 | G289: كيلو | H289: =IFERROR(VLOOKUP($D289,القوائم!$A$2:$B$4,2,0),"") -> RAW | I289: =IF($H289="FIN","RTS",IF(ISNUMBER(SEARCH("مجمد",$E289)),"FRZ",IF(ISNUMBER(SEARCH("مبرد",$E289)),"CHL",IF(ISNUMBER(SEARCH("جاف",$E289)),"DRY",IF(ISNUMBER(SEARCH("استهلاك",$E289)),"CNS",IF(ISNUMBER(SEARCH("بيع",$E289)),"RTS","")))))) -> DRY | J289: =IF($H289="","",IF($N289=0,$Q289,SUMPRODUCT(($O$157:$O$590=$H289)*($P$157:$P$590=$I289)*$Q$157:$Q$590)+COUNTIFS($H$157:$H289,$H289,$I$157:$I289,$I289,$N$157:$N289,1))) -> 5 | M289: =IF($I289="","",COUNTIF($I$5:$I289,$I289)) -> 6 | N289: =IF($H289="","",IF(OR($H289<>$O289,$I289<>$P289),1,0)) -> 0 | O289: RAW | P289: DRY | Q289: 5 | R289: 486 | S289: 100 | T289: =IF(OR($R289="",$S289="",$S289=0),"",ROUND($R289/$S289,2)) -> 4.86
A290: 134 | B290: بذور الكتان | C290: Flax Seeds | D290: مواد خام | E290: تخزين جاف | F290: =IF($H290="","",$H290&"-"&$I290&"-"&TEXT($J290,"000")) -> RAW-DRY-006 | G290: كيلو | H290: =IFERROR(VLOOKUP($D290,القوائم!$A$2:$B$4,2,0),"") -> RAW | I290: =IF($H290="FIN","RTS",IF(ISNUMBER(SEARCH("مجمد",$E290)),"FRZ",IF(ISNUMBER(SEARCH("مبرد",$E290)),"CHL",IF(ISNUMBER(SEARCH("جاف",$E290)),"DRY",IF(ISNUMBER(SEARCH("استهلاك",$E290)),"CNS",IF(ISNUMBER(SEARCH("بيع",$E290)),"RTS","")))))) -> DRY | J290: =IF($H290="","",IF($N290=0,$Q290,SUMPRODUCT(($O$157:$O$590=$H290)*($P$157:$P$590=$I290)*$Q$157:$Q$590)+COUNTIFS($H$157:$H290,$H290,$I$157:$I290,$I290,$N$157:$N290,1))) -> 6 | M290: =IF($I290="","",COUNTIF($I$5:$I290,$I290)) -> 7 | N290: =IF($H290="","",IF(OR($H290<>$O290,$I290<>$P290),1,0)) -> 0 | O290: RAW | P290: DRY | Q290: 6 | R290: 534 | S290: 100 | T290: =IF(OR($R290="",$S290="",$S290=0),"",ROUND($R290/$S290,2)) -> 5.34
A291: 135 | B291: برتقال | C291: Orange | D291: مواد خام | E291: تخزين مبرد | F291: =IF($H291="","",$H291&"-"&$I291&"-"&TEXT($J291,"000")) -> RAW-CHL-005 | G291: كيلو | H291: =IFERROR(VLOOKUP($D291,القوائم!$A$2:$B$4,2,0),"") -> RAW | I291: =IF($H291="FIN","RTS",IF(ISNUMBER(SEARCH("مجمد",$E291)),"FRZ",IF(ISNUMBER(SEARCH("مبرد",$E291)),"CHL",IF(ISNUMBER(SEARCH("جاف",$E291)),"DRY",IF(ISNUMBER(SEARCH("استهلاك",$E291)),"CNS",IF(ISNUMBER(SEARCH("بيع",$E291)),"RTS","")))))) -> CHL | J291: =IF($H291="","",IF($N291=0,$Q291,SUMPRODUCT(($O$157:$O$590=$H291)*($P$157:$P$590=$I291)*$Q$157:$Q$590)+COUNTIFS($H$157:$H291,$H291,$I$157:$I291,$I291,$N$157:$N291,1))) -> 5 | M291: =IF($I291="","",COUNTIF($I$5:$I291,$I291)) -> 14 | N291: =IF($H291="","",IF(OR($H291<>$O291,$I291<>$P291),1,0)) -> 0 | O291: RAW | P291: CHL | Q291: 5 | R291: 47 | S291: 100 | T291: =IF(OR($R291="",$S291="",$S291=0),"",ROUND($R291/$S291,2)) -> 0.47
A292: 136 | B292: برطمان صوص زجاج | C292: Sauce Jar | D292: مواد خام | E292: استهلاكي | F292: =IF($H292="","",$H292&"-"&$I292&"-"&TEXT($J292,"000")) -> RAW-CNS-017 | G292: وحدة | H292: =IFERROR(VLOOKUP($D292,القوائم!$A$2:$B$4,2,0),"") -> RAW | I292: =IF($H292="FIN","RTS",IF(ISNUMBER(SEARCH("مجمد",$E292)),"FRZ",IF(ISNUMBER(SEARCH("مبرد",$E292)),"CHL",IF(ISNUMBER(SEARCH("جاف",$E292)),"DRY",IF(ISNUMBER(SEARCH("استهلاك",$E292)),"CNS",IF(ISNUMBER(SEARCH("بيع",$E292)),"RTS","")))))) -> CNS | J292: =IF($H292="","",IF($N292=0,$Q292,SUMPRODUCT(($O$157:$O$590=$H292)*($P$157:$P$590=$I292)*$Q$157:$Q$590)+COUNTIFS($H$157:$H292,$H292,$I$157:$I292,$I292,$N$157:$N292,1))) -> 17 | M292: =IF($I292="","",COUNTIF($I$5:$I292,$I292)) -> 18 | N292: =IF($H292="","",IF(OR($H292<>$O292,$I292<>$P292),1,0)) -> 0 | O292: RAW | P292: CNS | Q292: 17 | T292: =IF(OR($R292="",$S292="",$S292=0),"",ROUND($R292/$S292,2))
A293: 137 | B293: بسكوت الاسكريم | C293: Cream Biscuit | D293: مواد خام | E293: تخزين جاف | F293: =IF($H293="","",$H293&"-"&$I293&"-"&TEXT($J293,"000")) -> RAW-DRY-007 | G293: كيلو | H293: =IFERROR(VLOOKUP($D293,القوائم!$A$2:$B$4,2,0),"") -> RAW | I293: =IF($H293="FIN","RTS",IF(ISNUMBER(SEARCH("مجمد",$E293)),"FRZ",IF(ISNUMBER(SEARCH("مبرد",$E293)),"CHL",IF(ISNUMBER(SEARCH("جاف",$E293)),"DRY",IF(ISNUMBER(SEARCH("استهلاك",$E293)),"CNS",IF(ISNUMBER(SEARCH("بيع",$E293)),"RTS","")))))) -> DRY | J293: =IF($H293="","",IF($N293=0,$Q293,SUMPRODUCT(($O$157:$O$590=$H293)*($P$157:$P$590=$I293)*$Q$157:$Q$590)+COUNTIFS($H$157:$H293,$H293,$I$157:$I293,$I293,$N$157:$N293,1))) -> 7 | M293: =IF($I293="","",COUNTIF($I$5:$I293,$I293)) -> 8 | N293: =IF($H293="","",IF(OR($H293<>$O293,$I293<>$P293),1,0)) -> 0 | O293: RAW | P293: DRY | Q293: 7 | R293: 420 | S293: 100 | T293: =IF(OR($R293="",$S293="",$S293=0),"",ROUND($R293/$S293,2)) -> 4.2
A294: 138 | B294: بسكوت ليدي فنجر | C294: Biscuit | D294: مواد خام | E294: تخزين جاف | F294: =IF($H294="","",$H294&"-"&$I294&"-"&TEXT($J294,"000")) -> RAW-DRY-008 | G294: كيلو | H294: =IFERROR(VLOOKUP($D294,القوائم!$A$2:$B$4,2,0),"") -> RAW | I294: =IF($H294="FIN","RTS",IF(ISNUMBER(SEARCH("مجمد",$E294)),"FRZ",IF(ISNUMBER(SEARCH("مبرد",$E294)),"CHL",IF(ISNUMBER(SEARCH("جاف",$E294)),"DRY",IF(ISNUMBER(SEARCH("استهلاك",$E294)),"CNS",IF(ISNUMBER(SEARCH("بيع",$E294)),"RTS","")))))) -> DRY | J294: =IF($H294="","",IF($N294=0,$Q294,SUMPRODUCT(($O$157:$O$590=$H294)*($P$157:$P$590=$I294)*$Q$157:$Q$590)+COUNTIFS($H$157:$H294,$H294,$I$157:$I294,$I294,$N$157:$N294,1))) -> 8 | M294: =IF($I294="","",COUNTIF($I$5:$I294,$I294)) -> 9 | N294: =IF($H294="","",IF(OR($H294<>$O294,$I294<>$P294),1,0)) -> 0 | O294: RAW | P294: DRY | Q294: 8 | R294: 400 | S294: 100 | T294: =IF(OR($R294="",$S294="",$S294=0),"",ROUND($R294/$S294,2)) -> 4
A295: 139 | B295: بسكويت تيراميسو | C295: Tiramisu Biscuit | D295: مواد خام | E295: تخزين جاف | F295: =IF($H295="","",$H295&"-"&$I295&"-"&TEXT($J295,"000")) -> RAW-DRY-009 | G295: كيلو | H295: =IFERROR(VLOOKUP($D295,القوائم!$A$2:$B$4,2,0),"") -> RAW | I295: =IF($H295="FIN","RTS",IF(ISNUMBER(SEARCH("مجمد",$E295)),"FRZ",IF(ISNUMBER(SEARCH("مبرد",$E295)),"CHL",IF(ISNUMBER(SEARCH("جاف",$E295)),"DRY",IF(ISNUMBER(SEARCH("استهلاك",$E295)),"CNS",IF(ISNUMBER(SEARCH("بيع",$E295)),"RTS","")))))) -> DRY | J295: =IF($H295="","",IF($N295=0,$Q295,SUMPRODUCT(($O$157:$O$590=$H295)*($P$157:$P$590=$I295)*$Q$157:$Q$590)+COUNTIFS($H$157:$H295,$H295,$I$157:$I295,$I295,$N$157:$N295,1))) -> 9 | M295: =IF($I295="","",COUNTIF($I$5:$I295,$I295)) -> 10 | N295: =IF($H295="","",IF(OR($H295<>$O295,$I295<>$P295),1,0)) -> 0 | O295: RAW | P295: DRY | Q295: 9 | R295: 400 | S295: 100 | T295: =IF(OR($R295="",$S295="",$S295=0),"",ROUND($R295/$S295,2)) -> 4
A296: 140 | B296: بصل ابيض | C296: Onion | D296: مواد خام | E296: تخزين جاف | F296: =IF($H296="","",$H296&"-"&$I296&"-"&TEXT($J296,"000")) -> RAW-DRY-010 | G296: كيلو | H296: =IFERROR(VLOOKUP($D296,القوائم!$A$2:$B$4,2,0),"") -> RAW | I296: =IF($H296="FIN","RTS",IF(ISNUMBER(SEARCH("مجمد",$E296)),"FRZ",IF(ISNUMBER(SEARCH("مبرد",$E296)),"CHL",IF(ISNUMBER(SEARCH("جاف",$E296)),"DRY",IF(ISNUMBER(SEARCH("استهلاك",$E296)),"CNS",IF(ISNUMBER(SEARCH("بيع",$E296)),"RTS","")))))) -> DRY | J296: =IF($H296="","",IF($N296=0,$Q296,SUMPRODUCT(($O$157:$O$590=$H296)*($P$157:$P$590=$I296)*$Q$157:$Q$590)+COUNTIFS($H$157:$H296,$H296,$I$157:$I296,$I296,$N$157:$N296,1))) -> 10 | M296: =IF($I296="","",COUNTIF($I$5:$I296,$I296)) -> 11 | N296: =IF($H296="","",IF(OR($H296<>$O296,$I296<>$P296),1,0)) -> 0 | O296: RAW | P296: DRY | Q296: 10 | R296: 40 | S296: 100 | T296: =IF(OR($R296="",$S296="",$S296=0),"",ROUND($R296/$S296,2)) -> 0.4
A297: 141 | B297: بصل احمر | C297: Onion | D297: مواد خام | E297: تخزين جاف | F297: =IF($H297="","",$H297&"-"&$I297&"-"&TEXT($J297,"000")) -> RAW-DRY-011 | G297: كيلو | H297: =IFERROR(VLOOKUP($D297,القوائم!$A$2:$B$4,2,0),"") -> RAW | I297: =IF($H297="FIN","RTS",IF(ISNUMBER(SEARCH("مجمد",$E297)),"FRZ",IF(ISNUMBER(SEARCH("مبرد",$E297)),"CHL",IF(ISNUMBER(SEARCH("جاف",$E297)),"DRY",IF(ISNUMBER(SEARCH("استهلاك",$E297)),"CNS",IF(ISNUMBER(SEARCH("بيع",$E297)),"RTS","")))))) -> DRY | J297: =IF($H297="","",IF($N297=0,$Q297,SUMPRODUCT(($O$157:$O$590=$H297)*($P$157:$P$590=$I297)*$Q$157:$Q$590)+COUNTIFS($H$157:$H297,$H297,$I$157:$I297,$I297,$N$157:$N297,1))) -> 11 | M297: =IF($I297="","",COUNTIF($I$5:$I297,$I297)) -> 12 | N297: =IF($H297="","",IF(OR($H297<>$O297,$I297<>$P297),1,0)) -> 0 | O297: RAW | P297: DRY | Q297: 11 | R297: 40 | S297: 100 | T297: =IF(OR($R297="",$S297="",$S297=0),"",ROUND($R297/$S297,2)) -> 0.4
A298: 142 | B298: بصل مكرمل | C298: Onion | D298: مواد تحويلية | E298: تخزين جاف | F298: =IF($H298="","",$H298&"-"&$I298&"-"&TEXT($J298,"000")) -> TRN-DRY-001 | G298: كيلو | H298: =IFERROR(VLOOKUP($D298,القوائم!$A$2:$B$4,2,0),"") -> TRN | I298: =IF($H298="FIN","RTS",IF(ISNUMBER(SEARCH("مجمد",$E298)),"FRZ",IF(ISNUMBER(SEARCH("مبرد",$E298)),"CHL",IF(ISNUMBER(SEARCH("جاف",$E298)),"DRY",IF(ISNUMBER(SEARCH("استهلاك",$E298)),"CNS",IF(ISNUMBER(SEARCH("بيع",$E298)),"RTS","")))))) -> DRY | J298: =IF($H298="","",IF($N298=0,$Q298,SUMPRODUCT(($O$157:$O$590=$H298)*($P$157:$P$590=$I298)*$Q$157:$Q$590)+COUNTIFS($H$157:$H298,$H298,$I$157:$I298,$I298,$N$157:$N298,1))) -> 1 | M298: =IF($I298="","",COUNTIF($I$5:$I298,$I298)) -> 13 | N298: =IF($H298="","",IF(OR($H298<>$O298,$I298<>$P298),1,0)) -> 0 | O298: TRN | P298: DRY | Q298: 1 | R298: 150 | S298: 100 | T298: =IF(OR($R298="",$S298="",$S298=0),"",ROUND($R298/$S298,2)) -> 1.5
A299: 143 | B299: بطاطا | C299: Potato | D299: مواد خام | E299: تخزين جاف | F299: =IF($H299="","",$H299&"-"&$I299&"-"&TEXT($J299,"000")) -> RAW-DRY-012 | G299: كيلو | H299: =IFERROR(VLOOKUP($D299,القوائم!$A$2:$B$4,2,0),"") -> RAW | I299: =IF($H299="FIN","RTS",IF(ISNUMBER(SEARCH("مجمد",$E299)),"FRZ",IF(ISNUMBER(SEARCH("مبرد",$E299)),"CHL",IF(ISNUMBER(SEARCH("جاف",$E299)),"DRY",IF(ISNUMBER(SEARCH("استهلاك",$E299)),"CNS",IF(ISNUMBER(SEARCH("بيع",$E299)),"RTS","")))))) -> DRY | J299: =IF($H299="","",IF($N299=0,$Q299,SUMPRODUCT(($O$157:$O$590=$H299)*($P$157:$P$590=$I299)*$Q$157:$Q$590)+COUNTIFS($H$157:$H299,$H299,$I$157:$I299,$I299,$N$157:$N299,1))) -> 12 | M299: =IF($I299="","",COUNTIF($I$5:$I299,$I299)) -> 14 | N299: =IF($H299="","",IF(OR($H299<>$O299,$I299<>$P299),1,0)) -> 0 | O299: RAW | P299: DRY | Q299: 12 | R299: 77 | S299: 100 | T299: =IF(OR($R299="",$S299="",$S299=0),"",ROUND($R299/$S299,2)) -> 0.77
A300: 144 | B300: بطاطا حلوة | C300: Sweet Potato | D300: مواد خام | E300: تخزين جاف | F300: =IF($H300="","",$H300&"-"&$I300&"-"&TEXT($J300,"000")) -> RAW-DRY-013 | G300: كيلو | H300: =IFERROR(VLOOKUP($D300,القوائم!$A$2:$B$4,2,0),"") -> RAW | I300: =IF($H300="FIN","RTS",IF(ISNUMBER(SEARCH("مجمد",$E300)),"FRZ",IF(ISNUMBER(SEARCH("مبرد",$E300)),"CHL",IF(ISNUMBER(SEARCH("جاف",$E300)),"DRY",IF(ISNUMBER(SEARCH("استهلاك",$E300)),"CNS",IF(ISNUMBER(SEARCH("بيع",$E300)),"RTS","")))))) -> DRY | J300: =IF($H300="","",IF($N300=0,$Q300,SUMPRODUCT(($O$157:$O$590=$H300)*($P$157:$P$590=$I300)*$Q$157:$Q$590)+COUNTIFS($H$157:$H300,$H300,$I$157:$I300,$I300,$N$157:$N300,1))) -> 13 | M300: =IF($I300="","",COUNTIF($I$5:$I300,$I300)) -> 15 | N300: =IF($H300="","",IF(OR($H300<>$O300,$I300<>$P300),1,0)) -> 0 | O300: RAW | P300: DRY | Q300: 13 | R300: 86 | S300: 100 | T300: =IF(OR($R300="",$S300="",$S300=0),"",ROUND($R300/$S300,2)) -> 0.86
A301: 145 | B301: بطاطس | C301: Fries | D301: مواد خام | E301: تخزين جاف | F301: =IF($H301="","",$H301&"-"&$I301&"-"&TEXT($J301,"000")) -> RAW-DRY-014 | G301: كيلو | H301: =IFERROR(VLOOKUP($D301,القوائم!$A$2:$B$4,2,0),"") -> RAW | I301: =IF($H301="FIN","RTS",IF(ISNUMBER(SEARCH("مجمد",$E301)),"FRZ",IF(ISNUMBER(SEARCH("مبرد",$E301)),"CHL",IF(ISNUMBER(SEARCH("جاف",$E301)),"DRY",IF(ISNUMBER(SEARCH("استهلاك",$E301)),"CNS",IF(ISNUMBER(SEARCH("بيع",$E301)),"RTS","")))))) -> DRY | J301: =IF($H301="","",IF($N301=0,$Q301,SUMPRODUCT(($O$157:$O$590=$H301)*($P$157:$P$590=$I301)*$Q$157:$Q$590)+COUNTIFS($H$157:$H301,$H301,$I$157:$I301,$I301,$N$157:$N301,1))) -> 14 | M301: =IF($I301="","",COUNTIF($I$5:$I301,$I301)) -> 16 | N301: =IF($H301="","",IF(OR($H301<>$O301,$I301<>$P301),1,0)) -> 0 | O301: RAW | P301: DRY | Q301: 14 | R301: 150 | S301: 100 | T301: =IF(OR($R301="",$S301="",$S301=0),"",ROUND($R301/$S301,2)) -> 1.5
A302: 146 | B302: بطاطس كري | C302: Curry Fries | D302: منتج نهائي | E302: جاهز للبيع | F302: =IF($H302="","",$H302&"-"&$I302&"-"&TEXT($J302,"000")) -> FIN-RTS-098 | G302: وحدة | H302: =IFERROR(VLOOKUP($D302,القوائم!$A$2:$B$4,2,0),"") -> FIN | I302: =IF($H302="FIN","RTS",IF(ISNUMBER(SEARCH("مجمد",$E302)),"FRZ",IF(ISNUMBER(SEARCH("مبرد",$E302)),"CHL",IF(ISNUMBER(SEARCH("جاف",$E302)),"DRY",IF(ISNUMBER(SEARCH("استهلاك",$E302)),"CNS",IF(ISNUMBER(SEARCH("بيع",$E302)),"RTS","")))))) -> RTS | J302: =IF($H302="","",IF($N302=0,$Q302,SUMPRODUCT(($O$157:$O$590=$H302)*($P$157:$P$590=$I302)*$Q$157:$Q$590)+COUNTIFS($H$157:$H302,$H302,$I$157:$I302,$I302,$N$157:$N302,1))) -> 98 | M302: =IF($I302="","",COUNTIF($I$5:$I302,$I302)) -> 98 | N302: =IF($H302="","",IF(OR($H302<>$O302,$I302<>$P302),1,0)) -> 0 | O302: FIN | P302: RTS | Q302: 98 | R302: 320 | S302: 100 | T302: =IF(OR($R302="",$S302="",$S302=0),"",ROUND($R302/$S302,2)) -> 3.2
A303: 147 | B303: بطاطس كريسبر | C303: Crisper Fries | D303: منتج نهائي | E303: جاهز للبيع | F303: =IF($H303="","",$H303&"-"&$I303&"-"&TEXT($J303,"000")) -> FIN-RTS-099 | G303: وحدة | H303: =IFERROR(VLOOKUP($D303,القوائم!$A$2:$B$4,2,0),"") -> FIN | I303: =IF($H303="FIN","RTS",IF(ISNUMBER(SEARCH("مجمد",$E303)),"FRZ",IF(ISNUMBER(SEARCH("مبرد",$E303)),"CHL",IF(ISNUMBER(SEARCH("جاف",$E303)),"DRY",IF(ISNUMBER(SEARCH("استهلاك",$E303)),"CNS",IF(ISNUMBER(SEARCH("بيع",$E303)),"RTS","")))))) -> RTS | J303: =IF($H303="","",IF($N303=0,$Q303,SUMPRODUCT(($O$157:$O$590=$H303)*($P$157:$P$590=$I303)*$Q$157:$Q$590)+COUNTIFS($H$157:$H303,$H303,$I$157:$I303,$I303,$N$157:$N303,1))) -> 99 | M303: =IF($I303="","",COUNTIF($I$5:$I303,$I303)) -> 99 | N303: =IF($H303="","",IF(OR($H303<>$O303,$I303<>$P303),1,0)) -> 0 | O303: FIN | P303: RTS | Q303: 99 | R303: 330 | S303: 100 | T303: =IF(OR($R303="",$S303="",$S303=0),"",ROUND($R303/$S303,2)) -> 3.3
A304: 148 | B304: بطاطس كريسبر مكعبات | C304: Crisper Fries | D304: منتج نهائي | E304: جاهز للبيع | F304: =IF($H304="","",$H304&"-"&$I304&"-"&TEXT($J304,"000")) -> FIN-RTS-100 | G304: وحدة | H304: =IFERROR(VLOOKUP($D304,القوائم!$A$2:$B$4,2,0),"") -> FIN | I304: =IF($H304="FIN","RTS",IF(ISNUMBER(SEARCH("مجمد",$E304)),"FRZ",IF(ISNUMBER(SEARCH("مبرد",$E304)),"CHL",IF(ISNUMBER(SEARCH("جاف",$E304)),"DRY",IF(ISNUMBER(SEARCH("استهلاك",$E304)),"CNS",IF(ISNUMBER(SEARCH("بيع",$E304)),"RTS","")))))) -> RTS | J304: =IF($H304="","",IF($N304=0,$Q304,SUMPRODUCT(($O$157:$O$590=$H304)*($P$157:$P$590=$I304)*$Q$157:$Q$590)+COUNTIFS($H$157:$H304,$H304,$I$157:$I304,$I304,$N$157:$N304,1))) -> 100 | M304: =IF($I304="","",COUNTIF($I$5:$I304,$I304)) -> 100 | N304: =IF($H304="","",IF(OR($H304<>$O304,$I304<>$P304),1,0)) -> 0 | O304: FIN | P304: RTS | Q304: 100 | R304: 330 | S304: 100 | T304: =IF(OR($R304="",$S304="",$S304=0),"",ROUND($R304/$S304,2)) -> 3.3
... A312: 156 | B312: بودرة ثوم | C312: Powder Garlic | D312: مواد خام | E312: تخزين جاف | F312: =IF($H312="","",$H312&"-"&$I312&"-"&TEXT($J312,"000")) -> RAW-DRY-020 | G312: كيلو | H312: =IFERROR(VLOOKUP($D312,القوائم!$A$2:$B$4,2,0),"") -> RAW | I312: =IF($H312="FIN","RTS",IF(ISNUMBER(SEARCH("مجمد",$E312)),"FRZ",IF(ISNUMBER(SEARCH("مبرد",$E312)),"CHL",IF(ISNUMBER(SEARCH("جاف",$E312)),"DRY",IF(ISNUMBER(SEARCH("استهلاك",$E312)),"CNS",IF(ISNUMBER(SEARCH("بيع",$E312)),"RTS","")))))) -> DRY | J312: =IF($H312="","",IF($N312=0,$Q312,SUMPRODUCT(($O$157:$O$590=$H312)*($P$157:$P$590=$I312)*$Q$157:$Q$590)+COUNTIFS($H$157:$H312,$H312,$I$157:$I312,$I312,$N$157:$N312,1))) -> 20 | M312: =IF($I312="","",COUNTIF($I$5:$I312,$I312)) -> 22 | N312: =IF($H312="","",IF(OR($H312<>$O312,$I312<>$P312),1,0)) -> 0 | O312: RAW | P312: DRY | Q312: 20 | R312: 331 | S312: 100 | T312: =IF(OR($R312="",$S312="",$S312=0),"",ROUND($R312/$S312,2)) -> 3.31
A313: 157 | B313: بوكس بينو | C313: Pino Box | D313: مواد خام | E313: استهلاكي | F313: =IF($H313="","",$H313&"-"&$I313&"-"&TEXT($J313,"000")) -> RAW-CNS-018 | G313: وحدة | H313: =IFERROR(VLOOKUP($D313,القوائم!$A$2:$B$4,2,0),"") -> RAW | I313: =IF($H313="FIN","RTS",IF(ISNUMBER(SEARCH("مجمد",$E313)),"FRZ",IF(ISNUMBER(SEARCH("مبرد",$E313)),"CHL",IF(ISNUMBER(SEARCH("جاف",$E313)),"DRY",IF(ISNUMBER(SEARCH("استهلاك",$E313)),"CNS",IF(ISNUMBER(SEARCH("بيع",$E313)),"RTS","")))))) -> CNS | J313: =IF($H313="","",IF($N313=0,$Q313,SUMPRODUCT(($O$157:$O$590=$H313)*($P$157:$P$590=$I313)*$Q$157:$Q$590)+COUNTIFS($H$157:$H313,$H313,$I$157:$I313,$I313,$N$157:$N313,1))) -> 18 | M313: =IF($I313="","",COUNTIF($I$5:$I313,$I313)) -> 19 | N313: =IF($H313="","",IF(OR($H313<>$O313,$I313<>$P313),1,0)) -> 0 | O313: RAW | P313: CNS | Q313: 18 | T313: =IF(OR($R313="",$S313="",$S313=0),"",ROUND($R313/$S313,2))
A314: 158 | B314: بومدورو | C314: Pomodoro | D314: مواد خام | E314: تخزين جاف | F314: =IF($H314="","",$H314&"-"&$I314&"-"&TEXT($J314,"000")) -> RAW-DRY-021 | G314: كيلو | H314: =IFERROR(VLOOKUP($D314,القوائم!$A$2:$B$4,2,0),"") -> RAW | I314: =IF($H314="FIN","RTS",IF(ISNUMBER(SEARCH("مجمد",$E314)),"FRZ",IF(ISNUMBER(SEARCH("مبرد",$E314)),"CHL",IF(ISNUMBER(SEARCH("جاف",$E314)),"DRY",IF(ISNUMBER(SEARCH("استهلاك",$E314)),"CNS",IF(ISNUMBER(SEARCH("بيع",$E314)),"RTS","")))))) -> DRY | J314: =IF($H314="","",IF($N314=0,$Q314,SUMPRODUCT(($O$157:$O$590=$H314)*($P$157:$P$590=$I314)*$Q$157:$Q$590)+COUNTIFS($H$157:$H314,$H314,$I$157:$I314,$I314,$N$157:$N314,1))) -> 21 | M314: =IF($I314="","",COUNTIF($I$5:$I314,$I314)) -> 23 | N314: =IF($H314="","",IF(OR($H314<>$O314,$I314<>$P314),1,0)) -> 0 | O314: RAW | P314: DRY | Q314: 21 | R314: 35 | S314: 100 | T314: =IF(OR($R314="",$S314="",$S314=0),"",ROUND($R314/$S314,2)) -> 0.35
...

Sheet جرد المجمّدة
A1: جرد المنتجات المجمّدة — تخزين مجمد
A2: تاريخ الجرد: __________ القائم بالجرد: __________ (تتحدّث تلقائيًا من السجل) | F2: ="عدد الأصناف: "&COUNTIF('إدخال وسجل المنتجات'!$I$5:$I$590,"FRZ") -> عدد الأصناف: 17
A3: م | B3: الكود | C3: اسم المنتج | D3: الاسم EN | E3: الفئة | F3: الوحدة | G3: الكمية الفعلية | H3: ملاحظات | J3: إجمالي الوزن (كجم)
A4: =IF($I4=0,"",1) -> 1 | B4: =IF($I4=0,"",INDEX('إدخال وسجل المنتجات'!$F$5:$F$590,$I4)) -> RAW-FRZ-001 | C4: =IF($I4=0,"",INDEX('إدخال وسجل المنتجات'!$B$5:$B$590,$I4)) -> كاس ثلج | D4: =IF($I4=0,"",INDEX('إدخال وسجل المنتجات'!$C$5:$C$590,$I4)) -> Cup Of Ice | E4: =IF($I4=0,"",INDEX('إدخال وسجل المنتجات'!$D$5:$D$590,$I4)) -> مواد خام | F4: =IF($I4=0,"",INDEX('إدخال وسجل المنتجات'!$G$5:$G$590,$I4)) -> وحدة | I4: =SUMPRODUCT(('إدخال وسجل المنتجات'!$I$5:$I$590="FRZ")*('إدخال وسجل المنتجات'!$M$5:$M$590=1)*(ROW('إدخال وسجل المنتجات'!$I$5:$I$590)-4)) -> 249 | J4: =IF($I4=0,"",IF($G4="","",$G4*IF(INDEX('إدخال وسجل المنتجات'!$U$5:$U$590,$I4)=0,1,INDEX('إدخال وسجل المنتجات'!$U$5:$U$590,$I4))))
A5: =IF($I5=0,"",2) -> 2 | B5: =IF($I5=0,"",INDEX('إدخال وسجل المنتجات'!$F$5:$F$590,$I5)) -> RAW-FRZ-002 | C5: =IF($I5=0,"",INDEX('إدخال وسجل المنتجات'!$B$5:$B$590,$I5)) -> ببروني | D5: =IF($I5=0,"",INDEX('إدخال وسجل المنتجات'!$C$5:$C$590,$I5)) -> Pepperoni | E5: =IF($I5=0,"",INDEX('إدخال وسجل المنتجات'!$D$5:$D$590,$I5)) -> مواد خام | F5: =IF($I5=0,"",INDEX('إدخال وسجل المنتجات'!$G$5:$G$590,$I5)) -> كيلو | I5: =SUMPRODUCT(('إدخال وسجل المنتجات'!$I$5:$I$590="FRZ")*('إدخال وسجل المنتجات'!$M$5:$M$590=2)*(ROW('إدخال وسجل المنتجات'!$I$5:$I$590)-4)) -> 284 | J5: =IF($I5=0,"",IF($G5="","",$G5*IF(INDEX('إدخال وسجل المنتجات'!$U$5:$U$590,$I5)=0,1,INDEX('إدخال وسجل المنتجات'!$U$5:$U$590,$I5))))
A6: =IF($I6=0,"",3) -> 3 | B6: =IF($I6=0,"",INDEX('إدخال وسجل المنتجات'!$F$5:$F$590,$I6)) -> RAW-FRZ-003 | C6: =IF($I6=0,"",INDEX('إدخال وسجل المنتجات'!$B$5:$B$590,$I6)) -> ثلج | D6: =IF($I6=0,"",INDEX('إدخال وسجل المنتجات'!$C$5:$C$590,$I6)) -> Ice | E6: =IF($I6=0,"",INDEX('إدخال وسجل المنتجات'!$D$5:$D$590,$I6)) -> مواد خام | F6: =IF($I6=0,"",INDEX('إدخال وسجل المنتجات'!$G$5:$G$590,$I6)) -> كيلو | I6: =SUMPRODUCT(('إدخال وسجل المنتجات'!$I$5:$I$590="FRZ")*('إدخال وسجل المنتجات'!$M$5:$M$590=3)*(ROW('إدخال وسجل المنتجات'!$I$5:$I$590)-4)) -> 323 | J6: =IF($I6=0,"",IF($G6="","",$G6*IF(INDEX('إدخال وسجل المنتجات'!$U$5:$U$590,$I6)=0,1,INDEX('إدخال وسجل المنتجات'!$U$5:$U$590,$I6))))
A7: =IF($I7=0,"",4) -> 4 | B7: =IF($I7=0,"",INDEX('إدخال وسجل المنتجات'!$F$5:$F$590,$I7)) -> RAW-FRZ-004 | C7: =IF($I7=0,"",INDEX('إدخال وسجل المنتجات'!$B$5:$B$590,$I7)) -> جمبري | D7: =IF($I7=0,"",INDEX('إدخال وسجل المنتجات'!$C$5:$C$590,$I7)) -> Shrimp | E7: =IF($I7=0,"",INDEX('إدخال وسجل المنتجات'!$D$5:$D$590,$I7)) -> مواد خام | F7: =IF($I7=0,"",INDEX('إدخال وسجل المنتجات'!$G$5:$G$590,$I7)) -> كيلو | I7: =SUMPRODUCT(('إدخال وسجل المنتجات'!$I$5:$I$590="FRZ")*('إدخال وسجل المنتجات'!$M$5:$M$590=4)*(ROW('إدخال وسجل المنتجات'!$I$5:$I$590)-4)) -> 338 | J7: =IF($I7=0,"",IF($G7="","",$G7*IF(INDEX('إدخال وسجل المنتجات'!$U$5:$U$590,$I7)=0,1,INDEX('إدخال وسجل المنتجات'!$U$5:$U$590,$I7))))
A8: =IF($I8=0,"",5) -> 5 | B8: =IF($I8=0,"",INDEX('إدخال وسجل المنتجات'!$F$5:$F$590,$I8)) -> RAW-FRZ-005 | C8: =IF($I8=0,"",INDEX('إدخال وسجل المنتجات'!$B$5:$B$590,$I8)) -> سلامي | D8: =IF($I8=0,"",INDEX('إدخال وسجل المنتجات'!$C$5:$C$590,$I8)) -> Salami | E8: =IF($I8=0,"",INDEX('إدخال وسجل المنتجات'!$D$5:$D$590,$I8)) -> مواد خام | F8: =IF($I8=0,"",INDEX('إدخال وسجل المنتجات'!$G$5:$G$590,$I8)) -> كيلو | I8: =SUMPRODUCT(('إدخال وسجل المنتجات'!$I$5:$I$590="FRZ")*('إدخال وسجل المنتجات'!$M$5:$M$590=5)*(ROW('إدخال وسجل المنتجات'!$I$5:$I$590)-4)) -> 407 | J8: =IF($I8=0,"",IF($G8="","",$G8*IF(INDEX('إدخال وسجل المنتجات'!$U$5:$U$590,$I8)=0,1,INDEX('إدخال وسجل المنتجات'!$U$5:$U$590,$I8))))
A9: =IF($I9=0,"",6) -> 6 | B9: =IF($I9=0,"",INDEX('إدخال وسجل المنتجات'!$F$5:$F$590,$I9)) -> RAW-FRZ-006 | C9: =IF($I9=0,"",INDEX('إدخال وسجل المنتجات'!$B$5:$B$590,$I9)) -> شرائح لحم امريكي | D9: =IF($I9=0,"",INDEX('إدخال وسجل المنتجات'!$C$5:$C$590,$I9)) -> Sliced Meat | E9: =IF($I9=0,"",INDEX('إدخال وسجل المنتجات'!$D$5:$D$590,$I9)) -> مواد خام | F9: =IF($I9=0,"",INDEX('إدخال وسجل المنتجات'!$G$5:$G$590,$I9)) -> كيلو | I9: =SUMPRODUCT(('إدخال وسجل المنتجات'!$I$5:$I$590="FRZ")*('إدخال وسجل المنتجات'!$M$5:$M$590=6)*(ROW('إدخال وسجل المنتجات'!$I$5:$I$590)-4)) -> 421 | J9: =IF($I9=0,"",IF($G9="","",$G9*IF(INDEX('إدخال وسجل المنتجات'!$U$5:$U$590,$I9)=0,1,INDEX('إدخال وسجل المنتجات'!$U$5:$U$590,$I9))))
A10: =IF($I10=0,"",7) -> 7 | B10: =IF($I10=0,"",INDEX('إدخال وسجل المنتجات'!$F$5:$F$590,$I10)) -> RAW-FRZ-007 | C10: =IF($I10=0,"",INDEX('إدخال وسجل المنتجات'!$B$5:$B$590,$I10)) -> شرائح لحم بقري | D10: =IF($I10=0,"",INDEX('إدخال وسجل المنتجات'!$C$5:$C$590,$I10)) -> Sliced Meat | E10: =IF($I10=0,"",INDEX('إدخال وسجل المنتجات'!$D$5:$D$590,$I10)) -> مواد خام | F10: =IF($I10=0,"",INDEX('إدخال وسجل المنتجات'!$G$5:$G$590,$I10)) -> كيلو | I10: =SUMPRODUCT(('إدخال وسجل المنتجات'!$I$5:$I$590="FRZ")*('إدخال وسجل المنتجات'!$M$5:$M$590=7)*(ROW('إدخال وسجل المنتجات'!$I$5:$I$590)-4)) -> 422 | J10: =IF($I10=0,"",IF($G10="","",$G10*IF(INDEX('إدخال وسجل المنتجات'!$U$5:$U$590,$I10)=0,1,INDEX('إدخال وسجل المنتجات'!$U$5:$U$590,$I10))))
A11: =IF($I11=0,"",8) -> 8 | B11: =IF($I11=0,"",INDEX('إدخال وسجل المنتجات'!$F$5:$F$590,$I11)) -> TRN-FRZ-001 | C11: =IF($I11=0,"",INDEX('إدخال وسجل المنتجات'!$B$5:$B$590,$I11)) -> صدور الدجاج المتبلة | D11: =IF($I11=0,"",INDEX('إدخال وسجل المنتجات'!$C$5:$C$590,$I11)) -> Marinated Chicken Breast | E11: =IF($I11=0,"",INDEX('إدخال وسجل المنتجات'!$D$5:$D$590,$I11)) -> مواد تحويلية | F11: =IF($I11=0,"",INDEX('إدخال وسجل المنتجات'!$G$5:$G$590,$I11)) -> كيلو | I11: =SUMPRODUCT(('إدخال وسجل المنتجات'!$I$5:$I$590="FRZ")*('إدخال وسجل المنتجات'!$M$5:$M$590=8)*(ROW('إدخال وسجل المنتجات'!$I$5:$I$590)-4)) -> 436 | J11: =IF($I11=0,"",IF($G11="","",$G11*IF(INDEX('إدخال وسجل المنتجات'!$U$5:$U$590,$I11)=0,1,INDEX('إدخال وسجل المنتجات'!$U$5:$U$590,$I11))))
A12: =IF($I12=0,"",9) -> 9 | B12: =IF($I12=0,"",INDEX('إدخال وسجل المنتجات'!$F$5:$F$590,$I12)) -> RAW-FRZ-008 | C12: =IF($I12=0,"",INDEX('إدخال وسجل المنتجات'!$B$5:$B$590,$I12)) -> صدور دجاج | D12: =IF($I12=0,"",INDEX('إدخال وسجل المنتجات'!$C$5:$C$590,$I12)) -> Chicken Breast | E12: =IF($I12=0,"",INDEX('إدخال وسجل المنتجات'!$D$5:$D$590,$I12)) -> مواد خام | F12: =IF($I12=0,"",INDEX('إدخال وسجل المنتجات'!$G$5:$G$590,$I12)) -> كيلو | I12: =SUMPRODUCT(('إدخال وسجل المنتجات'!$I$5:$I$590="FRZ")*('إدخال وسجل المنتجات'!$M$5:$M$590=9)*(ROW('إدخال وسجل المنتجات'!$I$5:$I$590)-4)) -> 437 | J12: =IF($I12=0,"",IF($G12="","",$G12*IF(INDEX('إدخال وسجل المنتجات'!$U$5:$U$590,$I12)=0,1,INDEX('إدخال وسجل المنتجات'!$U$5:$U$590,$I12))))
A13: =IF($I13=0,"",10) -> 10 | B13: =IF($I13=0,"",INDEX('إدخال وسجل المنتجات'!$F$5:$F$590,$I13)) -> RAW-FRZ-009 | C13: =IF($I13=0,"",INDEX('إدخال وسجل المنتجات'!$B$5:$B$590,$I13)) -> لحم البريسكت | D13: =IF($I13=0,"",INDEX('إدخال وسجل المنتجات'!$C$5:$C$590,$I13)) -> Meat Brisket | E13: =IF($I13=0,"",INDEX('إدخال وسجل المنتجات'!$D$5:$D$590,$I13)) -> مواد خام | F13: =IF($I13=0,"",INDEX('إدخال وسجل المنتجات'!$G$5:$G$590,$I13)) -> كيلو | I13: =SUMPRODUCT(('إدخال وسجل المنتجات'!$I$5:$I$590="FRZ")*('إدخال وسجل المنتجات'!$M$5:$M$590=10)*(ROW('إدخال وسجل المنتجات'!$I$5:$I$590)-4)) -> 534 | J13: =IF($I13=0,"",IF($G13="","",$G13*IF(INDEX('إدخال وسجل المنتجات'!$U$5:$U$590,$I13)=0,1,INDEX('إدخال وسجل المنتجات'!$U$5:$U$590,$I13))))
A14: =IF($I14=0,"",11) -> 11 | B14: =IF($I14=0,"",INDEX('إدخال وسجل المنتجات'!$F$5:$F$590,$I14)) -> RAW-FRZ-010 | C14: =IF($I14=0,"",INDEX('إدخال وسجل المنتجات'!$B$5:$B$590,$I14)) -> لحم بريسكت | D14: =IF($I14=0,"",INDEX('إدخال وسجل المنتجات'!$C$5:$C$590,$I14)) -> Meat Brisket | E14: =IF($I14=0,"",INDEX('إدخال وسجل المنتجات'!$D$5:$D$590,$I14)) -> مواد خام | F14: =IF($I14=0,"",INDEX('إدخال وسجل المنتجات'!$G$5:$G$590,$I14)) -> كيلو | I14: =SUMPRODUCT(('إدخال وسجل المنتجات'!$I$5:$I$590="FRZ")*('إدخال وسجل المنتجات'!$M$5:$M$590=11)*(ROW('إدخال وسجل المنتجات'!$I$5:$I$590)-4)) -> 535 | J14: =IF($I14=0,"",IF($G14="","",$G14*IF(INDEX('إدخال وسجل المنتجات'!$U$5:$U$590,$I14)=0,1,INDEX('إدخال وسجل المنتجات'!$U$5:$U$590,$I14))))
A15: =IF($I15=0,"",12) -> 12 | B15: =IF($I15=0,"",INDEX('إدخال وسجل المنتجات'!$F$5:$F$590,$I15)) -> RAW-FRZ-011 | C15: =IF($I15=0,"",INDEX('إدخال وسجل المنتجات'!$B$5:$B$590,$I15)) -> لحم بيبروني بلاك انجوس | D15: =IF($I15=0,"",INDEX('إدخال وسجل المنتجات'!$C$5:$C$590,$I15)) -> Meat Pepperoni Black Angus | E15: =IF($I15=0,"",INDEX('إدخال وسجل المنتجات'!$D$5:$D$590,$I15)) -> مواد خام | F15: =IF($I15=0,"",INDEX('إدخال وسجل المنتجات'!$G$5:$G$590,$I15)) -> كيلو | I15: =SUMPRODUCT(('إدخال وسجل المنتجات'!$I$5:$I$590="FRZ")*('إدخال وسجل المنتجات'!$M$5:$M$590=12)*(ROW('إدخال وسجل المنتجات'!$I$5:$I$590)-4)) -> 536 | J15: =IF($I15=0,"",IF($G15="","",$G15*IF(INDEX('إدخال وسجل المنتجات'!$U$5:$U$590,$I15)=0,1,INDEX('إدخال وسجل المنتجات'!$U$5:$U$590,$I15))))
A16: =IF($I16=0,"",13) -> 13 | B16: =IF($I16=0,"",INDEX('إدخال وسجل المنتجات'!$F$5:$F$590,$I16)) -> RAW-FRZ-012 | C16: =IF($I16=0,"",INDEX('إدخال وسجل المنتجات'!$B$5:$B$590,$I16)) -> لحم غنم | D16: =IF($I16=0,"",INDEX('إدخال وسجل المنتجات'!$C$5:$C$590,$I16)) -> Meat Lamb | E16: =IF($I16=0,"",INDEX('إدخال وسجل المنتجات'!$D$5:$D$590,$I16)) -> مواد خام | F16: =IF($I16=0,"",INDEX('إدخال وسجل المنتجات'!$G$5:$G$590,$I16)) -> كيلو | I16: =SUMPRODUCT(('إدخال وسجل المنتجات'!$I$5:$I$590="FRZ")*('إدخال وسجل المنتجات'!$M$5:$M$590=13)*(ROW('إدخال وسجل المنتجات'!$I$5:$I$590)-4)) -> 537 | J16: =IF($I16=0,"",IF($G16="","",$G16*IF(INDEX('إدخال وسجل المنتجات'!$U$5:$U$590,$I16)=0,1,INDEX('إدخال وسجل المنتجات'!$U$5:$U$590,$I16))))
A17: =IF($I17=0,"",14) -> 14 | B17: =IF($I17=0,"",INDEX('إدخال وسجل المنتجات'!$F$5:$F$590,$I17)) -> RAW-FRZ-013 | C17: =IF($I17=0,"",INDEX('إدخال وسجل المنتجات'!$B$5:$B$590,$I17)) -> لحم لازانيا مفروم | D17: =IF($I17=0,"",INDEX('إدخال وسجل المنتجات'!$C$5:$C$590,$I17)) -> Lasagna Ground Meat | E17: =IF($I17=0,"",INDEX('إدخال وسجل المنتجات'!$D$5:$D$590,$I17)) -> مواد خام | F17: =IF($I17=0,"",INDEX('إدخال وسجل المنتجات'!$G$5:$G$590,$I17)) -> كيلو | I17: =SUMPRODUCT(('إدخال وسجل المنتجات'!$I$5:$I$590="FRZ")*('إدخال وسجل المنتجات'!$M$5:$M$590=14)*(ROW('إدخال وسجل المنتجات'!$I$5:$I$590)-4)) -> 538 | J17: =IF($I17=0,"",IF($G17="","",$G17*IF(INDEX('إدخال وسجل المنتجات'!$U$5:$U$590,$I17)=0,1,INDEX('إدخال وسجل المنتجات'!$U$5:$U$590,$I17))))
A18: =IF($I18=0,"",15) -> 15 | B18: =IF($I18=0,"",INDEX('إدخال وسجل المنتجات'!$F$5:$F$590,$I18)) -> TRN-FRZ-002 | C18: =IF($I18=0,"",INDEX('إدخال وسجل المنتجات'!$B$5:$B$590,$I18)) -> لحم متبل | D18: =IF($I18=0,"",INDEX('إدخال وسجل المنتجات'!$C$5:$C$590,$I18)) -> Marinated Meat | E18: =IF($I18=0,"",INDEX('إدخال وسجل المنتجات'!$D$5:$D$590,$I18)) -> مواد تحويلية | F18: =IF($I18=0,"",INDEX('إدخال وسجل المنتجات'!$G$5:$G$590,$I18)) -> كيلو | I18: =SUMPRODUCT(('إدخال وسجل المنتجات'!$I$5:$I$590="FRZ")*('إدخال وسجل المنتجات'!$M$5:$M$590=15)*(ROW('إدخال وسجل المنتجات'!$I$5:$I$590)-4)) -> 539 | J18: =IF($I18=0,"",IF($G18="","",$G18*IF(INDEX('إدخال وسجل المنتجات'!$U$5:$U$590,$I18)=0,1,INDEX('إدخال وسجل المنتجات'!$U$5:$U$590,$I18))))
A19: =IF($I19=0,"",16) -> 16 | B19: =IF($I19=0,"",INDEX('إدخال وسجل المنتجات'!$F$5:$F$590,$I19)) -> RAW-FRZ-014 | C19: =IF($I19=0,"",INDEX('إدخال وسجل المنتجات'!$B$5:$B$590,$I19)) -> لحم مفروم | D19: =IF($I19=0,"",INDEX('إدخال وسجل المنتجات'!$C$5:$C$590,$I19)) -> Ground Meat | E19: =IF($I19=0,"",INDEX('إدخال وسجل المنتجات'!$D$5:$D$590,$I19)) -> مواد خام | F19: =IF($I19=0,"",INDEX('إدخال وسجل المنتجات'!$G$5:$G$590,$I19)) -> كيلو | I19: =SUMPRODUCT(('إدخال وسجل المنتجات'!$I$5:$I$590="FRZ")*('إدخال وسجل المنتجات'!$M$5:$M$590=16)*(ROW('إدخال وسجل المنتجات'!$I$5:$I$590)-4)) -> 540 | J19: =IF($I19=0,"",IF($G19="","",$G19*IF(INDEX('إدخال وسجل المنتجات'!$U$5:$U$590,$I19)=0,1,INDEX('إدخال وسجل المنتجات'!$U$5:$U$590,$I19))))
A20: =IF($I20=0,"",17) -> 17 | B20: =IF($I20=0,"",INDEX('إدخال وسجل المنتجات'!$F$5:$F$590,$I20)) -> RAW-FRZ-015 | C20: =IF($I20=0,"",INDEX('إدخال وسجل المنتجات'!$B$5:$B$590,$I20)) -> محار | D20: =IF($I20=0,"",INDEX('إدخال وسجل المنتجات'!$C$5:$C$590,$I20)) -> Clams | E20: =IF($I20=0,"",INDEX('إدخال وسجل المنتجات'!$D$5:$D$590,$I20)) -> مواد خام | F20: =IF($I20=0,"",INDEX('إدخال وسجل المنتجات'!$G$5:$G$590,$I20)) -> كيلو | I20: =SUMPRODUCT(('إدخال وسجل المنتجات'!$I$5:$I$590="FRZ")*('إدخال وسجل المنتجات'!$M$5:$M$590=17)*(ROW('إدخال وسجل المنتجات'!$I$5:$I$590)-4)) -> 549 | J20: =IF($I20=0,"",IF($G20="","",$G20*IF(INDEX('إدخال وسجل المنتجات'!$U$5:$U$590,$I20)=0,1,INDEX('إدخال وسجل المنتجات'!$U$5:$U$590,$I20))))
A21: =IF($I21=0,"",18) | B21: =IF($I21=0,"",INDEX('إدخال وسجل المنتجات'!$F$5:$F$590,$I21)) | C21: =IF($I21=0,"",INDEX('إدخال وسجل المنتجات'!$B$5:$B$590,$I21)) | D21: =IF($I21=0,"",INDEX('إدخال وسجل المنتجات'!$C$5:$C$590,$I21)) | E21: =IF($I21=0,"",INDEX('إدخال وسجل المنتجات'!$D$5:$D$590,$I21)) | F21: =IF($I21=0,"",INDEX('إدخال وسجل المنتجات'!$G$5:$G$590,$I21)) | I21: =SUMPRODUCT(('إدخال وسجل المنتجات'!$I$5:$I$590="FRZ")*('إدخال وسجل المنتجات'!$M$5:$M$590=18)*(ROW('إدخال وسجل المنتجات'!$I$5:$I$590)-4)) -> 0 | J21: =IF($I21=0,"",IF($G21="","",$G21*IF(INDEX('إدخال وسجل المنتجات'!$U$5:$U$590,$I21)=0,1,INDEX('إدخال وسجل المنتجات'!$U$5:$U$590,$I21))))
A22: =IF($I22=0,"",19) | B22: =IF($I22=0,"",INDEX('إدخال وسجل المنتجات'!$F$5:$F$590,$I22)) | C22: =IF($I22=0,"",INDEX('إدخال وسجل المنتجات'!$B$5:$B$590,$I22)) | D22: =IF($I22=0,"",INDEX('إدخال وسجل المنتجات'!$C$5:$C$590,$I22)) | E22: =IF($I22=0,"",INDEX('إدخال وسجل المنتجات'!$D$5:$D$590,$I22)) | F22: =IF($I22=0,"",INDEX('إدخال وسجل المنتجات'!$G$5:$G$590,$I22)) | I22: =SUMPRODUCT(('إدخال وسجل المنتجات'!$I$5:$I$590="FRZ")*('إدخال وسجل المنتجات'!$M$5:$M$590=19)*(ROW('إدخال وسجل المنتجات'!$I$5:$I$590)-4)) -> 0 | J22: =IF($I22=0,"",IF($G22="","",$G22*IF(INDEX('إدخال وسجل المنتجات'!$U$5:$U$590,$I22)=0,1,INDEX('إدخال وسجل المنتجات'!$U$5:$U$590,$I22))))
A23: =IF($I23=0,"",20) | B23: =IF($I23=0,"",INDEX('إدخال وسجل المنتجات'!$F$5:$F$590,$I23)) | C23: =IF($I23=0,"",INDEX('إدخال وسجل المنتجات'!$B$5:$B$590,$I23)) | D23: =IF($I23=0,"",INDEX('إدخال وسجل المنتجات'!$C$5:$C$590,$I23)) | E23: =IF($I23=0,"",INDEX('إدخال وسجل المنتجات'!$D$5:$D$590,$I23)) | F23: =IF($I23=0,"",INDEX('إدخال وسجل المنتجات'!$G$5:$G$590,$I23)) | I23: =SUMPRODUCT(('إدخال وسجل المنتجات'!$I$5:$I$590="FRZ")*('إدخال وسجل المنتجات'!$M$5:$M$590=20)*(ROW('إدخال وسجل المنتجات'!$I$5:$I$590)-4)) -> 0 | J23: =IF($I23=0,"",IF($G23="","",$G23*IF(INDEX('إدخال وسجل المنتجات'!$U$5:$U$590,$I23)=0,1,INDEX('إدخال وسجل المنتجات'!$U$5:$U$590,$I23))))
A24: =IF($I24=0,"",21) | B24: =IF($I24=0,"",INDEX('إدخال وسجل المنتجات'!$F$5:$F$590,$I24)) | C24: =IF($I24=0,"",INDEX('إدخال وسجل المنتجات'!$B$5:$B$590,$I24)) | D24: =IF($I24=0,"",INDEX('إدخال وسجل المنتجات'!$C$5:$C$590,$I24)) | E24: =IF($I24=0,"",INDEX('إدخال وسجل المنتجات'!$D$5:$D$590,$I24)) | F24: =IF($I24=0,"",INDEX('إدخال وسجل المنتجات'!$G$5:$G$590,$I24)) | I24: =SUMPRODUCT(('إدخال وسجل المنتجات'!$I$5:$I$590="FRZ")*('إدخال وسجل المنتجات'!$M$5:$M$590=21)*(ROW('إدخال وسجل المنتجات'!$I$5:$I$590)-4)) -> 0 | J24: =IF($I24=0,"",IF($G24="","",$G24*IF(INDEX('إدخال وسجل المنتجات'!$U$5:$U$590,$I24)=0,1,INDEX('إدخال وسجل المنتجات'!$U$5:$U$590,$I24))))
A25: =IF($I25=0,"",22) | B25: =IF($I25=0,"",INDEX('إدخال وسجل المنتجات'!$F$5:$F$590,$I25)) | C25: =IF($I25=0,"",INDEX('إدخال وسجل المنتجات'!$B$5:$B$590,$I25)) | D25: =IF($I25=0,"",INDEX('إدخال وسجل المنتجات'!$C$5:$C$590,$I25)) | E25: =IF($I25=0,"",INDEX('إدخال وسجل المنتجات'!$D$5:$D$590,$I25)) | F25: =IF($I25=0,"",INDEX('إدخال وسجل المنتجات'!$G$5:$G$590,$I25)) | I25: =SUMPRODUCT(('إدخال وسجل المنتجات'!$I$5:$I$590="FRZ")*('إدخال وسجل المنتجات'!$M$5:$M$590=22)*(ROW('إدخال وسجل المنتجات'!$I$5:$I$590)-4)) -> 0 | J25: =IF($I25=0,"",IF($G25="","",$G25*IF(INDEX('إدخال وسجل المنتجات'!$U$5:$U$590,$I25)=0,1,INDEX('إدخال وسجل المنتجات'!$U$5:$U$590,$I25))))
A26: =IF($I26=0,"",23) | B26: =IF($I26=0,"",INDEX('إدخال وسجل المنتجات'!$F$5:$F$590,$I26)) | C26: =IF($I26=0,"",INDEX('إدخال وسجل المنتجات'!$B$5:$B$590,$I26)) | D26: =IF($I26=0,"",INDEX('إدخال وسجل المنتجات'!$C$5:$C$590,$I26)) | E26: =IF($I26=0,"",INDEX('إدخال وسجل المنتجات'!$D$5:$D$590,$I26)) | F26: =IF($I26=0,"",INDEX('إدخال وسجل المنتجات'!$G$5:$G$590,$I26)) | I26: =SUMPRODUCT(('إدخال وسجل المنتجات'!$I$5:$I$590="FRZ")*('إدخال وسجل المنتجات'!$M$5:$M$590=23)*(ROW('إدخال وسجل المنتجات'!$I$5:$I$590)-4)) -> 0 | J26: =IF($I26=0,"",IF($G26="","",$G26*IF(INDEX('إدخال وسجل المنتجات'!$U$5:$U$590,$I26)=0,1,INDEX('إدخال وسجل المنتجات'!$U$5:$U$590,$I26))))
A27: =IF($I27=0,"",24) | B27: =IF($I27=0,"",INDEX('إدخال وسجل المنتجات'!$F$5:$F$590,$I27)) | C27: =IF($I27=0,"",INDEX('إدخال وسجل المنتجات'!$B$5:$B$590,$I27)) | D27: =IF($I27=0,"",INDEX('إدخال وسجل المنتجات'!$C$5:$C$590,$I27)) | E27: =IF($I27=0,"",INDEX('إدخال وسجل المنتجات'!$D$5:$D$590,$I27)) | F27: =IF($I27=0,"",INDEX('إدخال وسجل المنتجات'!$G$5:$G$590,$I27)) | I27: =SUMPRODUCT(('إدخال وسجل المنتجات'!$I$5:$I$590="FRZ")*('إدخال وسجل المنتجات'!$M$5:$M$590=24)*(ROW('إدخال وسجل المنتجات'!$I$5:$I$590)-4)) -> 0 | J27: =IF($I27=0,"",IF($G27="","",$G27*IF(INDEX('إدخال وسجل المنتجات'!$U$5:$U$590,$I27)=0,1,INDEX('إدخال وسجل المنتجات'!$U$5:$U$590,$I27))))
A28: =IF($I28=0,"",25) | B28: =IF($I28=0,"",INDEX('إدخال وسجل المنتجات'!$F$5:$F$590,$I28)) | C28: =IF($I28=0,"",INDEX('إدخال وسجل المنتجات'!$B$5:$B$590,$I28)) | D28: =IF($I28=0,"",INDEX('إدخال وسجل المنتجات'!$C$5:$C$590,$I28)) | E28: =IF($I28=0,"",INDEX('إدخال وسجل المنتجات'!$D$5:$D$590,$I28)) | F28: =IF($I28=0,"",INDEX('إدخال وسجل المنتجات'!$G$5:$G$590,$I28)) | I28: =SUMPRODUCT(('إدخال وسجل المنتجات'!$I$5:$I$590="FRZ")*('إدخال وسجل المنتجات'!$M$5:$M$590=25)*(ROW('إدخال وسجل المنتجات'!$I$5:$I$590)-4)) -> 0 | J28: =IF($I28=0,"",IF($G28="","",$G28*IF(INDEX('إدخال وسجل المنتجات'!$U$5:$U$590,$I28)=0,1,INDEX('إدخال وسجل المنتجات'!$U$5:$U$590,$I28))))
A29: =IF($I29=0,"",26) | B29: =IF($I29=0,"",INDEX('إدخال وسجل المنتجات'!$F$5:$F$590,$I29)) | C29: =IF($I29=0,"",INDEX('إدخال وسجل المنتجات'!$B$5:$B$590,$I29)) | D29: =IF($I29=0,"",INDEX('إدخال وسجل المنتجات'!$C$5:$C$590,$I29)) | E29: =IF($I29=0,"",INDEX('إدخال وسجل المنتجات'!$D$5:$D$590,$I29)) | F29: =IF($I29=0,"",INDEX('إدخال وسجل المنتجات'!$G$5:$G$590,$I29)) | I29: =SUMPRODUCT(('إدخال وسجل المنتجات'!$I$5:$I$590="FRZ")*('إدخال وسجل المنتجات'!$M$5:$M$590=26)*(ROW('إدخال وسجل المنتجات'!$I$5:$I$590)-4)) -> 0 | J29: =IF($I29=0,"",IF($G29="","",$G29*IF(INDEX('إدخال وسجل المنتجات'!$U$5:$U$590,$I29)=0,1,INDEX('إدخال وسجل المنتجات'!$U$5:$U$590,$I29))))
A30: =IF($I30=0,"",27) | B30: =IF($I30=0,"",INDEX('إدخال وسجل المنتجات'!$F$5:$F$590,$I30)) | C30: =IF($I30=0,"",INDEX('إدخال وسجل المنتجات'!$B$5:$B$590,$I30)) | D30: =IF($I30=0,"",INDEX('إدخال وسجل المنتجات'!$C$5:$C$590,$I30)) | E30: =IF($I30=0,"",INDEX('إدخال وسجل المنتجات'!$D$5:$D$590,$I30)) | F30: =IF($I30=0,"",INDEX('إدخال وسجل المنتجات'!$G$5:$G$590,$I30)) | I30: =SUMPRODUCT(('إدخال وسجل المنتجات'!$I$5:$I$590="FRZ")*('إدخال وسجل المنتجات'!$M$5:$M$590=27)*(ROW('إدخال وسجل المنتجات'!$I$5:$I$590)-4)) -> 0 | J30: =IF($I30=0,"",IF($G30="","",$G30*IF(INDEX('إدخال وسجل المنتجات'!$U$5:$U$590,$I30)=0,1,INDEX('إدخال وسجل المنتجات'!$U$5:$U$590,$I30))))
A31: =IF($I31=0,"",28) | B31: =IF($I31=0,"",INDEX('إدخال وسجل المنتجات'!$F$5:$F$590,$I31)) | C31: =IF($I31=0,"",INDEX('إدخال وسجل المنتجات'!$B$5:$B$590,$I31)) | D31: =IF($I31=0,"",INDEX('إدخال وسجل المنتجات'!$C$5:$C$590,$I31)) | E31: =IF($I31=0,"",INDEX('إدخال وسجل المنتجات'!$D$5:$D$590,$I31)) | F31: =IF($I31=0,"",INDEX('إدخال وسجل المنتجات'!$G$5:$G$590,$I31)) | I31: =SUMPRODUCT(('إدخال وسجل المنتجات'!$I$5:$I$590="FRZ")*('إدخال وسجل المنتجات'!$M$5:$M$590=28)*(ROW('إدخال وسجل المنتجات'!$I$5:$I$590)-4)) -> 0 | J31: =IF($I31=0,"",IF($G31="","",$G31*IF(INDEX('إدخال وسجل المنتجات'!$U$5:$U$590,$I31)=0,1,INDEX('إدخال وسجل المنتجات'!$U$5:$U$590,$I31))))
A32: =IF($I32=0,"",29) | B32: =IF($I32=0,"",INDEX('إدخال وسجل المنتجات'!$F$5:$F$590,$I32)) | C32: =IF($I32=0,"",INDEX('إدخال وسجل المنتجات'!$B$5:$B$590,$I32)) | D32: =IF($I32=0,"",INDEX('إدخال وسجل المنتجات'!$C$5:$C$590,$I32)) | E32: =IF($I32=0,"",INDEX('إدخال وسجل المنتجات'!$D$5:$D$590,$I32)) | F32: =IF($I32=0,"",INDEX('إدخال وسجل المنتجات'!$G$5:$G$590,$I32)) | I32: =SUMPRODUCT(('إدخال وسجل المنتجات'!$I$5:$I$590="FRZ")*('إدخال وسجل المنتجات'!$M$5:$M$590=29)*(ROW('إدخال وسجل المنتجات'!$I$5:$I$590)-4)) -> 0 | J32: =IF($I32=0,"",IF($G32="","",$G32*IF(INDEX('إدخال وسجل المنتجات'!$U$5:$U$590,$I32)=0,1,INDEX('إدخال وسجل المنتجات'!$U$5:$U$590,$I32))))
A33: =IF($I33=0,"",30) | B33: =IF($I33=0,"",INDEX('إدخال وسجل المنتجات'!$F$5:$F$590,$I33)) | C33: =IF($I33=0,"",INDEX('إدخال وسجل المنتجات'!$B$5:$B$590,$I33)) | D33: =IF($I33=0,"",INDEX('إدخال وسجل المنتجات'!$C$5:$C$590,$I33)) | E33: =IF($I33=0,"",INDEX('إدخال وسجل المنتجات'!$D$5:$D$590,$I33)) | F33: =IF($I33=0,"",INDEX('إدخال وسجل المنتجات'!$G$5:$G$590,$I33)) | I33: =SUMPRODUCT(('إدخال وسجل المنتجات'!$I$5:$I$590="FRZ")*('إدخال وسجل المنتجات'!$M$5:$M$590=30)*(ROW('إدخال وسجل المنتجات'!$I$5:$I$590)-4)) -> 0 | J33: =IF($I33=0,"",IF($G33="","",$G33*IF(INDEX('إدخال وسجل المنتجات'!$U$5:$U$590,$I33)=0,1,INDEX('إدخال وسجل المنتجات'!$U$5:$U$590,$I33))))
A34: =IF($I34=0,"",31) | B34: =IF($I34=0,"",INDEX('إدخال وسجل المنتجات'!$F$5:$F$590,$I34)) | C34: =IF($I34=0,"",INDEX('إدخال وسجل المنتجات'!$B$5:$B$590,$I34)) | D34: =IF($I34=0,"",INDEX('إدخال وسجل المنتجات'!$C$5:$C$590,$I34)) | E34: =IF($I34=0,"",INDEX('إدخال وسجل المنتجات'!$D$5:$D$590,$I34)) | F34: =IF($I34=0,"",INDEX('إدخال وسجل المنتجات'!$G$5:$G$590,$I34)) | I34: =SUMPRODUCT(('إدخال وسجل المنتجات'!$I$5:$I$590="FRZ")*('إدخال وسجل المنتجات'!$M$5:$M$590=31)*(ROW('إدخال وسجل المنتجات'!$I$5:$I$590)-4)) -> 0 | J34: =IF($I34=0,"",IF($G34="","",$G34*IF(INDEX('إدخال وسجل المنتجات'!$U$5:$U$590,$I34)=0,1,INDEX('إدخال وسجل المنتجات'!$U$5:$U$590,$I34))))
A35: =IF($I35=0,"",32) | B35: =IF($I35=0,"",INDEX('إدخال وسجل المنتجات'!$F$5:$F$590,$I35)) | C35: =IF($I35=0,"",INDEX('إدخال وسجل المنتجات'!$B$5:$B$590,$I35)) | D35: =IF($I35=0,"",INDEX('إدخال وسجل المنتجات'!$C$5:$C$590,$I35)) | E35: =IF($I35=0,"",INDEX('إدخال وسجل المنتجات'!$D$5:$D$590,$I35)) | F35: =IF($I35=0,"",INDEX('إدخال وسجل المنتجات'!$G$5:$G$590,$I35)) | I35: =SUMPRODUCT(('إدخال وسجل المنتجات'!$I$5:$I$590="FRZ")*('إدخال وسجل المنتجات'!$M$5:$M$590=32)*(ROW('إدخال وسجل المنتجات'!$I$5:$I$590)-4)) -> 0 | J35: =IF($I35=0,"",IF($G35="","",$G35*IF(INDEX('إدخال وسجل المنتجات'!$U$5:$U$590,$I35)=0,1,INDEX('إدخال وسجل المنتجات'!$U$5:$U$590,$I35))))
A36: =IF($I36=0,"",33) | B36: =IF($I36=0,"",INDEX('إدخال وسجل المنتجات'!$F$5:$F$590,$I36)) | C36: =IF($I36=0,"",INDEX('إدخال وسجل المنتجات'!$B$5:$B$590,$I36)) | D36: =IF($I36=0,"",INDEX('إدخال وسجل المنتجات'!$C$5:$C$590,$I36)) | E36: =IF($I36=0,"",INDEX('إدخال وسجل المنتجات'!$D$5:$D$590,$I36)) | F36: =IF($I36=0,"",INDEX('إدخال وسجل المنتجات'!$G$5:$G$590,$I36)) | I36: =SUMPRODUCT(('إدخال وسجل المنتجات'!$I$5:$I$590="FRZ")*('إدخال وسجل المنتجات'!$M$5:$M$590=33)*(ROW('إدخال وسجل المنتجات'!$I$5:$I$590)-4)) -> 0 | J36: =IF($I36=0,"",IF($G36="","",$G36*IF(INDEX('إدخال وسجل المنتجات'!$U$5:$U$590,$I36)=0,1,INDEX('إدخال وسجل المنتجات'!$U$5:$U$590,$I36))))
A37: =IF($I37=0,"",34) | B37: =IF($I37=0,"",INDEX('إدخال وسجل المنتجات'!$F$5:$F$590,$I37)) | C37: =IF($I37=0,"",INDEX('إدخال وسجل المنتجات'!$B$5:$B$590,$I37)) | D37: =IF($I37=0,"",INDEX('إدخال وسجل المنتجات'!$C$5:$C$590,$I37)) | E37: =IF($I37=0,"",INDEX('إدخال وسجل المنتجات'!$D$5:$D$590,$I37)) | F37: =IF($I37=0,"",INDEX('إدخال وسجل المنتجات'!$G$5:$G$590,$I37)) | I37: =SUMPRODUCT(('إدخال وسجل المنتجات'!$I$5:$I$590="FRZ")*('إدخال وسجل المنتجات'!$M$5:$M$590=34)*(ROW('إدخال وسجل المنتجات'!$I$5:$I$590)-4)) -> 0 | J37: =IF($I37=0,"",IF($G37="","",$G37*IF(INDEX('إدخال وسجل المنتجات'!$U$5:$U$590,$I37)=0,1,INDEX('إدخال وسجل المنتجات'!$U$5:$U$590,$I37))))
A38: =IF($I38=0,"",35) | B38: =IF($I38=0,"",INDEX('إدخال وسجل المنتجات'!$F$5:$F$590,$I38)) | C38: =IF($I38=0,"",INDEX('إدخال وسجل المنتجات'!$B$5:$B$590,$I38)) | D38: =IF($I38=0,"",INDEX('إدخال وسجل المنتجات'!$C$5:$C$590,$I38)) | E38: =IF($I38=0,"",INDEX('إدخال وسجل المنتجات'!$D$5:$D$590,$I38)) | F38: =IF($I38=0,"",INDEX('إدخال وسجل المنتجات'!$G$5:$G$590,$I38)) | I38: =SUMPRODUCT(('إدخال وسجل المنتجات'!$I$5:$I$590="FRZ")*('إدخال وسجل المنتجات'!$M$5:$M$590=35)*(ROW('إدخال وسجل المنتجات'!$I$5:$I$590)-4)) -> 0 | J38: =IF($I38=0,"",IF($G38="","",$G38*IF(INDEX('إدخال وسجل المنتجات'!$U$5:$U$590,$I38)=0,1,INDEX('إدخال وسجل المنتجات'!$U$5:$U$590,$I38))))
A39: =IF($I39=0,"",36) | B39: =IF($I39=0,"",INDEX('إدخال وسجل المنتجات'!$F$5:$F$590,$I39)) | C39: =IF($I39=0,"",INDEX('إدخال وسجل المنتجات'!$B$5:$B$590,$I39)) | D39: =IF($I39=0,"",INDEX('إدخال وسجل المنتجات'!$C$5:$C$590,$I39)) | E39: =IF($I39=0,"",INDEX('إدخال وسجل المنتجات'!$D$5:$D$590,$I39)) | F39: =IF($I39=0,"",INDEX('إدخال وسجل المنتجات'!$G$5:$G$590,$I39)) | I39: =SUMPRODUCT(('إدخال وسجل المنتجات'!$I$5:$I$590="FRZ")*('إدخال وسجل المنتجات'!$M$5:$M$590=36)*(ROW('إدخال وسجل المنتجات'!$I$5:$I$590)-4)) -> 0 | J39: =IF($I39=0,"",IF($G39="","",$G39*IF(INDEX('إدخال وسجل المنتجات'!$U$5:$U$590,$I39)=0,1,INDEX('إدخال وسجل المنتجات'!$U$5:$U$590,$I39))))
A40: =IF($I40=0,"",37) | B40: =IF($I40=0,"",INDEX('إدخال وسجل المنتجات'!$F$5:$F$590,$I40)) | C40: =IF($I40=0,"",INDEX('إدخال وسجل المنتجات'!$B$5:$B$590,$I40)) | D40: =IF($I40=0,"",INDEX('إدخال وسجل المنتجات'!$C$5:$C$590,$I40)) | E40: =IF($I40=0,"",INDEX('إدخال وسجل المنتجات'!$D$5:$D$590,$I40)) | F40: =IF($I40=0,"",INDEX('إدخال وسجل المنتجات'!$G$5:$G$590,$I40)) | I40: =SUMPRODUCT(('إدخال وسجل المنتجات'!$I$5:$I$590="FRZ")*('إدخال وسجل المنتجات'!$M$5:$M$590=37)*(ROW('إدخال وسجل المنتجات'!$I$5:$I$590)-4)) -> 0 | J40: =IF($I40=0,"",IF($G40="","",$G40*IF(INDEX('إدخال وسجل المنتجات'!$U$5:$U$590,$I40)=0,1,INDEX('إدخال وسجل المنتجات'!$U$5:$U$590,$I40))))
A41: =IF($I41=0,"",38) | B41: =IF($I41=0,"",INDEX('إدخال وسجل المنتجات'!$F$5:$F$590,$I41)) | C41: =IF($I41=0,"",INDEX('إدخال وسجل المنتجات'!$B$5:$B$590,$I41)) | D41: =IF($I41=0,"",INDEX('إدخال وسجل المنتجات'!$C$5:$C$590,$I41)) | E41: =IF($I41=0,"",INDEX('إدخال وسجل المنتجات'!$D$5:$D$590,$I41)) | F41: =IF($I41=0,"",INDEX('إدخال وسجل المنتجات'!$G$5:$G$590,$I41)) | I41: =SUMPRODUCT(('إدخال وسجل المنتجات'!$I$5:$I$590="FRZ")*('إدخال وسجل المنتجات'!$M$5:$M$590=38)*(ROW('إدخال وسجل المنتجات'!$I$5:$I$590)-4)) -> 0 | J41: =IF($I41=0,"",IF($G41="","",$G41*IF(INDEX('إدخال وسجل المنتجات'!$U$5:$U$590,$I41)=0,1,INDEX('إدخال وسجل المنتجات'!$U$5:$U$590,$I41))))
A42: =IF($I42=0,"",39) | B42: =IF($I42=0,"",INDEX('إدخال وسجل المنتجات'!$F$5:$F$590,$I42)) | C42: =IF($I42=0,"",INDEX('إدخال وسجل المنتجات'!$B$5:$B$590,$I42)) | D42: =IF($I42=0,"",INDEX('إدخال وسجل المنتجات'!$C$5:$C$590,$I42)) | E42: =IF($I42=0,"",INDEX('إدخال وسجل المنتجات'!$D$5:$D$590,$I42)) | F42: =IF($I42=0,"",INDEX('إدخال وسجل المنتجات'!$G$5:$G$590,$I42)) | I42: =SUMPRODUCT(('إدخال وسجل المنتجات'!$I$5:$I$590="FRZ")*('إدخال وسجل المنتجات'!$M$5:$M$590=39)*(ROW('إدخال وسجل المنتجات'!$I$5:$I$590)-4)) -> 0 | J42: =IF($I42=0,"",IF($G42="","",$G42*IF(INDEX('إدخال وسجل المنتجات'!$U$5:$U$590,$I42)=0,1,INDEX('إدخال وسجل المنتجات'!$U$5:$U$590,$I42))))
A43: =IF($I43=0,"",40) | B43: =IF($I43=0,"",INDEX('إدخال وسجل المنتجات'!$F$5:$F$590,$I43)) | C43: =IF($I43=0,"",INDEX('إدخال وسجل المنتجات'!$B$5:$B$590,$I43)) | D43: =IF($I43=0,"",INDEX('إدخال وسجل المنتجات'!$C$5:$C$590,$I43)) | E43: =IF($I43=0,"",INDEX('إدخال وسجل المنتجات'!$D$5:$D$590,$I43)) | F43: =IF($I43=0,"",INDEX('إدخال وسجل المنتجات'!$G$5:$G$590,$I43)) | I43: =SUMPRODUCT(('إدخال وسجل المنتجات'!$I$5:$I$590="FRZ")*('إدخال وسجل المنتجات'!$M$5:$M$590=40)*(ROW('إدخال وسجل المنتجات'!$I$5:$I$590)-4)) -> 0 | J43: =IF($I43=0,"",IF($G43="","",$G43*IF(INDEX('إدخال وسجل المنتجات'!$U$5:$U$590,$I43)=0,1,INDEX('إدخال وسجل المنتجات'!$U$5:$U$590,$I43))))
A44: =IF($I44=0,"",41) | B44: =IF($I44=0,"",INDEX('إدخال وسجل المنتجات'!$F$5:$F$590,$I44)) | C44: =IF($I44=0,"",INDEX('إدخال وسجل المنتجات'!$B$5:$B$590,$I44)) | D44: =IF($I44=0,"",INDEX('إدخال وسجل المنتجات'!$C$5:$C$590,$I44)) | E44: =IF($I44=0,"",INDEX('إدخال وسجل المنتجات'!$D$5:$D$590,$I44)) | F44: =IF($I44=0,"",INDEX('إدخال وسجل المنتجات'!$G$5:$G$590,$I44)) | I44: =SUMPRODUCT(('إدخال وسجل المنتجات'!$I$5:$I$590="FRZ")*('إدخال وسجل المنتجات'!$M$5:$M$590=41)*(ROW('إدخال وسجل المنتجات'!$I$5:$I$590)-4)) -> 0 | J44: =IF($I44=0,"",IF($G44="","",$G44*IF(INDEX('إدخال وسجل المنتجات'!$U$5:$U$590,$I44)=0,1,INDEX('إدخال وسجل المنتجات'!$U$5:$U$590,$I44))))
A45: =IF($I45=0,"",42) | B45: =IF($I45=0,"",INDEX('إدخال وسجل المنتجات'!$F$5:$F$590,$I45)) | C45: =IF($I45=0,"",INDEX('إدخال وسجل المنتجات'!$B$5:$B$590,$I45)) | D45: =IF($I45=0,"",INDEX('إدخال وسجل المنتجات'!$C$5:$C$590,$I45)) | E45: =IF($I45=0,"",INDEX('إدخال وسجل المنتجات'!$D$5:$D$590,$I45)) | F45: =IF($I45=0,"",INDEX('إدخال وسجل المنتجات'!$G$5:$G$590,$I45)) | I45: =SUMPRODUCT(('إدخال وسجل المنتجات'!$I$5:$I$590="FRZ")*('إدخال وسجل المنتجات'!$M$5:$M$590=42)*(ROW('إدخال وسجل المنتجات'!$I$5:$I$590)-4)) -> 0 | J45: =IF($I45=0,"",IF($G45="","",$G45*IF(INDEX('إدخال وسجل المنتجات'!$U$5:$U$590,$I45)=0,1,INDEX('إدخال وسجل المنتجات'!$U$5:$U$590,$I45))))
A46: =IF($I46=0,"",43) | B46: =IF($I46=0,"",INDEX('إدخال وسجل المنتجات'!$F$5:$F$590,$I46)) | C46: =IF($I46=0,"",INDEX('إدخال وسجل المنتجات'!$B$5:$B$590,$I46)) | D46: =IF($I46=0,"",INDEX('إدخال وسجل المنتجات'!$C$5:$C$590,$I46)) | E46: =IF($I46=0,"",INDEX('إدخال وسجل المنتجات'!$D$5:$D$590,$I46)) | F46: =IF($I46=0,"",INDEX('إدخال وسجل المنتجات'!$G$5:$G$590,$I46)) | I46: =SUMPRODUCT(('إدخال وسجل المنتجات'!$I$5:$I$590="FRZ")*('إدخال وسجل المنتجات'!$M$5:$M$590=43)*(ROW('إدخال وسجل المنتجات'!$I$5:$I$590)-4)) -> 0 | J46: =IF($I46=0,"",IF($G46="","",$G46*IF(INDEX('إدخال وسجل المنتجات'!$U$5:$U$590,$I46)=0,1,INDEX('إدخال وسجل المنتجات'!$U$5:$U$590,$I46))))
A47: =IF($I47=0,"",44) | B47: =IF($I47=0,"",INDEX('إدخال وسجل المنتجات'!$F$5:$F$590,$I47)) | C47: =IF($I47=0,"",INDEX('إدخال وسجل المنتجات'!$B$5:$B$590,$I47)) | D47: =IF($I47=0,"",INDEX('إدخال وسجل المنتجات'!$C$5:$C$590,$I47)) | E47: =IF($I47=0,"",INDEX('إدخال وسجل المنتجات'!$D$5:$D$590,$I47)) | F47: =IF($I47=0,"",INDEX('إدخال وسجل المنتجات'!$G$5:$G$590,$I47)) | I47: =SUMPRODUCT(('إدخال وسجل المنتجات'!$I$5:$I$590="FRZ")*('إدخال وسجل المنتجات'!$M$5:$M$590=44)*(ROW('إدخال وسجل المنتجات'!$I$5:$I$590)-4)) -> 0 | J47: =IF($I47=0,"",IF($G47="","",$G47*IF(INDEX('إدخال وسجل المنتجات'!$U$5:$U$590,$I47)=0,1,INDEX('إدخال وسجل المنتجات'!$U$5:$U$590,$I47))))
A48: =IF($I48=0,"",45) | B48: =IF($I48=0,"",INDEX('إدخال وسجل المنتجات'!$F$5:$F$590,$I48)) | C48: =IF($I48=0,"",INDEX('إدخال وسجل المنتجات'!$B$5:$B$590,$I48)) | D48: =IF($I48=0,"",INDEX('إدخال وسجل المنتجات'!$C$5:$C$590,$I48)) | E48: =IF($I48=0,"",INDEX('إدخال وسجل المنتجات'!$D$5:$D$590,$I48)) | F48: =IF($I48=0,"",INDEX('إدخال وسجل المنتجات'!$G$5:$G$590,$I48)) | I48: =SUMPRODUCT(('إدخال وسجل المنتجات'!$I$5:$I$590="FRZ")*('إدخال وسجل المنتجات'!$M$5:$M$590=45)*(ROW('إدخال وسجل المنتجات'!$I$5:$I$590)-4)) -> 0 | J48: =IF($I48=0,"",IF($G48="","",$G48*IF(INDEX('إدخال وسجل المنتجات'!$U$5:$U$590,$I48)=0,1,INDEX('إدخال وسجل المنتجات'!$U$5:$U$590,$I48))))
A49: =IF($I49=0,"",46) | B49: =IF($I49=0,"",INDEX('إدخال وسجل المنتجات'!$F$5:$F$590,$I49)) | C49: =IF($I49=0,"",INDEX('إدخال وسجل المنتجات'!$B$5:$B$590,$I49)) | D49: =IF($I49=0,"",INDEX('إدخال وسجل المنتجات'!$C$5:$C$590,$I49)) | E49: =IF($I49=0,"",INDEX('إدخال وسجل المنتجات'!$D$5:$D$590,$I49)) | F49: =IF($I49=0,"",INDEX('إدخال وسجل المنتجات'!$G$5:$G$590,$I49)) | I49: =SUMPRODUCT(('إدخال وسجل المنتجات'!$I$5:$I$590="FRZ")*('إدخال وسجل المنتجات'!$M$5:$M$590=46)*(ROW('إدخال وسجل المنتجات'!$I$5:$I$590)-4)) -> 0 | J49: =IF($I49=0,"",IF($G49="","",$G49*IF(INDEX('إدخال وسجل المنتجات'!$U$5:$U$590,$I49)=0,1,INDEX('إدخال وسجل المنتجات'!$U$5:$U$590,$I49))))
A50: =IF($I50=0,"",47) | B50: =IF($I50=0,"",INDEX('إدخال وسجل المنتجات'!$F$5:$F$590,$I50)) | C50: =IF($I50=0,"",INDEX('إدخال وسجل المنتجات'!$B$5:$B$590,$I50)) | D50: =IF($I50=0,"",INDEX('إدخال وسجل المنتجات'!$C$5:$C$590,$I50)) | E50: =IF($I50=0,"",INDEX('إدخال وسجل المنتجات'!$D$5:$D$590,$I50)) | F50: =IF($I50=0,"",INDEX('إدخال وسجل المنتجات'!$G$5:$G$590,$I50)) | I50: =SUMPRODUCT(('إدخال وسجل المنتجات'!$I$5:$I$590="FRZ")*('إدخال وسجل المنتجات'!$M$5:$M$590=47)*(ROW('إدخال وسجل المنتجات'!$I$5:$I$590)-4)) -> 0 | J50: =IF($I50=0,"",IF($G50="","",$G50*IF(INDEX('إدخال وسجل المنتجات'!$U$5:$U$590,$I50)=0,1,INDEX('إدخال وسجل المنتجات'!$U$5:$U$590,$I50))))
A51: =IF($I51=0,"",48) | B51: =IF($I51=0,"",INDEX('إدخال وسجل المنتجات'!$F$5:$F$590,$I51)) | C51: =IF($I51=0,"",INDEX('إدخال وسجل المنتجات'!$B$5:$B$590,$I51)) | D51: =IF($I51=0,"",INDEX('إدخال وسجل المنتجات'!$C$5:$C$590,$I51)) | E51: =IF($I51=0,"",INDEX('إدخال وسجل المنتجات'!$D$5:$D$590,$I51)) | F51: =IF($I51=0,"",INDEX('إدخال وسجل المنتجات'!$G$5:$G$590,$I51)) | I51: =SUMPRODUCT(('إدخال وسجل المنتجات'!$I$5:$I$590="FRZ")*('إدخال وسجل المنتجات'!$M$5:$M$590=48)*(ROW('إدخال وسجل المنتجات'!$I$5:$I$590)-4)) -> 0 | J51: =IF($I51=0,"",IF($G51="","",$G51*IF(INDEX('إدخال وسجل المنتجات'!$U$5:$U$590,$I51)=0,1,INDEX('إدخال وسجل المنتجات'!$U$5:$U$590,$I51))))
A52: =IF($I52=0,"",49) | B52: =IF($I52=0,"",INDEX('إدخال وسجل المنتجات'!$F$5:$F$590,$I52)) | C52: =IF($I52=0,"",INDEX('إدخال وسجل المنتجات'!$B$5:$B$590,$I52)) | D52: =IF($I52=0,"",INDEX('إدخال وسجل المنتجات'!$C$5:$C$590,$I52)) | E52: =IF($I52=0,"",INDEX('إدخال وسجل المنتجات'!$D$5:$D$590,$I52)) | F52: =IF($I52=0,"",INDEX('إدخال وسجل المنتجات'!$G$5:$G$590,$I52)) | I52: =SUMPRODUCT(('إدخال وسجل المنتجات'!$I$5:$I$590="FRZ")*('إدخال وسجل المنتجات'!$M$5:$M$590=49)*(ROW('إدخال وسجل المنتجات'!$I$5:$I$590)-4)) -> 0 | J52: =IF($I52=0,"",IF($G52="","",$G52*IF(INDEX('إدخال وسجل المنتجات'!$U$5:$U$590,$I52)=0,1,INDEX('إدخال وسجل المنتجات'!$U$5:$U$590,$I52))))
A53: =IF($I53=0,"",50) | B53: =IF($I53=0,"",INDEX('إدخال وسجل المنتجات'!$F$5:$F$590,$I53)) | C53: =IF($I53=0,"",INDEX('إدخال وسجل المنتجات'!$B$5:$B$590,$I53)) | D53: =IF($I53=0,"",INDEX('إدخال وسجل المنتجات'!$C$5:$C$590,$I53)) | E53: =IF($I53=0,"",INDEX('إدخال وسجل المنتجات'!$D$5:$D$590,$I53)) | F53: =IF($I53=0,"",INDEX('إدخال وسجل المنتجات'!$G$5:$G$590,$I53)) | I53: =SUMPRODUCT(('إدخال وسجل المنتجات'!$I$5:$I$590="FRZ")*('إدخال وسجل المنتجات'!$M$5:$M$590=50)*(ROW('إدخال وسجل المنتجات'!$I$5:$I$590)-4)) -> 0 | J53: =IF($I53=0,"",IF($G53="","",$G53*IF(INDEX('إدخال وسجل المنتجات'!$U$5:$U$590,$I53)=0,1,INDEX('إدخال وسجل المنتجات'!$U$5:$U$590,$I53))))
A54: =IF($I54=0,"",51) | B54: =IF($I54=0,"",INDEX('إدخال وسجل المنتجات'!$F$5:$F$590,$I54)) | C54: =IF($I54=0,"",INDEX('إدخال وسجل المنتجات'!$B$5:$B$590,$I54)) | D54: =IF($I54=0,"",INDEX('إدخال وسجل المنتجات'!$C$5:$C$590,$I54)) | E54: =IF($I54=0,"",INDEX('إدخال وسجل المنتجات'!$D$5:$D$590,$I54)) | F54: =IF($I54=0,"",INDEX('إدخال وسجل المنتجات'!$G$5:$G$590,$I54)) | I54: =SUMPRODUCT(('إدخال وسجل المنتجات'!$I$5:$I$590="FRZ")*('إدخال وسجل المنتجات'!$M$5:$M$590=51)*(ROW('إدخال وسجل المنتجات'!$I$5:$I$590)-4)) -> 0 | J54: =IF($I54=0,"",IF($G54="","",$G54*IF(INDEX('إدخال وسجل المنتجات'!$U$5:$U$590,$I54)=0,1,INDEX('إدخال وسجل المنتجات'!$U$5:$U$590,$I54))))
A55: =IF($I55=0,"",52) | B55: =IF($I55=0,"",INDEX('إدخال وسجل المنتجات'!$F$5:$F$590,$I55)) | C55: =IF($I55=0,"",INDEX('إدخال وسجل المنتجات'!$B$5:$B$590,$I55)) | D55: =IF($I55=0,"",INDEX('إدخال وسجل المنتجات'!$C$5:$C$590,$I55)) | E55: =IF($I55=0,"",INDEX('إدخال وسجل المنتجات'!$D$5:$D$590,$I55)) | F55: =IF($I55=0,"",INDEX('إدخال وسجل المنتجات'!$G$5:$G$590,$I55)) | I55: =SUMPRODUCT(('إدخال وسجل المنتجات'!$I$5:$I$590="FRZ")*('إدخال وسجل المنتجات'!$M$5:$M$590=52)*(ROW('إدخال وسجل المنتجات'!$I$5:$I$590)-4)) -> 0 | J55: =IF($I55=0,"",IF($G55="","",$G55*IF(INDEX('إدخال وسجل المنتجات'!$U$5:$U$590,$I55)=0,1,INDEX('إدخال وسجل المنتجات'!$U$5:$U$590,$I55))))
A56: =IF($I56=0,"",53) | B56: =IF($I56=0,"",INDEX('إدخال وسجل المنتجات'!$F$5:$F$590,$I56)) | C56: =IF($I56=0,"",INDEX('إدخال وسجل المنتجات'!$B$5:$B$590,$I56)) | D56: =IF($I56=0,"",INDEX('إدخال وسجل المنتجات'!$C$5:$C$590,$I56)) | E56: =IF($I56=0,"",INDEX('إدخال وسجل المنتجات'!$D$5:$D$590,$I56)) | F56: =IF($I56=0,"",INDEX('إدخال وسجل المنتجات'!$G$5:$G$590,$I56)) | I56: =SUMPRODUCT(('إدخال وسجل المنتجات'!$I$5:$I$590="FRZ")*('إدخال وسجل المنتجات'!$M$5:$M$590=53)*(ROW('إدخال وسجل المنتجات'!$I$5:$I$590)-4)) -> 0 | J56: =IF($I56=0,"",IF($G56="","",$G56*IF(INDEX('إدخال وسجل المنتجات'!$U$5:$U$590,$I56)=0,1,INDEX('إدخال وسجل المنتجات'!$U$5:$U$590,$I56))))
A57: =IF($I57=0,"",54) | B57: =IF($I57=0,"",INDEX('إدخال وسجل المنتجات'!$F$5:$F$590,$I57)) | C57: =IF($I57=0,"",INDEX('إدخال وسجل المنتجات'!$B$5:$B$590,$I57)) | D57: =IF($I57=0,"",INDEX('إدخال وسجل المنتجات'!$C$5:$C$590,$I57)) | E57: =IF($I57=0,"",INDEX('إدخال وسجل المنتجات'!$D$5:$D$590,$I57)) | F57: =IF($I57=0,"",INDEX('إدخال وسجل المنتجات'!$G$5:$G$590,$I57)) | I57: =SUMPRODUCT(('إدخال وسجل المنتجات'!$I$5:$I$590="FRZ")*('إدخال وسجل المنتجات'!$M$5:$M$590=54)*(ROW('إدخال وسجل المنتجات'!$I$5:$I$590)-4)) -> 0 | J57: =IF($I57=0,"",IF($G57="","",$G57*IF(INDEX('إدخال وسجل المنتجات'!$U$5:$U$590,$I57)=0,1,INDEX('إدخال وسجل المنتجات'!$U$5:$U$590,$I57))))
A58: =IF($I58=0,"",55) | B58: =IF($I58=0,"",INDEX('إدخال وسجل المنتجات'!$F$5:$F$590,$I58)) | C58: =IF($I58=0,"",INDEX('إدخال وسجل المنتجات'!$B$5:$B$590,$I58)) | D58: =IF($I58=0,"",INDEX('إدخال وسجل المنتجات'!$C$5:$C$590,$I58)) | E58: =IF($I58=0,"",INDEX('إدخال وسجل المنتجات'!$D$5:$D$590,$I58)) | F58: =IF($I58=0,"",INDEX('إدخال وسجل المنتجات'!$G$5:$G$590,$I58)) | I58: =SUMPRODUCT(('إدخال وسجل المنتجات'!$I$5:$I$590="FRZ")*('إدخال وسجل المنتجات'!$M$5:$M$590=55)*(ROW('إدخال وسجل المنتجات'!$I$5:$I$590)-4)) -> 0 | J58: =IF($I58=0,"",IF($G58="","",$G58*IF(INDEX('إدخال وسجل المنتجات'!$U$5:$U$590,$I58)=0,1,INDEX('إدخال وسجل المنتجات'!$U$5:$U$590,$I58))))
A59: =IF($I59=0,"",56) | B59: =IF($I59=0,"",INDEX('إدخال وسجل المنتجات'!$F$5:$F$590,$I59)) | C59: =IF($I59=0,"",INDEX('إدخال وسجل المنتجات'!$B$5:$B$590,$I59)) | D59: =IF($I59=0,"",INDEX('إدخال وسجل المنتجات'!$C$5:$C$590,$I59)) | E59: =IF($I59=0,"",INDEX('إدخال وسجل المنتجات'!$D$5:$D$590,$I59)) | F59: =IF($I59=0,"",INDEX('إدخال وسجل المنتجات'!$G$5:$G$590,$I59)) | I59: =SUMPRODUCT(('إدخال وسجل المنتجات'!$I$5:$I$590="FRZ")*('إدخال وسجل المنتجات'!$M$5:$M$590=56)*(ROW('إدخال وسجل المنتجات'!$I$5:$I$590)-4)) -> 0 | J59: =IF($I59=0,"",IF($G59="","",$G59*IF(INDEX('إدخال وسجل المنتجات'!$U$5:$U$590,$I59)=0,1,INDEX('إدخال وسجل المنتجات'!$U$5:$U$590,$I59))))
A60: =IF($I60=0,"",57) | B60: =IF($I60=0,"",INDEX('إدخال وسجل المنتجات'!$F$5:$F$590,$I60)) | C60: =IF($I60=0,"",INDEX('إدخال وسجل المنتجات'!$B$5:$B$590,$I60)) | D60: =IF($I60=0,"",INDEX('إدخال وسجل المنتجات'!$C$5:$C$590,$I60)) | E60: =IF($I60=0,"",INDEX('إدخال وسجل المنتجات'!$D$5:$D$590,$I60)) | F60: =IF($I60=0,"",INDEX('إدخال وسجل المنتجات'!$G$5:$G$590,$I60)) | I60: =SUMPRODUCT(('إدخال وسجل المنتجات'!$I$5:$I$590="FRZ")*('إدخال وسجل المنتجات'!$M$5:$M$590=57)*(ROW('إدخال وسجل المنتجات'!$I$5:$I$590)-4)) -> 0 | J60: =IF($I60=0,"",IF($G60="","",$G60*IF(INDEX('إدخال وسجل المنتجات'!$U$5:$U$590,$I60)=0,1,INDEX('إدخال وسجل المنتجات'!$U$5:$U$590,$I60))))
A61: =IF($I61=0,"",58) | B61: =IF($I61=0,"",INDEX('إدخال وسجل المنتجات'!$F$5:$F$590,$I61)) | C61: =IF($I61=0,"",INDEX('إدخال وسجل المنتجات'!$B$5:$B$590,$I61)) | D61: =IF($I61=0,"",INDEX('إدخال وسجل المنتجات'!$C$5:$C$590,$I61)) | E61: =IF($I61=0,"",INDEX('إدخال وسجل المنتجات'!$D$5:$D$590,$I61)) | F61: =IF($I61=0,"",INDEX('إدخال وسجل المنتجات'!$G$5:$G$590,$I61)) | I61: =SUMPRODUCT(('إدخال وسجل المنتجات'!$I$5:$I$590="FRZ")*('إدخال وسجل المنتجات'!$M$5:$M$590=58)*(ROW('إدخال وسجل المنتجات'!$I$5:$I$590)-4)) -> 0 | J61: =IF($I61=0,"",IF($G61="","",$G61*IF(INDEX('إدخال وسجل المنتجات'!$U$5:$U$590,$I61)=0,1,INDEX('إدخال وسجل المنتجات'!$U$5:$U$590,$I61))))
A62: =IF($I62=0,"",59) | B62: =IF($I62=0,"",INDEX('إدخال وسجل المنتجات'!$F$5:$F$590,$I62)) | C62: =IF($I62=0,"",INDEX('إدخال وسجل المنتجات'!$B$5:$B$590,$I62)) | D62: =IF($I62=0,"",INDEX('إدخال وسجل المنتجات'!$C$5:$C$590,$I62)) | E62: =IF($I62=0,"",INDEX('إدخال وسجل المنتجات'!$D$5:$D$590,$I62)) | F62: =IF($I62=0,"",INDEX('إدخال وسجل المنتجات'!$G$5:$G$590,$I62)) | I62: =SUMPRODUCT(('إدخال وسجل المنتجات'!$I$5:$I$590="FRZ")*('إدخال وسجل المنتجات'!$M$5:$M$590=59)*(ROW('إدخال وسجل المنتجات'!$I$5:$I$590)-4)) -> 0 | J62: =IF($I62=0,"",IF($G62="","",$G62*IF(INDEX('إدخال وسجل المنتجات'!$U$5:$U$590,$I62)=0,1,INDEX('إدخال وسجل المنتجات'!$U$5:$U$590,$I62))))
A63: =IF($I63=0,"",60) | B63: =IF($I63=0,"",INDEX('إدخال وسجل المنتجات'!$F$5:$F$590,$I63)) | C63: =IF($I63=0,"",INDEX('إدخال وسجل المنتجات'!$B$5:$B$590,$I63)) | D63: =IF($I63=0,"",INDEX('إدخال وسجل المنتجات'!$C$5:$C$590,$I63)) | E63: =IF($I63=0,"",INDEX('إدخال وسجل المنتجات'!$D$5:$D$590,$I63)) | F63: =IF($I63=0,"",INDEX('إدخال وسجل المنتجات'!$G$5:$G$590,$I63)) | I63: =SUMPRODUCT(('إدخال وسجل المنتجات'!$I$5:$I$590="FRZ")*('إدخال وسجل المنتجات'!$M$5:$M$590=60)*(ROW('إدخال وسجل المنتجات'!$I$5:$I$590)-4)) -> 0 | J63: =IF($I63=0,"",IF($G63="","",$G63*IF(INDEX('إدخال وسجل المنتجات'!$U$5:$U$590,$I63)=0,1,INDEX('إدخال وسجل المنتجات'!$U$5:$U$590,$I63))))
A64: =IF($I64=0,"",61) | B64: =IF($I64=0,"",INDEX('إدخال وسجل المنتجات'!$F$5:$F$590,$I64)) | C64: =IF($I64=0,"",INDEX('إدخال وسجل المنتجات'!$B$5:$B$590,$I64)) | D64: =IF($I64=0,"",INDEX('إدخال وسجل المنتجات'!$C$5:$C$590,$I64)) | E64: =IF($I64=0,"",INDEX('إدخال وسجل المنتجات'!$D$5:$D$590,$I64)) | F64: =IF($I64=0,"",INDEX('إدخال وسجل المنتجات'!$G$5:$G$590,$I64)) | I64: =SUMPRODUCT(('إدخال وسجل المنتجات'!$I$5:$I$590="FRZ")*('إدخال وسجل المنتجات'!$M$5:$M$590=61)*(ROW('إدخال وسجل المنتجات'!$I$5:$I$590)-4)) -> 0 | J64: =IF($I64=0,"",IF($G64="","",$G64*IF(INDEX('إدخال وسجل المنتجات'!$U$5:$U$590,$I64)=0,1,INDEX('إدخال وسجل المنتجات'!$U$5:$U$590,$I64))))
A65: =IF($I65=0,"",62) | B65: =IF($I65=0,"",INDEX('إدخال وسجل المنتجات'!$F$5:$F$590,$I65)) | C65: =IF($I65=0,"",INDEX('إدخال وسجل المنتجات'!$B$5:$B$590,$I65)) | D65: =IF($I65=0,"",INDEX('إدخال وسجل المنتجات'!$C$5:$C$590,$I65)) | E65: =IF($I65=0,"",INDEX('إدخال وسجل المنتجات'!$D$5:$D$590,$I65)) | F65: =IF($I65=0,"",INDEX('إدخال وسجل المنتجات'!$G$5:$G$590,$I65)) | I65: =SUMPRODUCT(('إدخال وسجل المنتجات'!$I$5:$I$590="FRZ")*('إدخال وسجل المنتجات'!$M$5:$M$590=62)*(ROW('إدخال وسجل المنتجات'!$I$5:$I$590)-4)) -> 0 | J65: =IF($I65=0,"",IF($G65="","",$G65*IF(INDEX('إدخال وسجل المنتجات'!$U$5:$U$590,$I65)=0,1,INDEX('إدخال وسجل المنتجات'!$U$5:$U$590,$I65))))
A66: =IF($I66=0,"",63) | B66: =IF($I66=0,"",INDEX('إدخال وسجل المنتجات'!$F$5:$F$590,$I66)) | C66: =IF($I66=0,"",INDEX('إدخال وسجل المنتجات'!$B$5:$B$590,$I66)) | D66: =IF($I66=0,"",INDEX('إدخال وسجل المنتجات'!$C$5:$C$590,$I66)) | E66: =IF($I66=0,"",INDEX('إدخال وسجل المنتجات'!$D$5:$D$590,$I66)) | F66: =IF($I66=0,"",INDEX('إدخال وسجل المنتجات'!$G$5:$G$590,$I66)) | I66: =SUMPRODUCT(('إدخال وسجل المنتجات'!$I$5:$I$590="FRZ")*('إدخال وسجل المنتجات'!$M$5:$M$590=63)*(ROW('إدخال وسجل المنتجات'!$I$5:$I$590)-4)) -> 0 | J66: =IF($I66=0,"",IF($G66="","",$G66*IF(INDEX('إدخال وسجل المنتجات'!$U$5:$U$590,$I66)=0,1,INDEX('إدخال وسجل المنتجات'!$U$5:$U$590,$I66))))
A67: =IF($I67=0,"",64) | B67: =IF($I67=0,"",INDEX('إدخال وسجل المنتجات'!$F$5:$F$590,$I67)) | C67: =IF($I67=0,"",INDEX('إدخال وسجل المنتجات'!$B$5:$B$590,$I67)) | D67: =IF($I67=0,"",INDEX('إدخال وسجل المنتجات'!$C$5:$C$590,$I67)) | E67: =IF($I67=0,"",INDEX('إدخال وسجل المنتجات'!$D$5:$D$590,$I67)) | F67: =IF($I67=0,"",INDEX('إدخال وسجل المنتجات'!$G$5:$G$590,$I67)) | I67: =SUMPRODUCT(('إدخال وسجل المنتجات'!$I$5:$I$590="FRZ")*('إدخال وسجل المنتجات'!$M$5:$M$590=64)*(ROW('إدخال وسجل المنتجات'!$I$5:$I$590)-4)) -> 0 | J67: =IF($I67=0,"",IF($G67="","",$G67*IF(INDEX('إدخال وسجل المنتجات'!$U$5:$U$590,$I67)=0,1,INDEX('إدخال وسجل المنتجات'!$U$5:$U$590,$I67))))
A68: =IF($I68=0,"",65) | B68: =IF($I68=0,"",INDEX('إدخال وسجل المنتجات'!$F$5:$F$590,$I68)) | C68: =IF($I68=0,"",INDEX('إدخال وسجل المنتجات'!$B$5:$B$590,$I68)) | D68: =IF($I68=0,"",INDEX('إدخال وسجل المنتجات'!$C$5:$C$590,$I68)) | E68: =IF($I68=0,"",INDEX('إدخال وسجل المنتجات'!$D$5:$D$590,$I68)) | F68: =IF($I68=0,"",INDEX('إدخال وسجل المنتجات'!$G$5:$G$590,$I68)) | I68: =SUMPRODUCT(('إدخال وسجل المنتجات'!$I$5:$I$590="FRZ")*('إدخال وسجل المنتجات'!$M$5:$M$590=65)*(ROW('إدخال وسجل المنتجات'!$I$5:$I$590)-4)) -> 0 | J68: =IF($I68=0,"",IF($G68="","",$G68*IF(INDEX('إدخال وسجل المنتجات'!$U$5:$U$590,$I68)=0,1,INDEX('إدخال وسجل المنتجات'!$U$5:$U$590,$I68))))
A69: =IF($I69=0,"",66) | B69: =IF($I69=0,"",INDEX('إدخال وسجل المنتجات'!$F$5:$F$590,$I69)) | C69: =IF($I69=0,"",INDEX('إدخال وسجل المنتجات'!$B$5:$B$590,$I69)) | D69: =IF($I69=0,"",INDEX('إدخال وسجل المنتجات'!$C$5:$C$590,$I69)) | E69: =IF($I69=0,"",INDEX('إدخال وسجل المنتجات'!$D$5:$D$590,$I69)) | F69: =IF($I69=0,"",INDEX('إدخال وسجل المنتجات'!$G$5:$G$590,$I69)) | I69: =SUMPRODUCT(('إدخال وسجل المنتجات'!$I$5:$I$590="FRZ")*('إدخال وسجل المنتجات'!$M$5:$M$590=66)*(ROW('إدخال وسجل المنتجات'!$I$5:$I$590)-4)) -> 0 | J69: =IF($I69=0,"",IF($G69="","",$G69*IF(INDEX('إدخال وسجل المنتجات'!$U$5:$U$590,$I69)=0,1,INDEX('إدخال وسجل المنتجات'!$U$5:$U$590,$I69))))
A70: =IF($I70=0,"",67) | B70: =IF($I70=0,"",INDEX('إدخال وسجل المنتجات'!$F$5:$F$590,$I70)) | C70: =IF($I70=0,"",INDEX('إدخال وسجل المنتجات'!$B$5:$B$590,$I70)) | D70: =IF($I70=0,"",INDEX('إدخال وسجل المنتجات'!$C$5:$C$590,$I70)) | E70: =IF($I70=0,"",INDEX('إدخال وسجل المنتجات'!$D$5:$D$590,$I70)) | F70: =IF($I70=0,"",INDEX('إدخال وسجل المنتجات'!$G$5:$G$590,$I70)) | I70: =SUMPRODUCT(('إدخال وسجل المنتجات'!$I$5:$I$590="FRZ")*('إدخال وسجل المنتجات'!$M$5:$M$590=67)*(ROW('إدخال وسجل المنتجات'!$I$5:$I$590)-4)) -> 0 | J70: =IF($I70=0,"",IF($G70="","",$G70*IF(INDEX('إدخال وسجل المنتجات'!$U$5:$U$590,$I70)=0,1,INDEX('إدخال وسجل المنتجات'!$U$5:$U$590,$I70))))
A71: =IF($I71=0,"",68) | B71: =IF($I71=0,"",INDEX('إدخال وسجل المنتجات'!$F$5:$F$590,$I71)) | C71: =IF($I71=0,"",INDEX('إدخال وسجل المنتجات'!$B$5:$B$590,$I71)) | D71: =IF($I71=0,"",INDEX('إدخال وسجل المنتجات'!$C$5:$C$590,$I71)) | E71: =IF($I71=0,"",INDEX('إدخال وسجل المنتجات'!$D$5:$D$590,$I71)) | F71: =IF($I71=0,"",INDEX('إدخال وسجل المنتجات'!$G$5:$G$590,$I71)) | I71: =SUMPRODUCT(('إدخال وسجل المنتجات'!$I$5:$I$590="FRZ")*('إدخال وسجل المنتجات'!$M$5:$M$590=68)*(ROW('إدخال وسجل المنتجات'!$I$5:$I$590)-4)) -> 0 | J71: =IF($I71=0,"",IF($G71="","",$G71*IF(INDEX('إدخال وسجل المنتجات'!$U$5:$U$590,$I71)=0,1,INDEX('إدخال وسجل المنتجات'!$U$5:$U$590,$I71))))
A72: =IF($I72=0,"",69) | B72: =IF($I72=0,"",INDEX('إدخال وسجل المنتجات'!$F$5:$F$590,$I72)) | C72: =IF($I72=0,"",INDEX('إدخال وسجل المنتجات'!$B$5:$B$590,$I72)) | D72: =IF($I72=0,"",INDEX('إدخال وسجل المنتجات'!$C$5:$C$590,$I72)) | E72: =IF($I72=0,"",INDEX('إدخال وسجل المنتجات'!$D$5:$D$590,$I72)) | F72: =IF($I72=0,"",INDEX('إدخال وسجل المنتجات'!$G$5:$G$590,$I72)) | I72: =SUMPRODUCT(('إدخال وسجل المنتجات'!$I$5:$I$590="FRZ")*('إدخال وسجل المنتجات'!$M$5:$M$590=69)*(ROW('إدخال وسجل المنتجات'!$I$5:$I$590)-4)) -> 0 | J72: =IF($I72=0,"",IF($G72="","",$G72*IF(INDEX('إدخال وسجل المنتجات'!$U$5:$U$590,$I72)=0,1,INDEX('إدخال وسجل المنتجات'!$U$5:$U$590,$I72))))
A73: =IF($I73=0,"",70) | B73: =IF($I73=0,"",INDEX('إدخال وسجل المنتجات'!$F$5:$F$590,$I73)) | C73: =IF($I73=0,"",INDEX('إدخال وسجل المنتجات'!$B$5:$B$590,$I73)) | D73: =IF($I73=0,"",INDEX('إدخال وسجل المنتجات'!$C$5:$C$590,$I73)) | E73: =IF($I73=0,"",INDEX('إدخال وسجل المنتجات'!$D$5:$D$590,$I73)) | F73: =IF($I73=0,"",INDEX('إدخال وسجل المنتجات'!$G$5:$G$590,$I73)) | I73: =SUMPRODUCT(('إدخال وسجل المنتجات'!$I$5:$I$590="FRZ")*('إدخال وسجل المنتجات'!$M$5:$M$590=70)*(ROW('إدخال وسجل المنتجات'!$I$5:$I$590)-4)) -> 0 | J73: =IF($I73=0,"",IF($G73="","",$G73*IF(INDEX('إدخال وسجل المنتجات'!$U$5:$U$590,$I73)=0,1,INDEX('إدخال وسجل المنتجات'!$U$5:$U$590,$I73))))
A74: =IF($I74=0,"",71) | B74: =IF($I74=0,"",INDEX('إدخال وسجل المنتجات'!$F$5:$F$590,$I74)) | C74: =IF($I74=0,"",INDEX('إدخال وسجل المنتجات'!$B$5:$B$590,$I74)) | D74: =IF($I74=0,"",INDEX('إدخال وسجل المنتجات'!$C$5:$C$590,$I74)) | E74: =IF($I74=0,"",INDEX('إدخال وسجل المنتجات'!$D$5:$D$590,$I74)) | F74: =IF($I74=0,"",INDEX('إدخال وسجل المنتجات'!$G$5:$G$590,$I74)) | I74: =SUMPRODUCT(('إدخال وسجل المنتجات'!$I$5:$I$590="FRZ")*('إدخال وسجل المنتجات'!$M$5:$M$590=71)*(ROW('إدخال وسجل المنتجات'!$I$5:$I$590)-4)) -> 0 | J74: =IF($I74=0,"",IF($G74="","",$G74*IF(INDEX('إدخال وسجل المنتجات'!$U$5:$U$590,$I74)=0,1,INDEX('إدخال وسجل المنتجات'!$U$5:$U$590,$I74))))
A75: =IF($I75=0,"",72) | B75: =IF($I75=0,"",INDEX('إدخال وسجل المنتجات'!$F$5:$F$590,$I75)) | C75: =IF($I75=0,"",INDEX('إدخال وسجل المنتجات'!$B$5:$B$590,$I75)) | D75: =IF($I75=0,"",INDEX('إدخال وسجل المنتجات'!$C$5:$C$590,$I75)) | E75: =IF($I75=0,"",INDEX('إدخال وسجل المنتجات'!$D$5:$D$590,$I75)) | F75: =IF($I75=0,"",INDEX('إدخال وسجل المنتجات'!$G$5:$G$590,$I75)) | I75: =SUMPRODUCT(('إدخال وسجل المنتجات'!$I$5:$I$590="FRZ")*('إدخال وسجل المنتجات'!$M$5:$M$590=72)*(ROW('إدخال وسجل المنتجات'!$I$5:$I$590)-4)) -> 0 | J75: =IF($I75=0,"",IF($G75="","",$G75*IF(INDEX('إدخال وسجل المنتجات'!$U$5:$U$590,$I75)=0,1,INDEX('إدخال وسجل المنتجات'!$U$5:$U$590,$I75))))
A76: =IF($I76=0,"",73) | B76: =IF($I76=0,"",INDEX('إدخال وسجل المنتجات'!$F$5:$F$590,$I76)) | C76: =IF($I76=0,"",INDEX('إدخال وسجل المنتجات'!$B$5:$B$590,$I76)) | D76: =IF($I76=0,"",INDEX('إدخال وسجل المنتجات'!$C$5:$C$590,$I76)) | E76: =IF($I76=0,"",INDEX('إدخال وسجل المنتجات'!$D$5:$D$590,$I76)) | F76: =IF($I76=0,"",INDEX('إدخال وسجل المنتجات'!$G$5:$G$590,$I76)) | I76: =SUMPRODUCT(('إدخال وسجل المنتجات'!$I$5:$I$590="FRZ")*('إدخال وسجل المنتجات'!$M$5:$M$590=73)*(ROW('إدخال وسجل المنتجات'!$I$5:$I$590)-4)) -> 0 | J76: =IF($I76=0,"",IF($G76="","",$G76*IF(INDEX('إدخال وسجل المنتجات'!$U$5:$U$590,$I76)=0,1,INDEX('إدخال وسجل المنتجات'!$U$5:$U$590,$I76))))
A77: =IF($I77=0,"",74) | B77: =IF($I77=0,"",INDEX('إدخال وسجل المنتجات'!$F$5:$F$590,$I77)) | C77: =IF($I77=0,"",INDEX('إدخال وسجل المنتجات'!$B$5:$B$590,$I77)) | D77: =IF($I77=0,"",INDEX('إدخال وسجل المنتجات'!$C$5:$C$590,$I77)) | E77: =IF($I77=0,"",INDEX('إدخال وسجل المنتجات'!$D$5:$D$590,$I77)) | F77: =IF($I77=0,"",INDEX('إدخال وسجل المنتجات'!$G$5:$G$590,$I77)) | I77: =SUMPRODUCT(('إدخال وسجل المنتجات'!$I$5:$I$590="FRZ")*('إدخال وسجل المنتجات'!$M$5:$M$590=74)*(ROW('إدخال وسجل المنتجات'!$I$5:$I$590)-4)) -> 0 | J77: =IF($I77=0,"",IF($G77="","",$G77*IF(INDEX('إدخال وسجل المنتجات'!$U$5:$U$590,$I77)=0,1,INDEX('إدخال وسجل المنتجات'!$U$5:$U$590,$I77))))
A78: =IF($I78=0,"",75) | B78: =IF($I78=0,"",INDEX('إدخال وسجل المنتجات'!$F$5:$F$590,$I78)) | C78: =IF($I78=0,"",INDEX('إدخال وسجل المنتجات'!$B$5:$B$590,$I78)) | D78: =IF($I78=0,"",INDEX('إدخال وسجل المنتجات'!$C$5:$C$590,$I78)) | E78: =IF($I78=0,"",INDEX('إدخال وسجل المنتجات'!$D$5:$D$590,$I78)) | F78: =IF($I78=0,"",INDEX('إدخال وسجل المنتجات'!$G$5:$G$590,$I78)) | I78: =SUMPRODUCT(('إدخال وسجل المنتجات'!$I$5:$I$590="FRZ")*('إدخال وسجل المنتجات'!$M$5:$M$590=75)*(ROW('إدخال وسجل المنتجات'!$I$5:$I$590)-4)) -> 0 | J78: =IF($I78=0,"",IF($G78="","",$G78*IF(INDEX('إدخال وسجل المنتجات'!$U$5:$U$590,$I78)=0,1,INDEX('إدخال وسجل المنتجات'!$U$5:$U$590,$I78))))
A79: =IF($I79=0,"",76) | B79: =IF($I79=0,"",INDEX('إدخال وسجل المنتجات'!$F$5:$F$590,$I79)) | C79: =IF($I79=0,"",INDEX('إدخال وسجل المنتجات'!$B$5:$B$590,$I79)) | D79: =IF($I79=0,"",INDEX('إدخال وسجل المنتجات'!$C$5:$C$590,$I79)) | E79: =IF($I79=0,"",INDEX('إدخال وسجل المنتجات'!$D$5:$D$590,$I79)) | F79: =IF($I79=0,"",INDEX('إدخال وسجل المنتجات'!$G$5:$G$590,$I79)) | I79: =SUMPRODUCT(('إدخال وسجل المنتجات'!$I$5:$I$590="FRZ")*('إدخال وسجل المنتجات'!$M$5:$M$590=76)*(ROW('إدخال وسجل المنتجات'!$I$5:$I$590)-4)) -> 0 | J79: =IF($I79=0,"",IF($G79="","",$G79*IF(INDEX('إدخال وسجل المنتجات'!$U$5:$U$590,$I79)=0,1,INDEX('إدخال وسجل المنتجات'!$U$5:$U$590,$I79))))
A80: =IF($I80=0,"",77) | B80: =IF($I80=0,"",INDEX('إدخال وسجل المنتجات'!$F$5:$F$590,$I80)) | C80: =IF($I80=0,"",INDEX('إدخال وسجل المنتجات'!$B$5:$B$590,$I80)) | D80: =IF($I80=0,"",INDEX('إدخال وسجل المنتجات'!$C$5:$C$590,$I80)) | E80: =IF($I80=0,"",INDEX('إدخال وسجل المنتجات'!$D$5:$D$590,$I80)) | F80: =IF($I80=0,"",INDEX('إدخال وسجل المنتجات'!$G$5:$G$590,$I80)) | I80: =SUMPRODUCT(('إدخال وسجل المنتجات'!$I$5:$I$590="FRZ")*('إدخال وسجل المنتجات'!$M$5:$M$590=77)*(ROW('إدخال وسجل المنتجات'!$I$5:$I$590)-4)) -> 0 | J80: =IF($I80=0,"",IF($G80="","",$G80*IF(INDEX('إدخال وسجل المنتجات'!$U$5:$U$590,$I80)=0,1,INDEX('إدخال وسجل المنتجات'!$U$5:$U$590,$I80))))
A81: =IF($I81=0,"",78) | B81: =IF($I81=0,"",INDEX('إدخال وسجل المنتجات'!$F$5:$F$590,$I81)) | C81: =IF($I81=0,"",INDEX('إدخال وسجل المنتجات'!$B$5:$B$590,$I81)) | D81: =IF($I81=0,"",INDEX('إدخال وسجل المنتجات'!$C$5:$C$590,$I81)) | E81: =IF($I81=0,"",INDEX('إدخال وسجل المنتجات'!$D$5:$D$590,$I81)) | F81: =IF($I81=0,"",INDEX('إدخال وسجل المنتجات'!$G$5:$G$590,$I81)) | I81: =SUMPRODUCT(('إدخال وسجل المنتجات'!$I$5:$I$590="FRZ")*('إدخال وسجل المنتجات'!$M$5:$M$590=78)*(ROW('إدخال وسجل المنتجات'!$I$5:$I$590)-4)) -> 0 | J81: =IF($I81=0,"",IF($G81="","",$G81*IF(INDEX('إدخال وسجل المنتجات'!$U$5:$U$590,$I81)=0,1,INDEX('إدخال وسجل المنتجات'!$U$5:$U$590,$I81))))
A82: =IF($I82=0,"",79) | B82: =IF($I82=0,"",INDEX('إدخال وسجل المنتجات'!$F$5:$F$590,$I82)) | C82: =IF($I82=0,"",INDEX('إدخال وسجل المنتجات'!$B$5:$B$590,$I82)) | D82: =IF($I82=0,"",INDEX('إدخال وسجل المنتجات'!$C$5:$C$590,$I82)) | E82: =IF($I82=0,"",INDEX('إدخال وسجل المنتجات'!$D$5:$D$590,$I82)) | F82: =IF($I82=0,"",INDEX('إدخال وسجل المنتجات'!$G$5:$G$590,$I82)) | I82: =SUMPRODUCT(('إدخال وسجل المنتجات'!$I$5:$I$590="FRZ")*('إدخال وسجل المنتجات'!$M$5:$M$590=79)*(ROW('إدخال وسجل المنتجات'!$I$5:$I$590)-4)) -> 0 | J82: =IF($I82=0,"",IF($G82="","",$G82*IF(INDEX('إدخال وسجل المنتجات'!$U$5:$U$590,$I82)=0,1,INDEX('إدخال وسجل المنتجات'!$U$5:$U$590,$I82))))
A83: =IF($I83=0,"",80) | B83: =IF($I83=0,"",INDEX('إدخال وسجل المنتجات'!$F$5:$F$590,$I83)) | C83: =IF($I83=0,"",INDEX('إدخال وسجل المنتجات'!$B$5:$B$590,$I83)) | D83: =IF($I83=0,"",INDEX('إدخال وسجل المنتجات'!$C$5:$C$590,$I83)) | E83: =IF($I83=0,"",INDEX('إدخال وسجل المنتجات'!$D$5:$D$590,$I83)) | F83: =IF($I83=0,"",INDEX('إدخال وسجل المنتجات'!$G$5:$G$590,$I83)) | I83: =SUMPRODUCT(('إدخال وسجل المنتجات'!$I$5:$I$590="FRZ")*('إدخال وسجل المنتجات'!$M$5:$M$590=80)*(ROW('إدخال وسجل المنتجات'!$I$5:$I$590)-4)) -> 0 | J83: =IF($I83=0,"",IF($G83="","",$G83*IF(INDEX('إدخال وسجل المنتجات'!$U$5:$U$590,$I83)=0,1,INDEX('إدخال وسجل المنتجات'!$U$5:$U$590,$I83))))
A84: =IF($I84=0,"",81) | B84: =IF($I84=0,"",INDEX('إدخال وسجل المنتجات'!$F$5:$F$590,$I84)) | C84: =IF($I84=0,"",INDEX('إدخال وسجل المنتجات'!$B$5:$B$590,$I84)) | D84: =IF($I84=0,"",INDEX('إدخال وسجل المنتجات'!$C$5:$C$590,$I84)) | E84: =IF($I84=0,"",INDEX('إدخال وسجل المنتجات'!$D$5:$D$590,$I84)) | F84: =IF($I84=0,"",INDEX('إدخال وسجل المنتجات'!$G$5:$G$590,$I84)) | I84: =SUMPRODUCT(('إدخال وسجل المنتجات'!$I$5:$I$590="FRZ")*('إدخال وسجل المنتجات'!$M$5:$M$590=81)*(ROW('إدخال وسجل المنتجات'!$I$5:$I$590)-4)) -> 0 | J84: =IF($I84=0,"",IF($G84="","",$G84*IF(INDEX('إدخال وسجل المنتجات'!$U$5:$U$590,$I84)=0,1,INDEX('إدخال وسجل المنتجات'!$U$5:$U$590,$I84))))
A85: =IF($I85=0,"",82) | B85: =IF($I85=0,"",INDEX('إدخال وسجل المنتجات'!$F$5:$F$590,$I85)) | C85: =IF($I85=0,"",INDEX('إدخال وسجل المنتجات'!$B$5:$B$590,$I85)) | D85: =IF($I85=0,"",INDEX('إدخال وسجل المنتجات'!$C$5:$C$590,$I85)) | E85: =IF($I85=0,"",INDEX('إدخال وسجل المنتجات'!$D$5:$D$590,$I85)) | F85: =IF($I85=0,"",INDEX('إدخال وسجل المنتجات'!$G$5:$G$590,$I85)) | I85: =SUMPRODUCT(('إدخال وسجل المنتجات'!$I$5:$I$590="FRZ")*('إدخال وسجل المنتجات'!$M$5:$M$590=82)*(ROW('إدخال وسجل المنتجات'!$I$5:$I$590)-4)) -> 0 | J85: =IF($I85=0,"",IF($G85="","",$G85*IF(INDEX('إدخال وسجل المنتجات'!$U$5:$U$590,$I85)=0,1,INDEX('إدخال وسجل المنتجات'!$U$5:$U$590,$I85))))
A86: =IF($I86=0,"",83) | B86: =IF($I86=0,"",INDEX('إدخال وسجل المنتجات'!$F$5:$F$590,$I86)) | C86: =IF($I86=0,"",INDEX('إدخال وسجل المنتجات'!$B$5:$B$590,$I86)) | D86: =IF($I86=0,"",INDEX('إدخال وسجل المنتجات'!$C$5:$C$590,$I86)) | E86: =IF($I86=0,"",INDEX('إدخال وسجل المنتجات'!$D$5:$D$590,$I86)) | F86: =IF($I86=0,"",INDEX('إدخال وسجل المنتجات'!$G$5:$G$590,$I86)) | I86: =SUMPRODUCT(('إدخال وسجل المنتجات'!$I$5:$I$590="FRZ")*('إدخال وسجل المنتجات'!$M$5:$M$590=83)*(ROW('إدخال وسجل المنتجات'!$I$5:$I$590)-4)) -> 0 | J86: =IF($I86=0,"",IF($G86="","",$G86*IF(INDEX('إدخال وسجل المنتجات'!$U$5:$U$590,$I86)=0,1,INDEX('إدخال وسجل المنتجات'!$U$5:$U$590,$I86))))
A87: =IF($I87=0,"",84) | B87: =IF($I87=0,"",INDEX('إدخال وسجل المنتجات'!$F$5:$F$590,$I87)) | C87: =IF($I87=0,"",INDEX('إدخال وسجل المنتجات'!$B$5:$B$590,$I87)) | D87: =IF($I87=0,"",INDEX('إدخال وسجل المنتجات'!$C$5:$C$590,$I87)) | E87: =IF($I87=0,"",INDEX('إدخال وسجل المنتجات'!$D$5:$D$590,$I87)) | F87: =IF($I87=0,"",INDEX('إدخال وسجل المنتجات'!$G$5:$G$590,$I87)) | I87: =SUMPRODUCT(('إدخال وسجل المنتجات'!$I$5:$I$590="FRZ")*('إدخال وسجل المنتجات'!$M$5:$M$590=84)*(ROW('إدخال وسجل المنتجات'!$I$5:$I$590)-4)) -> 0 | J87: =IF($I87=0,"",IF($G87="","",$G87*IF(INDEX('إدخال وسجل المنتجات'!$U$5:$U$590,$I87)=0,1,INDEX('إدخال وسجل المنتجات'!$U$5:$U$590,$I87))))
A88: =IF($I88=0,"",85) | B88: =IF($I88=0,"",INDEX('إدخال وسجل المنتجات'!$F$5:$F$590,$I88)) | C88: =IF($I88=0,"",INDEX('إدخال وسجل المنتجات'!$B$5:$B$590,$I88)) | D88: =IF($I88=0,"",INDEX('إدخال وسجل المنتجات'!$C$5:$C$590,$I88)) | E88: =IF($I88=0,"",INDEX('إدخال وسجل المنتجات'!$D$5:$D$590,$I88)) | F88: =IF($I88=0,"",INDEX('إدخال وسجل المنتجات'!$G$5:$G$590,$I88)) | I88: =SUMPRODUCT(('إدخال وسجل المنتجات'!$I$5:$I$590="FRZ")*('إدخال وسجل المنتجات'!$M$5:$M$590=85)*(ROW('إدخال وسجل المنتجات'!$I$5:$I$590)-4)) -> 0 | J88: =IF($I88=0,"",IF($G88="","",$G88*IF(INDEX('إدخال وسجل المنتجات'!$U$5:$U$590,$I88)=0,1,INDEX('إدخال وسجل المنتجات'!$U$5:$U$590,$I88))))
A89: =IF($I89=0,"",86) | B89: =IF($I89=0,"",INDEX('إدخال وسجل المنتجات'!$F$5:$F$590,$I89)) | C89: =IF($I89=0,"",INDEX('إدخال وسجل المنتجات'!$B$5:$B$590,$I89)) | D89: =IF($I89=0,"",INDEX('إدخال وسجل المنتجات'!$C$5:$C$590,$I89)) | E89: =IF($I89=0,"",INDEX('إدخال وسجل المنتجات'!$D$5:$D$590,$I89)) | F89: =IF($I89=0,"",INDEX('إدخال وسجل المنتجات'!$G$5:$G$590,$I89)) | I89: =SUMPRODUCT(('إدخال وسجل المنتجات'!$I$5:$I$590="FRZ")*('إدخال وسجل المنتجات'!$M$5:$M$590=86)*(ROW('إدخال وسجل المنتجات'!$I$5:$I$590)-4)) -> 0 | J89: =IF($I89=0,"",IF($G89="","",$G89*IF(INDEX('إدخال وسجل المنتجات'!$U$5:$U$590,$I89)=0,1,INDEX('إدخال وسجل المنتجات'!$U$5:$U$590,$I89))))
A90: =IF($I90=0,"",87) | B90: =IF($I90=0,"",INDEX('إدخال وسجل المنتجات'!$F$5:$F$590,$I90)) | C90: =IF($I90=0,"",INDEX('إدخال وسجل المنتجات'!$B$5:$B$590,$I90)) | D90: =IF($I90=0,"",INDEX('إدخال وسجل المنتجات'!$C$5:$C$590,$I90)) | E90: =IF($I90=0,"",INDEX('إدخال وسجل المنتجات'!$D$5:$D$590,$I90)) | F90: =IF($I90=0,"",INDEX('إدخال وسجل المنتجات'!$G$5:$G$590,$I90)) | I90: =SUMPRODUCT(('إدخال وسجل المنتجات'!$I$5:$I$590="FRZ")*('إدخال وسجل المنتجات'!$M$5:$M$590=87)*(ROW('إدخال وسجل المنتجات'!$I$5:$I$590)-4)) -> 0 | J90: =IF($I90=0,"",IF($G90="","",$G90*IF(INDEX('إدخال وسجل المنتجات'!$U$5:$U$590,$I90)=0,1,INDEX('إدخال وسجل المنتجات'!$U$5:$U$590,$I90))))
A91: =IF($I91=0,"",88) | B91: =IF($I91=0,"",INDEX('إدخال وسجل المنتجات'!$F$5:$F$590,$I91)) | C91: =IF($I91=0,"",INDEX('إدخال وسجل المنتجات'!$B$5:$B$590,$I91)) | D91: =IF($I91=0,"",INDEX('إدخال وسجل المنتجات'!$C$5:$C$590,$I91)) | E91: =IF($I91=0,"",INDEX('إدخال وسجل المنتجات'!$D$5:$D$590,$I91)) | F91: =IF($I91=0,"",INDEX('إدخال وسجل المنتجات'!$G$5:$G$590,$I91)) | I91: =SUMPRODUCT(('إدخال وسجل المنتجات'!$I$5:$I$590="FRZ")*('إدخال وسجل المنتجات'!$M$5:$M$590=88)*(ROW('إدخال وسجل المنتجات'!$I$5:$I$590)-4)) -> 0 | J91: =IF($I91=0,"",IF($G91="","",$G91*IF(INDEX('إدخال وسجل المنتجات'!$U$5:$U$590,$I91)=0,1,INDEX('إدخال وسجل المنتجات'!$U$5:$U$590,$I91))))
A92: =IF($I92=0,"",89) | B92: =IF($I92=0,"",INDEX('إدخال وسجل المنتجات'!$F$5:$F$590,$I92)) | C92: =IF($I92=0,"",INDEX('إدخال وسجل المنتجات'!$B$5:$B$590,$I92)) | D92: =IF($I92=0,"",INDEX('إدخال وسجل المنتجات'!$C$5:$C$590,$I92)) | E92: =IF($I92=0,"",INDEX('إدخال وسجل المنتجات'!$D$5:$D$590,$I92)) | F92: =IF($I92=0,"",INDEX('إدخال وسجل المنتجات'!$G$5:$G$590,$I92)) | I92: =SUMPRODUCT(('إدخال وسجل المنتجات'!$I$5:$I$590="FRZ")*('إدخال وسجل المنتجات'!$M$5:$M$590=89)*(ROW('إدخال وسجل المنتجات'!$I$5:$I$590)-4)) -> 0 | J92: =IF($I92=0,"",IF($G92="","",$G92*IF(INDEX('إدخال وسجل المنتجات'!$U$5:$U$590,$I92)=0,1,INDEX('إدخال وسجل المنتجات'!$U$5:$U$590,$I92))))
A93: =IF($I93=0,"",90) | B93: =IF($I93=0,"",INDEX('إدخال وسجل المنتجات'!$F$5:$F$590,$I93)) | C93: =IF($I93=0,"",INDEX('إدخال وسجل المنتجات'!$B$5:$B$590,$I93)) | D93: =IF($I93=0,"",INDEX('إدخال وسجل المنتجات'!$C$5:$C$590,$I93)) | E93: =IF($I93=0,"",INDEX('إدخال وسجل المنتجات'!$D$5:$D$590,$I93)) | F93: =IF($I93=0,"",INDEX('إدخال وسجل المنتجات'!$G$5:$G$590,$I93)) | I93: =SUMPRODUCT(('إدخال وسجل المنتجات'!$I$5:$I$590="FRZ")*('إدخال وسجل المنتجات'!$M$5:$M$590=90)*(ROW('إدخال وسجل المنتجات'!$I$5:$I$590)-4)) -> 0 | J93: =IF($I93=0,"",IF($G93="","",$G93*IF(INDEX('إدخال وسجل المنتجات'!$U$5:$U$590,$I93)=0,1,INDEX('إدخال وسجل المنتجات'!$U$5:$U$590,$I93))))
A94: =IF($I94=0,"",91) | B94: =IF($I94=0,"",INDEX('إدخال وسجل المنتجات'!$F$5:$F$590,$I94)) | C94: =IF($I94=0,"",INDEX('إدخال وسجل المنتجات'!$B$5:$B$590,$I94)) | D94: =IF($I94=0,"",INDEX('إدخال وسجل المنتجات'!$C$5:$C$590,$I94)) | E94: =IF($I94=0,"",INDEX('إدخال وسجل المنتجات'!$D$5:$D$590,$I94)) | F94: =IF($I94=0,"",INDEX('إدخال وسجل المنتجات'!$G$5:$G$590,$I94)) | I94: =SUMPRODUCT(('إدخال وسجل المنتجات'!$I$5:$I$590="FRZ")*('إدخال وسجل المنتجات'!$M$5:$M$590=91)*(ROW('إدخال وسجل المنتجات'!$I$5:$I$590)-4)) -> 0 | J94: =IF($I94=0,"",IF($G94="","",$G94*IF(INDEX('إدخال وسجل المنتجات'!$U$5:$U$590,$I94)=0,1,INDEX('إدخال وسجل المنتجات'!$U$5:$U$590,$I94))))
A95: =IF($I95=0,"",92) | B95: =IF($I95=0,"",INDEX('إدخال وسجل المنتجات'!$F$5:$F$590,$I95)) | C95: =IF($I95=0,"",INDEX('إدخال وسجل المنتجات'!$B$5:$B$590,$I95)) | D95: =IF($I95=0,"",INDEX('إدخال وسجل المنتجات'!$C$5:$C$590,$I95)) | E95: =IF($I95=0,"",INDEX('إدخال وسجل المنتجات'!$D$5:$D$590,$I95)) | F95: =IF($I95=0,"",INDEX('إدخال وسجل المنتجات'!$G$5:$G$590,$I95)) | I95: =SUMPRODUCT(('إدخال وسجل المنتجات'!$I$5:$I$590="FRZ")*('إدخال وسجل المنتجات'!$M$5:$M$590=92)*(ROW('إدخال وسجل المنتجات'!$I$5:$I$590)-4)) -> 0 | J95: =IF($I95=0,"",IF($G95="","",$G95*IF(INDEX('إدخال وسجل المنتجات'!$U$5:$U$590,$I95)=0,1,INDEX('إدخال وسجل المنتجات'!$U$5:$U$590,$I95))))
A96: =IF($I96=0,"",93) | B96: =IF($I96=0,"",INDEX('إدخال وسجل المنتجات'!$F$5:$F$590,$I96)) | C96: =IF($I96=0,"",INDEX('إدخال وسجل المنتجات'!$B$5:$B$590,$I96)) | D96: =IF($I96=0,"",INDEX('إدخال وسجل المنتجات'!$C$5:$C$590,$I96)) | E96: =IF($I96=0,"",INDEX('إدخال وسجل المنتجات'!$D$5:$D$590,$I96)) | F96: =IF($I96=0,"",INDEX('إدخال وسجل المنتجات'!$G$5:$G$590,$I96)) | I96: =SUMPRODUCT(('إدخال وسجل المنتجات'!$I$5:$I$590="FRZ")*('إدخال وسجل المنتجات'!$M$5:$M$590=93)*(ROW('إدخال وسجل المنتجات'!$I$5:$I$590)-4)) -> 0 | J96: =IF($I96=0,"",IF($G96="","",$G96*IF(INDEX('إدخال وسجل المنتجات'!$U$5:$U$590,$I96)=0,1,INDEX('إدخال وسجل المنتجات'!$U$5:$U$590,$I96))))
A97: =IF($I97=0,"",94) | B97: =IF($I97=0,"",INDEX('إدخال وسجل المنتجات'!$F$5:$F$590,$I97)) | C97: =IF($I97=0,"",INDEX('إدخال وسجل المنتجات'!$B$5:$B$590,$I97)) | D97: =IF($I97=0,"",INDEX('إدخال وسجل المنتجات'!$C$5:$C$590,$I97)) | E97: =IF($I97=0,"",INDEX('إدخال وسجل المنتجات'!$D$5:$D$590,$I97)) | F97: =IF($I97=0,"",INDEX('إدخال وسجل المنتجات'!$G$5:$G$590,$I97)) | I97: =SUMPRODUCT(('إدخال وسجل المنتجات'!$I$5:$I$590="FRZ")*('إدخال وسجل المنتجات'!$M$5:$M$590=94)*(ROW('إدخال وسجل المنتجات'!$I$5:$I$590)-4)) -> 0 | J97: =IF($I97=0,"",IF($G97="","",$G97*IF(INDEX('إدخال وسجل المنتجات'!$U$5:$U$590,$I97)=0,1,INDEX('إدخال وسجل المنتجات'!$U$5:$U$590,$I97))))
A98: =IF($I98=0,"",95) | B98: =IF($I98=0,"",INDEX('إدخال وسجل المنتجات'!$F$5:$F$590,$I98)) | C98: =IF($I98=0,"",INDEX('إدخال وسجل المنتجات'!$B$5:$B$590,$I98)) | D98: =IF($I98=0,"",INDEX('إدخال وسجل المنتجات'!$C$5:$C$590,$I98)) | E98: =IF($I98=0,"",INDEX('إدخال وسجل المنتجات'!$D$5:$D$590,$I98)) | F98: =IF($I98=0,"",INDEX('إدخال وسجل المنتجات'!$G$5:$G$590,$I98)) | I98: =SUMPRODUCT(('إدخال وسجل المنتجات'!$I$5:$I$590="FRZ")*('إدخال وسجل المنتجات'!$M$5:$M$590=95)*(ROW('إدخال وسجل المنتجات'!$I$5:$I$590)-4)) -> 0 | J98: =IF($I98=0,"",IF($G98="","",$G98*IF(INDEX('إدخال وسجل المنتجات'!$U$5:$U$590,$I98)=0,1,INDEX('إدخال وسجل المنتجات'!$U$5:$U$590,$I98))))
A99: =IF($I99=0,"",96) | B99: =IF($I99=0,"",INDEX('إدخال وسجل المنتجات'!$F$5:$F$590,$I99)) | C99: =IF($I99=0,"",INDEX('إدخال وسجل المنتجات'!$B$5:$B$590,$I99)) | D99: =IF($I99=0,"",INDEX('إدخال وسجل المنتجات'!$C$5:$C$590,$I99)) | E99: =IF($I99=0,"",INDEX('إدخال وسجل المنتجات'!$D$5:$D$590,$I99)) | F99: =IF($I99=0,"",INDEX('إدخال وسجل المنتجات'!$G$5:$G$590,$I99)) | I99: =SUMPRODUCT(('إدخال وسجل المنتجات'!$I$5:$I$590="FRZ")*('إدخال وسجل المنتجات'!$M$5:$M$590=96)*(ROW('إدخال وسجل المنتجات'!$I$5:$I$590)-4)) -> 0 | J99: =IF($I99=0,"",IF($G99="","",$G99*IF(INDEX('إدخال وسجل المنتجات'!$U$5:$U$590,$I99)=0,1,INDEX('إدخال وسجل المنتجات'!$U$5:$U$590,$I99))))
A100: =IF($I100=0,"",97) | B100: =IF($I100=0,"",INDEX('إدخال وسجل المنتجات'!$F$5:$F$590,$I100)) | C100: =IF($I100=0,"",INDEX('إدخال وسجل المنتجات'!$B$5:$B$590,$I100)) | D100: =IF($I100=0,"",INDEX('إدخال وسجل المنتجات'!$C$5:$C$590,$I100)) | E100: =IF($I100=0,"",INDEX('إدخال وسجل المنتجات'!$D$5:$D$590,$I100)) | F100: =IF($I100=0,"",INDEX('إدخال وسجل المنتجات'!$G$5:$G$590,$I100)) | I100: =SUMPRODUCT(('إدخال وسجل المنتجات'!$I$5:$I$590="FRZ")*('إدخال وسجل المنتجات'!$M$5:$M$590=97)*(ROW('إدخال وسجل المنتجات'!$I$5:$I$590)-4)) -> 0 | J100: =IF($I100=0,"",IF($G100="","",$G100*IF(INDEX('إدخال وسجل المنتجات'!$U$5:$U$590,$I100)=0,1,INDEX('إدخال وسجل المنتجات'!$U$5:$U$590,$I100))))
...

Sheet جرد المبرّدة
A1: جرد المنتجات المبرّدة — تخزين مبرد
A2: تاريخ الجرد: __________ القائم بالجرد: __________ (تتحدّث تلقائيًا من السجل) | F2: ="عدد الأصناف: "&COUNTIF('إدخال وسجل المنتجات'!$I$5:$I$590,"CHL") -> عدد الأصناف: 104
A3: م | B3: الكود | C3: اسم المنتج | D3: الاسم EN | E3: الفئة | F3: الوحدة | G3: الكمية الفعلية | H3: ملاحظات | J3: إجمالي الوزن (كجم)
A4: =IF($I4=0,"",1) -> 1 | B4: =IF($I4=0,"",INDEX('إدخال وسجل المنتجات'!$F$5:$F$590,$I4)) -> TRN-CHL-001 | C4: =IF($I4=0,"",INDEX('إدخال وسجل المنتجات'!$B$5:$B$590,$I4)) -> بيستو الريحان | D4: =IF($I4=0,"",INDEX('إدخال وسجل المنتجات'!$C$5:$C$590,$I4)) -> Basil Pesto | E4: =IF($I4=0,"",INDEX('إدخال وسجل المنتجات'!$D$5:$D$590,$I4)) -> مواد تحويلية | F4: =IF($I4=0,"",INDEX('إدخال وسجل المنتجات'!$G$5:$G$590,$I4)) -> كيلو | I4: =SUMPRODUCT(('إدخال وسجل المنتجات'!$I$5:$I$590="CHL")*('إدخال وسجل المنتجات'!$M$5:$M$590=1)*(ROW('إدخال وسجل المنتجات'!$I$5:$I$590)-4)) -> 209 | J4: =IF($I4=0,"",IF($G4="","",$G4*IF(INDEX('إدخال وسجل المنتجات'!$U$5:$U$590,$I4)=0,1,INDEX('إدخال وسجل المنتجات'!$U$5:$U$590,$I4))))
A5: =IF($I5=0,"",2) -> 2 | B5: =IF($I5=0,"",INDEX('إدخال وسجل المنتجات'!$F$5:$F$590,$I5)) -> TRN-CHL-002 | C5: =IF($I5=0,"",INDEX('إدخال وسجل المنتجات'!$B$5:$B$590,$I5)) -> بيستو الطماطم المجففة | D5: =IF($I5=0,"",INDEX('إدخال وسجل المنتجات'!$C$5:$C$590,$I5)) -> Tomato Pesto | E5: =IF($I5=0,"",INDEX('إدخال وسجل المنتجات'!$D$5:$D$590,$I5)) -> مواد تحويلية | F5: =IF($I5=0,"",INDEX('إدخال وسجل المنتجات'!$G$5:$G$590,$I5)) -> كيلو | I5: =SUMPRODUCT(('إدخال وسجل المنتجات'!$I$5:$I$590="CHL")*('إدخال وسجل المنتجات'!$M$5:$M$590=2)*(ROW('إدخال وسجل المنتجات'!$I$5:$I$590)-4)) -> 210 | J5: =IF($I5=0,"",IF($G5="","",$G5*IF(INDEX('إدخال وسجل المنتجات'!$U$5:$U$590,$I5)=0,1,INDEX('إدخال وسجل المنتجات'!$U$5:$U$590,$I5))))
A6: =IF($I6=0,"",3) -> 3 | B6: =IF($I6=0,"",INDEX('إدخال وسجل المنتجات'!$F$5:$F$590,$I6)) -> TRN-CHL-003 | C6: =IF($I6=0,"",INDEX('إدخال وسجل المنتجات'!$B$5:$B$590,$I6)) -> بينو بيستو | D6: =IF($I6=0,"",INDEX('إدخال وسجل المنتجات'!$C$5:$C$590,$I6)) -> Pino Pesto | E6: =IF($I6=0,"",INDEX('إدخال وسجل المنتجات'!$D$5:$D$590,$I6)) -> مواد تحويلية | F6: =IF($I6=0,"",INDEX('إدخال وسجل المنتجات'!$G$5:$G$590,$I6)) -> كيلو | I6: =SUMPRODUCT(('إدخال وسجل المنتجات'!$I$5:$I$590="CHL")*('إدخال وسجل المنتجات'!$M$5:$M$590=3)*(ROW('إدخال وسجل المنتجات'!$I$5:$I$590)-4)) -> 212 | J6: =IF($I6=0,"",IF($G6="","",$G6*IF(INDEX('إدخال وسجل المنتجات'!$U$5:$U$590,$I6)=0,1,INDEX('إدخال وسجل المنتجات'!$U$5:$U$590,$I6))))
A7: =IF($I7=0,"",4) -> 4 | B7: =IF($I7=0,"",INDEX('إدخال وسجل المنتجات'!$F$5:$F$590,$I7)) -> RAW-CHL-001 | C7: =IF($I7=0,"",INDEX('إدخال وسجل المنتجات'!$B$5:$B$590,$I7)) -> تين | D7: =IF($I7=0,"",INDEX('إدخال وسجل المنتجات'!$C$5:$C$590,$I7)) -> Fig | E7: =IF($I7=0,"",INDEX('إدخال وسجل المنتجات'!$D$5:$D$590,$I7)) -> مواد خام | F7: =IF($I7=0,"",INDEX('إدخال وسجل المنتجات'!$G$5:$G$590,$I7)) -> كيلو | I7: =SUMPRODUCT(('إدخال وسجل المنتجات'!$I$5:$I$590="CHL")*('إدخال وسجل المنتجات'!$M$5:$M$590=4)*(ROW('إدخال وسجل المنتجات'!$I$5:$I$590)-4)) -> 219 | J7: =IF($I7=0,"",IF($G7="","",$G7*IF(INDEX('إدخال وسجل المنتجات'!$U$5:$U$590,$I7)=0,1,INDEX('إدخال وسجل المنتجات'!$U$5:$U$590,$I7))))
A8: =IF($I8=0,"",5) -> 5 | B8: =IF($I8=0,"",INDEX('إدخال وسجل المنتجات'!$F$5:$F$590,$I8)) -> TRN-CHL-004 | C8: =IF($I8=0,"",INDEX('إدخال وسجل المنتجات'!$B$5:$B$590,$I8)) -> خليط الكينوا | D8: =IF($I8=0,"",INDEX('إدخال وسجل المنتجات'!$C$5:$C$590,$I8)) -> Quinoa Mix | E8: =IF($I8=0,"",INDEX('إدخال وسجل المنتجات'!$D$5:$D$590,$I8)) -> مواد تحويلية | F8: =IF($I8=0,"",INDEX('إدخال وسجل المنتجات'!$G$5:$G$590,$I8)) -> كيلو | I8: =SUMPRODUCT(('إدخال وسجل المنتجات'!$I$5:$I$590="CHL")*('إدخال وسجل المنتجات'!$M$5:$M$590=5)*(ROW('إدخال وسجل المنتجات'!$I$5:$I$590)-4)) -> 221 | J8: =IF($I8=0,"",IF($G8="","",$G8*IF(INDEX('إدخال وسجل المنتجات'!$U$5:$U$590,$I8)=0,1,INDEX('إدخال وسجل المنتجات'!$U$5:$U$590,$I8))))
A9: =IF($I9=0,"",6) -> 6 | B9: =IF($I9=0,"",INDEX('إدخال وسجل المنتجات'!$F$5:$F$590,$I9)) -> TRN-CHL-005 | C9: =IF($I9=0,"",INDEX('إدخال وسجل المنتجات'!$B$5:$B$590,$I9)) -> عجين بيتزا | D9: =IF($I9=0,"",INDEX('إدخال وسجل المنتجات'!$C$5:$C$590,$I9)) -> Pizza Dough | E9: =IF($I9=0,"",INDEX('إدخال وسجل المنتجات'!$D$5:$D$590,$I9)) -> مواد تحويلية | F9: =IF($I9=0,"",INDEX('إدخال وسجل المنتجات'!$G$5:$G$590,$I9)) -> كيلو | I9: =SUMPRODUCT(('إدخال وسجل المنتجات'!$I$5:$I$590="CHL")*('إدخال وسجل المنتجات'!$M$5:$M$590=6)*(ROW('إدخال وسجل المنتجات'!$I$5:$I$590)-4)) -> 245 | J9: =IF($I9=0,"",IF($G9="","",$G9*IF(INDEX('إدخال وسجل المنتجات'!$U$5:$U$590,$I9)=0,1,INDEX('إدخال وسجل المنتجات'!$U$5:$U$590,$I9))))
A10: =IF($I10=0,"",7) -> 7 | B10: =IF($I10=0,"",INDEX('إدخال وسجل المنتجات'!$F$5:$F$590,$I10)) -> RAW-CHL-002 | C10: =IF($I10=0,"",INDEX('إدخال وسجل المنتجات'!$B$5:$B$590,$I10)) -> كرفس | D10: =IF($I10=0,"",INDEX('إدخال وسجل المنتجات'!$C$5:$C$590,$I10)) -> Celery | E10: =IF($I10=0,"",INDEX('إدخال وسجل المنتجات'!$D$5:$D$590,$I10)) -> مواد خام | F10: =IF($I10=0,"",INDEX('إدخال وسجل المنتجات'!$G$5:$G$590,$I10)) -> كيلو | I10: =SUMPRODUCT(('إدخال وسجل المنتجات'!$I$5:$I$590="CHL")*('إدخال وسجل المنتجات'!$M$5:$M$590=7)*(ROW('إدخال وسجل المنتجات'!$I$5:$I$590)-4)) -> 251 | J10: =IF($I10=0,"",IF($G10="","",$G10*IF(INDEX('إدخال وسجل المنتجات'!$U$5:$U$590,$I10)=0,1,INDEX('إدخال وسجل المنتجات'!$U$5:$U$590,$I10))))
A11: =IF($I11=0,"",8) -> 8 | B11: =IF($I11=0,"",INDEX('إدخال وسجل المنتجات'!$F$5:$F$590,$I11)) -> TRN-CHL-006 | C11: =IF($I11=0,"",INDEX('إدخال وسجل المنتجات'!$B$5:$B$590,$I11)) -> كريمة التيراميسو | D11: =IF($I11=0,"",INDEX('إدخال وسجل المنتجات'!$C$5:$C$590,$I11)) -> Tiramisu Cream | E11: =IF($I11=0,"",INDEX('إدخال وسجل المنتجات'!$D$5:$D$590,$I11)) -> مواد تحويلية | F11: =IF($I11=0,"",INDEX('إدخال وسجل المنتجات'!$G$5:$G$590,$I11)) -> كيلو | I11: =SUMPRODUCT(('إدخال وسجل المنتجات'!$I$5:$I$590="CHL")*('إدخال وسجل المنتجات'!$M$5:$M$590=8)*(ROW('إدخال وسجل المنتجات'!$I$5:$I$590)-4)) -> 253 | J11: =IF($I11=0,"",IF($G11="","",$G11*IF(INDEX('إدخال وسجل المنتجات'!$U$5:$U$590,$I11)=0,1,INDEX('إدخال وسجل المنتجات'!$U$5:$U$590,$I11))))
A12: =IF($I12=0,"",9) -> 9 | B12: =IF($I12=0,"",INDEX('إدخال وسجل المنتجات'!$F$5:$F$590,$I12)) -> TRN-CHL-007 | C12: =IF($I12=0,"",INDEX('إدخال وسجل المنتجات'!$B$5:$B$590,$I12)) -> انتاج ريزوتو زعفران | D12: =IF($I12=0,"",INDEX('إدخال وسجل المنتجات'!$C$5:$C$590,$I12)) -> Production Risotto Saffron | E12: =IF($I12=0,"",INDEX('إدخال وسجل المنتجات'!$D$5:$D$590,$I12)) -> مواد تحويلية | F12: =IF($I12=0,"",INDEX('إدخال وسجل المنتجات'!$G$5:$G$590,$I12)) -> كيلو | I12: =SUMPRODUCT(('إدخال وسجل المنتجات'!$I$5:$I$590="CHL")*('إدخال وسجل المنتجات'!$M$5:$M$590=9)*(ROW('إدخال وسجل المنتجات'!$I$5:$I$590)-4)) -> 276 | J12: =IF($I12=0,"",IF($G12="","",$G12*IF(INDEX('إدخال وسجل المنتجات'!$U$5:$U$590,$I12)=0,1,INDEX('إدخال وسجل المنتجات'!$U$5:$U$590,$I12))))
A13: =IF($I13=0,"",10) -> 10 | B13: =IF($I13=0,"",INDEX('إدخال وسجل المنتجات'!$F$5:$F$590,$I13)) -> TRN-CHL-008 | C13: =IF($I13=0,"",INDEX('إدخال وسجل المنتجات'!$B$5:$B$590,$I13)) -> انتاج كرات الارانشيني | D13: =IF($I13=0,"",INDEX('إدخال وسجل المنتجات'!$C$5:$C$590,$I13)) -> Production Arancini Balls | E13: =IF($I13=0,"",INDEX('إدخال وسجل المنتجات'!$D$5:$D$590,$I13)) -> مواد تحويلية | F13: =IF($I13=0,"",INDEX('إدخال وسجل المنتجات'!$G$5:$G$590,$I13)) -> كيلو | I13: =SUMPRODUCT(('إدخال وسجل المنتجات'!$I$5:$I$590="CHL")*('إدخال وسجل المنتجات'!$M$5:$M$590=10)*(ROW('إدخال وسجل المنتجات'!$I$5:$I$590)-4)) -> 277 | J13: =IF($I13=0,"",IF($G13="","",$G13*IF(INDEX('إدخال وسجل المنتجات'!$U$5:$U$590,$I13)=0,1,INDEX('إدخال وسجل المنتجات'!$U$5:$U$590,$I13))))
A14: =IF($I14=0,"",11) -> 11 | B14: =IF($I14=0,"",INDEX('إدخال وسجل المنتجات'!$F$5:$F$590,$I14)) -> TRN-CHL-009 | C14: =IF($I14=0,"",INDEX('إدخال وسجل المنتجات'!$B$5:$B$590,$I14)) -> انتاج كرات الباستا | D14: =IF($I14=0,"",INDEX('إدخال وسجل المنتجات'!$C$5:$C$590,$I14)) -> Production Pasta Balls | E14: =IF($I14=0,"",INDEX('إدخال وسجل المنتجات'!$D$5:$D$590,$I14)) -> مواد تحويلية | F14: =IF($I14=0,"",INDEX('إدخال وسجل المنتجات'!$G$5:$G$590,$I14)) -> كيلو | I14: =SUMPRODUCT(('إدخال وسجل المنتجات'!$I$5:$I$590="CHL")*('إدخال وسجل المنتجات'!$M$5:$M$590=11)*(ROW('إدخال وسجل المنتجات'!$I$5:$I$590)-4)) -> 278 | J14: =IF($I14=0,"",IF($G14="","",$G14*IF(INDEX('إدخال وسجل المنتجات'!$U$5:$U$590,$I14)=0,1,INDEX('إدخال وسجل المنتجات'!$U$5:$U$590,$I14))))
A15: =IF($I15=0,"",12) -> 12 | B15: =IF($I15=0,"",INDEX('إدخال وسجل المنتجات'!$F$5:$F$590,$I15)) -> RAW-CHL-003 | C15: =IF($I15=0,"",INDEX('إدخال وسجل المنتجات'!$B$5:$B$590,$I15)) -> اوراق كرنب | D15: =IF($I15=0,"",INDEX('إدخال وسجل المنتجات'!$C$5:$C$590,$I15)) -> Cabbage | E15: =IF($I15=0,"",INDEX('إدخال وسجل المنتجات'!$D$5:$D$590,$I15)) -> مواد خام | F15: =IF($I15=0,"",INDEX('إدخال وسجل المنتجات'!$G$5:$G$590,$I15)) -> كيلو | I15: =SUMPRODUCT(('إدخال وسجل المنتجات'!$I$5:$I$590="CHL")*('إدخال وسجل المنتجات'!$M$5:$M$590=12)*(ROW('إدخال وسجل المنتجات'!$I$5:$I$590)-4)) -> 279 | J15: =IF($I15=0,"",IF($G15="","",$G15*IF(INDEX('إدخال وسجل المنتجات'!$U$5:$U$590,$I15)=0,1,INDEX('إدخال وسجل المنتجات'!$U$5:$U$590,$I15))))
A16: =IF($I16=0,"",13) -> 13 | B16: =IF($I16=0,"",INDEX('إدخال وسجل المنتجات'!$F$5:$F$590,$I16)) -> RAW-CHL-004 | C16: =IF($I16=0,"",INDEX('إدخال وسجل المنتجات'!$B$5:$B$590,$I16)) -> باذنجان | D16: =IF($I16=0,"",INDEX('إدخال وسجل المنتجات'!$C$5:$C$590,$I16)) -> Eggplant | E16: =IF($I16=0,"",INDEX('إدخال وسجل المنتجات'!$D$5:$D$590,$I16)) -> مواد خام | F16: =IF($I16=0,"",INDEX('إدخال وسجل المنتجات'!$G$5:$G$590,$I16)) -> كيلو | I16: =SUMPRODUCT(('إدخال وسجل المنتجات'!$I$5:$I$590="CHL")*('إدخال وسجل المنتجات'!$M$5:$M$590=13)*(ROW('إدخال وسجل المنتجات'!$I$5:$I$590)-4)) -> 283 | J16: =IF($I16=0,"",IF($G16="","",$G16*IF(INDEX('إدخال وسجل المنتجات'!$U$5:$U$590,$I16)=0,1,INDEX('إدخال وسجل المنتجات'!$U$5:$U$590,$I16))))
A17: =IF($I17=0,"",14) -> 14 | B17: =IF($I17=0,"",INDEX('إدخال وسجل المنتجات'!$F$5:$F$590,$I17)) -> RAW-CHL-005 | C17: =IF($I17=0,"",INDEX('إدخال وسجل المنتجات'!$B$5:$B$590,$I17)) -> برتقال | D17: =IF($I17=0,"",INDEX('إدخال وسجل المنتجات'!$C$5:$C$590,$I17)) -> Orange | E17: =IF($I17=0,"",INDEX('إدخال وسجل المنتجات'!$D$5:$D$590,$I17)) -> مواد خام | F17: =IF($I17=0,"",INDEX('إدخال وسجل المنتجات'!$G$5:$G$590,$I17)) -> كيلو | I17: =SUMPRODUCT(('إدخال وسجل المنتجات'!$I$5:$I$590="CHL")*('إدخال وسجل المنتجات'!$M$5:$M$590=14)*(ROW('إدخال وسجل المنتجات'!$I$5:$I$590)-4)) -> 287 | J17: =IF($I17=0,"",IF($G17="","",$G17*IF(INDEX('إدخال وسجل المنتجات'!$U$5:$U$590,$I17)=0,1,INDEX('إدخال وسجل المنتجات'!$U$5:$U$590,$I17))))
A18: =IF($I18=0,"",15) -> 15 | B18: =IF($I18=0,"",INDEX('إدخال وسجل المنتجات'!$F$5:$F$590,$I18)) -> RAW-CHL-006 | C18: =IF($I18=0,"",INDEX('إدخال وسجل المنتجات'!$B$5:$B$590,$I18)) -> بقدونس | D18: =IF($I18=0,"",INDEX('إدخال وسجل المنتجات'!$C$5:$C$590,$I18)) -> Parsley | E18: =IF($I18=0,"",INDEX('إدخال وسجل المنتجات'!$D$5:$D$590,$I18)) -> مواد خام | F18: =IF($I18=0,"",INDEX('إدخال وسجل المنتجات'!$G$5:$G$590,$I18)) -> كيلو | I18: =SUMPRODUCT(('إدخال وسجل المنتجات'!$I$5:$I$590="CHL")*('إدخال وسجل المنتجات'!$M$5:$M$590=15)*(ROW('إدخال وسجل المنتجات'!$I$5:$I$590)-4)) -> 302 | J18: =IF($I18=0,"",IF($G18="","",$G18*IF(INDEX('إدخال وسجل المنتجات'!$U$5:$U$590,$I18)=0,1,INDEX('إدخال وسجل المنتجات'!$U$5:$U$590,$I18))))
A19: =IF($I19=0,"",16) -> 16 | B19: =IF($I19=0,"",INDEX('إدخال وسجل المنتجات'!$F$5:$F$590,$I19)) -> TRN-CHL-010 | C19: =IF($I19=0,"",INDEX('إدخال وسجل المنتجات'!$B$5:$B$590,$I19)) -> بيستو | D19: =IF($I19=0,"",INDEX('إدخال وسجل المنتجات'!$C$5:$C$590,$I19)) -> Pesto | E19: =IF($I19=0,"",INDEX('إدخال وسجل المنتجات'!$D$5:$D$590,$I19)) -> مواد تحويلية | F19: =IF($I19=0,"",INDEX('إدخال وسجل المنتجات'!$G$5:$G$590,$I19)) -> كيلو | I19: =SUMPRODUCT(('إدخال وسجل المنتجات'!$I$5:$I$590="CHL")*('إدخال وسجل المنتجات'!$M$5:$M$590=16)*(ROW('إدخال وسجل المنتجات'!$I$5:$I$590)-4)) -> 312 | J19: =IF($I19=0,"",IF($G19="","",$G19*IF(INDEX('إدخال وسجل المنتجات'!$U$5:$U$590,$I19)=0,1,INDEX('إدخال وسجل المنتجات'!$U$5:$U$590,$I19))))
A20: =IF($I20=0,"",17) -> 17 | B20: =IF($I20=0,"",INDEX('إدخال وسجل المنتجات'!$F$5:$F$590,$I20)) -> RAW-CHL-007 | C20: =IF($I20=0,"",INDEX('إدخال وسجل المنتجات'!$B$5:$B$590,$I20)) -> بيض | D20: =IF($I20=0,"",INDEX('إدخال وسجل المنتجات'!$C$5:$C$590,$I20)) -> Eggs | E20: =IF($I20=0,"",INDEX('إدخال وسجل المنتجات'!$D$5:$D$590,$I20)) -> مواد خام | F20: =IF($I20=0,"",INDEX('إدخال وسجل المنتجات'!$G$5:$G$590,$I20)) -> وحدة | I20: =SUMPRODUCT(('إدخال وسجل المنتجات'!$I$5:$I$590="CHL")*('إدخال وسجل المنتجات'!$M$5:$M$590=17)*(ROW('إدخال وسجل المنتجات'!$I$5:$I$590)-4)) -> 313 | J20: =IF($I20=0,"",IF($G20="","",$G20*IF(INDEX('إدخال وسجل المنتجات'!$U$5:$U$590,$I20)=0,1,INDEX('إدخال وسجل المنتجات'!$U$5:$U$590,$I20))))
A21: =IF($I21=0,"",18) -> 18 | B21: =IF($I21=0,"",INDEX('إدخال وسجل المنتجات'!$F$5:$F$590,$I21)) -> RAW-CHL-008 | C21: =IF($I21=0,"",INDEX('إدخال وسجل المنتجات'!$B$5:$B$590,$I21)) -> تفاح | D21: =IF($I21=0,"",INDEX('إدخال وسجل المنتجات'!$C$5:$C$590,$I21)) -> Apple | E21: =IF($I21=0,"",INDEX('إدخال وسجل المنتجات'!$D$5:$D$590,$I21)) -> مواد خام | F21: =IF($I21=0,"",INDEX('إدخال وسجل المنتجات'!$G$5:$G$590,$I21)) -> كيلو | I21: =SUMPRODUCT(('إدخال وسجل المنتجات'!$I$5:$I$590="CHL")*('إدخال وسجل المنتجات'!$M$5:$M$590=18)*(ROW('إدخال وسجل المنتجات'!$I$5:$I$590)-4)) -> 319 | J21: =IF($I21=0,"",IF($G21="","",$G21*IF(INDEX('إدخال وسجل المنتجات'!$U$5:$U$590,$I21)=0,1,INDEX('إدخال وسجل المنتجات'!$U$5:$U$590,$I21))))
A22: =IF($I22=0,"",19) -> 19 | B22: =IF($I22=0,"",INDEX('إدخال وسجل المنتجات'!$F$5:$F$590,$I22)) -> RAW-CHL-009 | C22: =IF($I22=0,"",INDEX('إدخال وسجل المنتجات'!$B$5:$B$590,$I22)) -> توت احمر | D22: =IF($I22=0,"",INDEX('إدخال وسجل المنتجات'!$C$5:$C$590,$I22)) -> Berry | E22: =IF($I22=0,"",INDEX('إدخال وسجل المنتجات'!$D$5:$D$590,$I22)) -> مواد خام | F22: =IF($I22=0,"",INDEX('إدخال وسجل المنتجات'!$G$5:$G$590,$I22)) -> كيلو | I22: =SUMPRODUCT(('إدخال وسجل المنتجات'!$I$5:$I$590="CHL")*('إدخال وسجل المنتجات'!$M$5:$M$590=19)*(ROW('إدخال وسجل المنتجات'!$I$5:$I$590)-4)) -> 322 | J22: =IF($I22=0,"",IF($G22="","",$G22*IF(INDEX('إدخال وسجل المنتجات'!$U$5:$U$590,$I22)=0,1,INDEX('إدخال وسجل المنتجات'!$U$5:$U$590,$I22))))
A23: =IF($I23=0,"",20) -> 20 | B23: =IF($I23=0,"",INDEX('إدخال وسجل المنتجات'!$F$5:$F$590,$I23)) -> RAW-CHL-010 | C23: =IF($I23=0,"",INDEX('إدخال وسجل المنتجات'!$B$5:$B$590,$I23)) -> جبن الماعز | D23: =IF($I23=0,"",INDEX('إدخال وسجل المنتجات'!$C$5:$C$590,$I23)) -> Goat Cheese | E23: =IF($I23=0,"",INDEX('إدخال وسجل المنتجات'!$D$5:$D$590,$I23)) -> مواد خام | F23: =IF($I23=0,"",INDEX('إدخال وسجل المنتجات'!$G$5:$G$590,$I23)) -> كيلو | I23: =SUMPRODUCT(('إدخال وسجل المنتجات'!$I$5:$I$590="CHL")*('إدخال وسجل المنتجات'!$M$5:$M$590=20)*(ROW('إدخال وسجل المنتجات'!$I$5:$I$590)-4)) -> 327 | J23: =IF($I23=0,"",IF($G23="","",$G23*IF(INDEX('إدخال وسجل المنتجات'!$U$5:$U$590,$I23)=0,1,INDEX('إدخال وسجل المنتجات'!$U$5:$U$590,$I23))))
A24: =IF($I24=0,"",21) -> 21 | B24: =IF($I24=0,"",INDEX('إدخال وسجل المنتجات'!$F$5:$F$590,$I24)) -> RAW-CHL-011 | C24: =IF($I24=0,"",INDEX('إدخال وسجل المنتجات'!$B$5:$B$590,$I24)) -> جبن بارميزان | D24: =IF($I24=0,"",INDEX('إدخال وسجل المنتجات'!$C$5:$C$590,$I24)) -> Parmesan Cheese | E24: =IF($I24=0,"",INDEX('إدخال وسجل المنتجات'!$D$5:$D$590,$I24)) -> مواد خام | F24: =IF($I24=0,"",INDEX('إدخال وسجل المنتجات'!$G$5:$G$590,$I24)) -> كيلو | I24: =SUMPRODUCT(('إدخال وسجل المنتجات'!$I$5:$I$590="CHL")*('إدخال وسجل المنتجات'!$M$5:$M$590=21)*(ROW('إدخال وسجل المنتجات'!$I$5:$I$590)-4)) -> 328 | J24: =IF($I24=0,"",IF($G24="","",$G24*IF(INDEX('إدخال وسجل المنتجات'!$U$5:$U$590,$I24)=0,1,INDEX('إدخال وسجل المنتجات'!$U$5:$U$590,$I24))))
A25: =IF($I25=0,"",22) -> 22 | B25: =IF($I25=0,"",INDEX('إدخال وسجل المنتجات'!$F$5:$F$590,$I25)) -> RAW-CHL-012 | C25: =IF($I25=0,"",INDEX('إدخال وسجل المنتجات'!$B$5:$B$590,$I25)) -> جبن بوراتا | D25: =IF($I25=0,"",INDEX('إدخال وسجل المنتجات'!$C$5:$C$590,$I25)) -> Burrata Cheese | E25: =IF($I25=0,"",INDEX('إدخال وسجل المنتجات'!$D$5:$D$590,$I25)) -> مواد خام | F25: =IF($I25=0,"",INDEX('إدخال وسجل المنتجات'!$G$5:$G$590,$I25)) -> كيلو | I25: =SUMPRODUCT(('إدخال وسجل المنتجات'!$I$5:$I$590="CHL")*('إدخال وسجل المنتجات'!$M$5:$M$590=22)*(ROW('إدخال وسجل المنتجات'!$I$5:$I$590)-4)) -> 329 | J25: =IF($I25=0,"",IF($G25="","",$G25*IF(INDEX('إدخال وسجل المنتجات'!$U$5:$U$590,$I25)=0,1,INDEX('إدخال وسجل المنتجات'!$U$5:$U$590,$I25))))
A26: =IF($I26=0,"",23) -> 23 | B26: =IF($I26=0,"",INDEX('إدخال وسجل المنتجات'!$F$5:$F$590,$I26)) -> RAW-CHL-013 | C26: =IF($I26=0,"",INDEX('إدخال وسجل المنتجات'!$B$5:$B$590,$I26)) -> جبن جران مورافيا | D26: =IF($I26=0,"",INDEX('إدخال وسجل المنتجات'!$C$5:$C$590,$I26)) -> Grana Moravia Cheese | E26: =IF($I26=0,"",INDEX('إدخال وسجل المنتجات'!$D$5:$D$590,$I26)) -> مواد خام | F26: =IF($I26=0,"",INDEX('إدخال وسجل المنتجات'!$G$5:$G$590,$I26)) -> كيلو | I26: =SUMPRODUCT(('إدخال وسجل المنتجات'!$I$5:$I$590="CHL")*('إدخال وسجل المنتجات'!$M$5:$M$590=23)*(ROW('إدخال وسجل المنتجات'!$I$5:$I$590)-4)) -> 330 | J26: =IF($I26=0,"",IF($G26="","",$G26*IF(INDEX('إدخال وسجل المنتجات'!$U$5:$U$590,$I26)=0,1,INDEX('إدخال وسجل المنتجات'!$U$5:$U$590,$I26))))
A27: =IF($I27=0,"",24) -> 24 | B27: =IF($I27=0,"",INDEX('إدخال وسجل المنتجات'!$F$5:$F$590,$I27)) -> RAW-CHL-014 | C27: =IF($I27=0,"",INDEX('إدخال وسجل المنتجات'!$B$5:$B$590,$I27)) -> جبن جرانا بيدانا | D27: =IF($I27=0,"",INDEX('إدخال وسجل المنتجات'!$C$5:$C$590,$I27)) -> Padano Cheese | E27: =IF($I27=0,"",INDEX('إدخال وسجل المنتجات'!$D$5:$D$590,$I27)) -> مواد خام | F27: =IF($I27=0,"",INDEX('إدخال وسجل المنتجات'!$G$5:$G$590,$I27)) -> كيلو | I27: =SUMPRODUCT(('إدخال وسجل المنتجات'!$I$5:$I$590="CHL")*('إدخال وسجل المنتجات'!$M$5:$M$590=24)*(ROW('إدخال وسجل المنتجات'!$I$5:$I$590)-4)) -> 331 | J27: =IF($I27=0,"",IF($G27="","",$G27*IF(INDEX('إدخال وسجل المنتجات'!$U$5:$U$590,$I27)=0,1,INDEX('إدخال وسجل المنتجات'!$U$5:$U$590,$I27))))
A28: =IF($I28=0,"",25) -> 25 | B28: =IF($I28=0,"",INDEX('إدخال وسجل المنتجات'!$F$5:$F$590,$I28)) -> RAW-CHL-015 | C28: =IF($I28=0,"",INDEX('إدخال وسجل المنتجات'!$B$5:$B$590,$I28)) -> جبن فيتا | D28: =IF($I28=0,"",INDEX('إدخال وسجل المنتجات'!$C$5:$C$590,$I28)) -> Feta Cheese | E28: =IF($I28=0,"",INDEX('إدخال وسجل المنتجات'!$D$5:$D$590,$I28)) -> مواد خام | F28: =IF($I28=0,"",INDEX('إدخال وسجل المنتجات'!$G$5:$G$590,$I28)) -> كيلو | I28: =SUMPRODUCT(('إدخال وسجل المنتجات'!$I$5:$I$590="CHL")*('إدخال وسجل المنتجات'!$M$5:$M$590=25)*(ROW('إدخال وسجل المنتجات'!$I$5:$I$590)-4)) -> 332 | J28: =IF($I28=0,"",IF($G28="","",$G28*IF(INDEX('إدخال وسجل المنتجات'!$U$5:$U$590,$I28)=0,1,INDEX('إدخال وسجل المنتجات'!$U$5:$U$590,$I28))))
A29: =IF($I29=0,"",26) -> 26 | B29: =IF($I29=0,"",INDEX('إدخال وسجل المنتجات'!$F$5:$F$590,$I29)) -> RAW-CHL-016 | C29: =IF($I29=0,"",INDEX('إدخال وسجل المنتجات'!$B$5:$B$590,$I29)) -> جبن كريمي انكور | D29: =IF($I29=0,"",INDEX('إدخال وسجل المنتجات'!$C$5:$C$590,$I29)) -> Anchor Cheese | E29: =IF($I29=0,"",INDEX('إدخال وسجل المنتجات'!$D$5:$D$590,$I29)) -> مواد خام | F29: =IF($I29=0,"",INDEX('إدخال وسجل المنتجات'!$G$5:$G$590,$I29)) -> كيلو | I29: =SUMPRODUCT(('إدخال وسجل المنتجات'!$I$5:$I$590="CHL")*('إدخال وسجل المنتجات'!$M$5:$M$590=26)*(ROW('إدخال وسجل المنتجات'!$I$5:$I$590)-4)) -> 333 | J29: =IF($I29=0,"",IF($G29="","",$G29*IF(INDEX('إدخال وسجل المنتجات'!$U$5:$U$590,$I29)=0,1,INDEX('إدخال وسجل المنتجات'!$U$5:$U$590,$I29))))
A30: =IF($I30=0,"",27) -> 27 | B30: =IF($I30=0,"",INDEX('إدخال وسجل المنتجات'!$F$5:$F$590,$I30)) -> RAW-CHL-017 | C30: =IF($I30=0,"",INDEX('إدخال وسجل المنتجات'!$B$5:$B$590,$I30)) -> جبن مونتري جاك | D30: =IF($I30=0,"",INDEX('إدخال وسجل المنتجات'!$C$5:$C$590,$I30)) -> Monterey Cheese | E30: =IF($I30=0,"",INDEX('إدخال وسجل المنتجات'!$D$5:$D$590,$I30)) -> مواد خام | F30: =IF($I30=0,"",INDEX('إدخال وسجل المنتجات'!$G$5:$G$590,$I30)) -> كيلو | I30: =SUMPRODUCT(('إدخال وسجل المنتجات'!$I$5:$I$590="CHL")*('إدخال وسجل المنتجات'!$M$5:$M$590=27)*(ROW('إدخال وسجل المنتجات'!$I$5:$I$590)-4)) -> 334 | J30: =IF($I30=0,"",IF($G30="","",$G30*IF(INDEX('إدخال وسجل المنتجات'!$U$5:$U$590,$I30)=0,1,INDEX('إدخال وسجل المنتجات'!$U$5:$U$590,$I30))))
A31: =IF($I31=0,"",28) -> 28 | B31: =IF($I31=0,"",INDEX('إدخال وسجل المنتجات'!$F$5:$F$590,$I31)) -> RAW-CHL-018 | C31: =IF($I31=0,"",INDEX('إدخال وسجل المنتجات'!$B$5:$B$590,$I31)) -> جبنة قشقوان | D31: =IF($I31=0,"",INDEX('إدخال وسجل المنتجات'!$C$5:$C$590,$I31)) -> Kashkaval Cheese | E31: =IF($I31=0,"",INDEX('إدخال وسجل المنتجات'!$D$5:$D$590,$I31)) -> مواد خام | F31: =IF($I31=0,"",INDEX('إدخال وسجل المنتجات'!$G$5:$G$590,$I31)) -> كيلو | I31: =SUMPRODUCT(('إدخال وسجل المنتجات'!$I$5:$I$590="CHL")*('إدخال وسجل المنتجات'!$M$5:$M$590=28)*(ROW('إدخال وسجل المنتجات'!$I$5:$I$590)-4)) -> 335 | J31: =IF($I31=0,"",IF($G31="","",$G31*IF(INDEX('إدخال وسجل المنتجات'!$U$5:$U$590,$I31)=0,1,INDEX('إدخال وسجل المنتجات'!$U$5:$U$590,$I31))))
A32: =IF($I32=0,"",29) -> 29 | B32: =IF($I32=0,"",INDEX('إدخال وسجل المنتجات'!$F$5:$F$590,$I32)) -> RAW-CHL-019 | C32: =IF($I32=0,"",INDEX('إدخال وسجل المنتجات'!$B$5:$B$590,$I32)) -> جرجير | D32: =IF($I32=0,"",INDEX('إدخال وسجل المنتجات'!$C$5:$C$590,$I32)) -> Arugula | E32: =IF($I32=0,"",INDEX('إدخال وسجل المنتجات'!$D$5:$D$590,$I32)) -> مواد خام | F32: =IF($I32=0,"",INDEX('إدخال وسجل المنتجات'!$G$5:$G$590,$I32)) -> كيلو | I32: =SUMPRODUCT(('إدخال وسجل المنتجات'!$I$5:$I$590="CHL")*('إدخال وسجل المنتجات'!$M$5:$M$590=29)*(ROW('إدخال وسجل المنتجات'!$I$5:$I$590)-4)) -> 336 | J32: =IF($I32=0,"",IF($G32="","",$G32*IF(INDEX('إدخال وسجل المنتجات'!$U$5:$U$590,$I32)=0,1,INDEX('إدخال وسجل المنتجات'!$U$5:$U$590,$I32))))
A33: =IF($I33=0,"",30) -> 30 | B33: =IF($I33=0,"",INDEX('إدخال وسجل المنتجات'!$F$5:$F$590,$I33)) -> RAW-CHL-020 | C33: =IF($I33=0,"",INDEX('إدخال وسجل المنتجات'!$B$5:$B$590,$I33)) -> جزر | D33: =IF($I33=0,"",INDEX('إدخال وسجل المنتجات'!$C$5:$C$590,$I33)) -> Carrot | E33: =IF($I33=0,"",INDEX('إدخال وسجل المنتجات'!$D$5:$D$590,$I33)) -> مواد خام | F33: =IF($I33=0,"",INDEX('إدخال وسجل المنتجات'!$G$5:$G$590,$I33)) -> كيلو | I33: =SUMPRODUCT(('إدخال وسجل المنتجات'!$I$5:$I$590="CHL")*('إدخال وسجل المنتجات'!$M$5:$M$590=30)*(ROW('إدخال وسجل المنتجات'!$I$5:$I$590)-4)) -> 337 | J33: =IF($I33=0,"",IF($G33="","",$G33*IF(INDEX('إدخال وسجل المنتجات'!$U$5:$U$590,$I33)=0,1,INDEX('إدخال وسجل المنتجات'!$U$5:$U$590,$I33))))
A34: =IF($I34=0,"",31) -> 31 | B34: =IF($I34=0,"",INDEX('إدخال وسجل المنتجات'!$F$5:$F$590,$I34)) -> RAW-CHL-021 | C34: =IF($I34=0,"",INDEX('إدخال وسجل المنتجات'!$B$5:$B$590,$I34)) -> حلومي | D34: =IF($I34=0,"",INDEX('إدخال وسجل المنتجات'!$C$5:$C$590,$I34)) -> Halloumi | E34: =IF($I34=0,"",INDEX('إدخال وسجل المنتجات'!$D$5:$D$590,$I34)) -> مواد خام | F34: =IF($I34=0,"",INDEX('إدخال وسجل المنتجات'!$G$5:$G$590,$I34)) -> كيلو | I34: =SUMPRODUCT(('إدخال وسجل المنتجات'!$I$5:$I$590="CHL")*('إدخال وسجل المنتجات'!$M$5:$M$590=31)*(ROW('إدخال وسجل المنتجات'!$I$5:$I$590)-4)) -> 349 | J34: =IF($I34=0,"",IF($G34="","",$G34*IF(INDEX('إدخال وسجل المنتجات'!$U$5:$U$590,$I34)=0,1,INDEX('إدخال وسجل المنتجات'!$U$5:$U$590,$I34))))
A35: =IF($I35=0,"",32) -> 32 | B35: =IF($I35=0,"",INDEX('إدخال وسجل المنتجات'!$F$5:$F$590,$I35)) -> RAW-CHL-022 | C35: =IF($I35=0,"",INDEX('إدخال وسجل المنتجات'!$B$5:$B$590,$I35)) -> حليب فرشكو | D35: =IF($I35=0,"",INDEX('إدخال وسجل المنتجات'!$C$5:$C$590,$I35)) -> Fresh Milk | E35: =IF($I35=0,"",INDEX('إدخال وسجل المنتجات'!$D$5:$D$590,$I35)) -> مواد خام | F35: =IF($I35=0,"",INDEX('إدخال وسجل المنتجات'!$G$5:$G$590,$I35)) -> لتر | I35: =SUMPRODUCT(('إدخال وسجل المنتجات'!$I$5:$I$590="CHL")*('إدخال وسجل المنتجات'!$M$5:$M$590=32)*(ROW('إدخال وسجل المنتجات'!$I$5:$I$590)-4)) -> 351 | J35: =IF($I35=0,"",IF($G35="","",$G35*IF(INDEX('إدخال وسجل المنتجات'!$U$5:$U$590,$I35)=0,1,INDEX('إدخال وسجل المنتجات'!$U$5:$U$590,$I35))))
A36: =IF($I36=0,"",33) -> 33 | B36: =IF($I36=0,"",INDEX('إدخال وسجل المنتجات'!$F$5:$F$590,$I36)) -> RAW-CHL-023 | C36: =IF($I36=0,"",INDEX('إدخال وسجل المنتجات'!$B$5:$B$590,$I36)) -> خس رومين | D36: =IF($I36=0,"",INDEX('إدخال وسجل المنتجات'!$C$5:$C$590,$I36)) -> Lettuce | E36: =IF($I36=0,"",INDEX('إدخال وسجل المنتجات'!$D$5:$D$590,$I36)) -> مواد خام | F36: =IF($I36=0,"",INDEX('إدخال وسجل المنتجات'!$G$5:$G$590,$I36)) -> كيلو | I36: =SUMPRODUCT(('إدخال وسجل المنتجات'!$I$5:$I$590="CHL")*('إدخال وسجل المنتجات'!$M$5:$M$590=33)*(ROW('إدخال وسجل المنتجات'!$I$5:$I$590)-4)) -> 355 | J36: =IF($I36=0,"",IF($G36="","",$G36*IF(INDEX('إدخال وسجل المنتجات'!$U$5:$U$590,$I36)=0,1,INDEX('إدخال وسجل المنتجات'!$U$5:$U$590,$I36))))
A37: =IF($I37=0,"",34) -> 34 | B37: =IF($I37=0,"",INDEX('إدخال وسجل المنتجات'!$F$5:$F$590,$I37)) -> RAW-CHL-024 | C37: =IF($I37=0,"",INDEX('إدخال وسجل المنتجات'!$B$5:$B$590,$I37)) -> خس لولو روسو | D37: =IF($I37=0,"",INDEX('إدخال وسجل المنتجات'!$C$5:$C$590,$I37)) -> Lettuce | E37: =IF($I37=0,"",INDEX('إدخال وسجل المنتجات'!$D$5:$D$590,$I37)) -> مواد خام | F37: =IF($I37=0,"",INDEX('إدخال وسجل المنتجات'!$G$5:$G$590,$I37)) -> كيلو | I37: =SUMPRODUCT(('إدخال وسجل المنتجات'!$I$5:$I$590="CHL")*('إدخال وسجل المنتجات'!$M$5:$M$590=34)*(ROW('إدخال وسجل المنتجات'!$I$5:$I$590)-4)) -> 356 | J37: =IF($I37=0,"",IF($G37="","",$G37*IF(INDEX('إدخال وسجل المنتجات'!$U$5:$U$590,$I37)=0,1,INDEX('إدخال وسجل المنتجات'!$U$5:$U$590,$I37))))
A38: =IF($I38=0,"",35) -> 35 | B38: =IF($I38=0,"",INDEX('إدخال وسجل المنتجات'!$F$5:$F$590,$I38)) -> RAW-CHL-025 | C38: =IF($I38=0,"",INDEX('إدخال وسجل المنتجات'!$B$5:$B$590,$I38)) -> خضروات | D38: =IF($I38=0,"",INDEX('إدخال وسجل المنتجات'!$C$5:$C$590,$I38)) -> Vegetables | E38: =IF($I38=0,"",INDEX('إدخال وسجل المنتجات'!$D$5:$D$590,$I38)) -> مواد خام | F38: =IF($I38=0,"",INDEX('إدخال وسجل المنتجات'!$G$5:$G$590,$I38)) -> كيلو | I38: =SUMPRODUCT(('إدخال وسجل المنتجات'!$I$5:$I$590="CHL")*('إدخال وسجل المنتجات'!$M$5:$M$590=35)*(ROW('إدخال وسجل المنتجات'!$I$5:$I$590)-4)) -> 357 | J38: =IF($I38=0,"",IF($G38="","",$G38*IF(INDEX('إدخال وسجل المنتجات'!$U$5:$U$590,$I38)=0,1,INDEX('إدخال وسجل المنتجات'!$U$5:$U$590,$I38))))
A39: =IF($I39=0,"",36) -> 36 | B39: =IF($I39=0,"",INDEX('إدخال وسجل المنتجات'!$F$5:$F$590,$I39)) -> RAW-CHL-026 | C39: =IF($I39=0,"",INDEX('إدخال وسجل المنتجات'!$B$5:$B$590,$I39)) -> خوخ | D39: =IF($I39=0,"",INDEX('إدخال وسجل المنتجات'!$C$5:$C$590,$I39)) -> Peach | E39: =IF($I39=0,"",INDEX('إدخال وسجل المنتجات'!$D$5:$D$590,$I39)) -> مواد خام | F39: =IF($I39=0,"",INDEX('إدخال وسجل المنتجات'!$G$5:$G$590,$I39)) -> كيلو | I39: =SUMPRODUCT(('إدخال وسجل المنتجات'!$I$5:$I$590="CHL")*('إدخال وسجل المنتجات'!$M$5:$M$590=36)*(ROW('إدخال وسجل المنتجات'!$I$5:$I$590)-4)) -> 363 | J39: =IF($I39=0,"",IF($G39="","",$G39*IF(INDEX('إدخال وسجل المنتجات'!$U$5:$U$590,$I39)=0,1,INDEX('إدخال وسجل المنتجات'!$U$5:$U$590,$I39))))
A40: =IF($I40=0,"",37) -> 37 | B40: =IF($I40=0,"",INDEX('إدخال وسجل المنتجات'!$F$5:$F$590,$I40)) -> RAW-CHL-027 | C40: =IF($I40=0,"",INDEX('إدخال وسجل المنتجات'!$B$5:$B$590,$I40)) -> رمان | D40: =IF($I40=0,"",INDEX('إدخال وسجل المنتجات'!$C$5:$C$590,$I40)) -> Pomegranate | E40: =IF($I40=0,"",INDEX('إدخال وسجل المنتجات'!$D$5:$D$590,$I40)) -> مواد خام | F40: =IF($I40=0,"",INDEX('إدخال وسجل المنتجات'!$G$5:$G$590,$I40)) -> كيلو | I40: =SUMPRODUCT(('إدخال وسجل المنتجات'!$I$5:$I$590="CHL")*('إدخال وسجل المنتجات'!$M$5:$M$590=37)*(ROW('إدخال وسجل المنتجات'!$I$5:$I$590)-4)) -> 374 | J40: =IF($I40=0,"",IF($G40="","",$G40*IF(INDEX('إدخال وسجل المنتجات'!$U$5:$U$590,$I40)=0,1,INDEX('إدخال وسجل المنتجات'!$U$5:$U$590,$I40))))
A41: =IF($I41=0,"",38) -> 38 | B41: =IF($I41=0,"",INDEX('إدخال وسجل المنتجات'!$F$5:$F$590,$I41)) -> TRN-CHL-011 | C41: =IF($I41=0,"",INDEX('إدخال وسجل المنتجات'!$B$5:$B$590,$I41)) -> روزيتو | D41: =IF($I41=0,"",INDEX('إدخال وسجل المنتجات'!$C$5:$C$590,$I41)) -> Risotto | E41: =IF($I41=0,"",INDEX('إدخال وسجل المنتجات'!$D$5:$D$590,$I41)) -> مواد تحويلية | F41: =IF($I41=0,"",INDEX('إدخال وسجل المنتجات'!$G$5:$G$590,$I41)) -> كيلو | I41: =SUMPRODUCT(('إدخال وسجل المنتجات'!$I$5:$I$590="CHL")*('إدخال وسجل المنتجات'!$M$5:$M$590=38)*(ROW('إدخال وسجل المنتجات'!$I$5:$I$590)-4)) -> 376 | J41: =IF($I41=0,"",IF($G41="","",$G41*IF(INDEX('إدخال وسجل المنتجات'!$U$5:$U$590,$I41)=0,1,INDEX('إدخال وسجل المنتجات'!$U$5:$U$590,$I41))))
A42: =IF($I42=0,"",39) -> 39 | B42: =IF($I42=0,"",INDEX('إدخال وسجل المنتجات'!$F$5:$F$590,$I42)) -> RAW-CHL-028 | C42: =IF($I42=0,"",INDEX('إدخال وسجل المنتجات'!$B$5:$B$590,$I42)) -> ريحان | D42: =IF($I42=0,"",INDEX('إدخال وسجل المنتجات'!$C$5:$C$590,$I42)) -> Basil | E42: =IF($I42=0,"",INDEX('إدخال وسجل المنتجات'!$D$5:$D$590,$I42)) -> مواد خام | F42: =IF($I42=0,"",INDEX('إدخال وسجل المنتجات'!$G$5:$G$590,$I42)) -> كيلو | I42: =SUMPRODUCT(('إدخال وسجل المنتجات'!$I$5:$I$590="CHL")*('إدخال وسجل المنتجات'!$M$5:$M$590=39)*(ROW('إدخال وسجل المنتجات'!$I$5:$I$590)-4)) -> 379 | J42: =IF($I42=0,"",IF($G42="","",$G42*IF(INDEX('إدخال وسجل المنتجات'!$U$5:$U$590,$I42)=0,1,INDEX('إدخال وسجل المنتجات'!$U$5:$U$590,$I42))))
A43: =IF($I43=0,"",40) -> 40 | B43: =IF($I43=0,"",INDEX('إدخال وسجل المنتجات'!$F$5:$F$590,$I43)) -> TRN-CHL-012 | C43: =IF($I43=0,"",INDEX('إدخال وسجل المنتجات'!$B$5:$B$590,$I43)) -> ريسبي بيقل | D43: =IF($I43=0,"",INDEX('إدخال وسجل المنتجات'!$C$5:$C$590,$I43)) -> Recipe Bagel | E43: =IF($I43=0,"",INDEX('إدخال وسجل المنتجات'!$D$5:$D$590,$I43)) -> مواد تحويلية | F43: =IF($I43=0,"",INDEX('إدخال وسجل المنتجات'!$G$5:$G$590,$I43)) -> كيلو | I43: =SUMPRODUCT(('إدخال وسجل المنتجات'!$I$5:$I$590="CHL")*('إدخال وسجل المنتجات'!$M$5:$M$590=40)*(ROW('إدخال وسجل المنتجات'!$I$5:$I$590)-4)) -> 380 | J43: =IF($I43=0,"",IF($G43="","",$G43*IF(INDEX('إدخال وسجل المنتجات'!$U$5:$U$590,$I43)=0,1,INDEX('إدخال وسجل المنتجات'!$U$5:$U$590,$I43))))
A44: =IF($I44=0,"",41) -> 41 | B44: =IF($I44=0,"",INDEX('إدخال وسجل المنتجات'!$F$5:$F$590,$I44)) -> TRN-CHL-013 | C44: =IF($I44=0,"",INDEX('إدخال وسجل المنتجات'!$B$5:$B$590,$I44)) -> ريسبي ساوردو الحبة الكاملة | D44: =IF($I44=0,"",INDEX('إدخال وسجل المنتجات'!$C$5:$C$590,$I44)) -> Recipe Sourdough Whole | E44: =IF($I44=0,"",INDEX('إدخال وسجل المنتجات'!$D$5:$D$590,$I44)) -> مواد تحويلية | F44: =IF($I44=0,"",INDEX('إدخال وسجل المنتجات'!$G$5:$G$590,$I44)) -> كيلو | I44: =SUMPRODUCT(('إدخال وسجل المنتجات'!$I$5:$I$590="CHL")*('إدخال وسجل المنتجات'!$M$5:$M$590=41)*(ROW('إدخال وسجل المنتجات'!$I$5:$I$590)-4)) -> 381 | J44: =IF($I44=0,"",IF($G44="","",$G44*IF(INDEX('إدخال وسجل المنتجات'!$U$5:$U$590,$I44)=0,1,INDEX('إدخال وسجل المنتجات'!$U$5:$U$590,$I44))))
A45: =IF($I45=0,"",42) -> 42 | B45: =IF($I45=0,"",INDEX('إدخال وسجل المنتجات'!$F$5:$F$590,$I45)) -> TRN-CHL-014 | C45: =IF($I45=0,"",INDEX('إدخال وسجل المنتجات'!$B$5:$B$590,$I45)) -> ريسبي ساوردو الحبوب | D45: =IF($I45=0,"",INDEX('إدخال وسجل المنتجات'!$C$5:$C$590,$I45)) -> Recipe Sourdough Grains | E45: =IF($I45=0,"",INDEX('إدخال وسجل المنتجات'!$D$5:$D$590,$I45)) -> مواد تحويلية | F45: =IF($I45=0,"",INDEX('إدخال وسجل المنتجات'!$G$5:$G$590,$I45)) -> كيلو | I45: =SUMPRODUCT(('إدخال وسجل المنتجات'!$I$5:$I$590="CHL")*('إدخال وسجل المنتجات'!$M$5:$M$590=42)*(ROW('إدخال وسجل المنتجات'!$I$5:$I$590)-4)) -> 382 | J45: =IF($I45=0,"",IF($G45="","",$G45*IF(INDEX('إدخال وسجل المنتجات'!$U$5:$U$590,$I45)=0,1,INDEX('إدخال وسجل المنتجات'!$U$5:$U$590,$I45))))
A46: =IF($I46=0,"",43) -> 43 | B46: =IF($I46=0,"",INDEX('إدخال وسجل المنتجات'!$F$5:$F$590,$I46)) -> TRN-CHL-015 | C46: =IF($I46=0,"",INDEX('إدخال وسجل المنتجات'!$B$5:$B$590,$I46)) -> ريسبي ساوردو الزيتون | D46: =IF($I46=0,"",INDEX('إدخال وسجل المنتجات'!$C$5:$C$590,$I46)) -> Recipe Sourdough Olive | E46: =IF($I46=0,"",INDEX('إدخال وسجل المنتجات'!$D$5:$D$590,$I46)) -> مواد تحويلية | F46: =IF($I46=0,"",INDEX('إدخال وسجل المنتجات'!$G$5:$G$590,$I46)) -> كيلو | I46: =SUMPRODUCT(('إدخال وسجل المنتجات'!$I$5:$I$590="CHL")*('إدخال وسجل المنتجات'!$M$5:$M$590=43)*(ROW('إدخال وسجل المنتجات'!$I$5:$I$590)-4)) -> 383 | J46: =IF($I46=0,"",IF($G46="","",$G46*IF(INDEX('إدخال وسجل المنتجات'!$U$5:$U$590,$I46)=0,1,INDEX('إدخال وسجل المنتجات'!$U$5:$U$590,$I46))))
A47: =IF($I47=0,"",44) -> 44 | B47: =IF($I47=0,"",INDEX('إدخال وسجل المنتجات'!$F$5:$F$590,$I47)) -> TRN-CHL-016 | C47: =IF($I47=0,"",INDEX('إدخال وسجل المنتجات'!$B$5:$B$590,$I47)) -> ريسبي ساوردو الزيتون مع الجبن | D47: =IF($I47=0,"",INDEX('إدخال وسجل المنتجات'!$C$5:$C$590,$I47)) -> Recipe Sourdough Olive Cheese | E47: =IF($I47=0,"",INDEX('إدخال وسجل المنتجات'!$D$5:$D$590,$I47)) -> مواد تحويلية | F47: =IF($I47=0,"",INDEX('إدخال وسجل المنتجات'!$G$5:$G$590,$I47)) -> كيلو | I47: =SUMPRODUCT(('إدخال وسجل المنتجات'!$I$5:$I$590="CHL")*('إدخال وسجل المنتجات'!$M$5:$M$590=44)*(ROW('إدخال وسجل المنتجات'!$I$5:$I$590)-4)) -> 384 | J47: =IF($I47=0,"",IF($G47="","",$G47*IF(INDEX('إدخال وسجل المنتجات'!$U$5:$U$590,$I47)=0,1,INDEX('إدخال وسجل المنتجات'!$U$5:$U$590,$I47))))
A48: =IF($I48=0,"",45) -> 45 | B48: =IF($I48=0,"",INDEX('إدخال وسجل المنتجات'!$F$5:$F$590,$I48)) -> TRN-CHL-017 | C48: =IF($I48=0,"",INDEX('إدخال وسجل المنتجات'!$B$5:$B$590,$I48)) -> ريسبي ساوردو الفلفل الحار مع الشيدر | D48: =IF($I48=0,"",INDEX('إدخال وسجل المنتجات'!$C$5:$C$590,$I48)) -> Recipe Sourdough Pepper Spicy Cheddar | E48: =IF($I48=0,"",INDEX('إدخال وسجل المنتجات'!$D$5:$D$590,$I48)) -> مواد تحويلية | F48: =IF($I48=0,"",INDEX('إدخال وسجل المنتجات'!$G$5:$G$590,$I48)) -> كيلو | I48: =SUMPRODUCT(('إدخال وسجل المنتجات'!$I$5:$I$590="CHL")*('إدخال وسجل المنتجات'!$M$5:$M$590=45)*(ROW('إدخال وسجل المنتجات'!$I$5:$I$590)-4)) -> 385 | J48: =IF($I48=0,"",IF($G48="","",$G48*IF(INDEX('إدخال وسجل المنتجات'!$U$5:$U$590,$I48)=0,1,INDEX('إدخال وسجل المنتجات'!$U$5:$U$590,$I48))))
A49: =IF($I49=0,"",46) -> 46 | B49: =IF($I49=0,"",INDEX('إدخال وسجل المنتجات'!$F$5:$F$590,$I49)) -> TRN-CHL-018 | C49: =IF($I49=0,"",INDEX('إدخال وسجل المنتجات'!$B$5:$B$590,$I49)) -> ريسبي ساوردو طماطم مجففة | D49: =IF($I49=0,"",INDEX('إدخال وسجل المنتجات'!$C$5:$C$590,$I49)) -> Recipe Sourdough Sun-Dried Tomato | E49: =IF($I49=0,"",INDEX('إدخال وسجل المنتجات'!$D$5:$D$590,$I49)) -> مواد تحويلية | F49: =IF($I49=0,"",INDEX('إدخال وسجل المنتجات'!$G$5:$G$590,$I49)) -> كيلو | I49: =SUMPRODUCT(('إدخال وسجل المنتجات'!$I$5:$I$590="CHL")*('إدخال وسجل المنتجات'!$M$5:$M$590=46)*(ROW('إدخال وسجل المنتجات'!$I$5:$I$590)-4)) -> 386 | J49: =IF($I49=0,"",IF($G49="","",$G49*IF(INDEX('إدخال وسجل المنتجات'!$U$5:$U$590,$I49)=0,1,INDEX('إدخال وسجل المنتجات'!$U$5:$U$590,$I49))))
A50: =IF($I50=0,"",47) -> 47 | B50: =IF($I50=0,"",INDEX('إدخال وسجل المنتجات'!$F$5:$F$590,$I50)) -> TRN-CHL-019 | C50: =IF($I50=0,"",INDEX('إدخال وسجل المنتجات'!$B$5:$B$590,$I50)) -> ريسبي ساوردو كلاسيك | D50: =IF($I50=0,"",INDEX('إدخال وسجل المنتجات'!$C$5:$C$590,$I50)) -> Recipe Sourdough Classic | E50: =IF($I50=0,"",INDEX('إدخال وسجل المنتجات'!$D$5:$D$590,$I50)) -> مواد تحويلية | F50: =IF($I50=0,"",INDEX('إدخال وسجل المنتجات'!$G$5:$G$590,$I50)) -> كيلو | I50: =SUMPRODUCT(('إدخال وسجل المنتجات'!$I$5:$I$590="CHL")*('إدخال وسجل المنتجات'!$M$5:$M$590=47)*(ROW('إدخال وسجل المنتجات'!$I$5:$I$590)-4)) -> 387 | J50: =IF($I50=0,"",IF($G50="","",$G50*IF(INDEX('إدخال وسجل المنتجات'!$U$5:$U$590,$I50)=0,1,INDEX('إدخال وسجل المنتجات'!$U$5:$U$590,$I50))))
A51: =IF($I51=0,"",48) -> 48 | B51: =IF($I51=0,"",INDEX('إدخال وسجل المنتجات'!$F$5:$F$590,$I51)) -> TRN-CHL-020 | C51: =IF($I51=0,"",INDEX('إدخال وسجل المنتجات'!$B$5:$B$590,$I51)) -> ريسبي كريم بروليه | D51: =IF($I51=0,"",INDEX('إدخال وسجل المنتجات'!$C$5:$C$590,$I51)) -> Recipe Creme Brulee | E51: =IF($I51=0,"",INDEX('إدخال وسجل المنتجات'!$D$5:$D$590,$I51)) -> مواد تحويلية | F51: =IF($I51=0,"",INDEX('إدخال وسجل المنتجات'!$G$5:$G$590,$I51)) -> كيلو | I51: =SUMPRODUCT(('إدخال وسجل المنتجات'!$I$5:$I$590="CHL")*('إدخال وسجل المنتجات'!$M$5:$M$590=48)*(ROW('إدخال وسجل المنتجات'!$I$5:$I$590)-4)) -> 388 | J51: =IF($I51=0,"",IF($G51="","",$G51*IF(INDEX('إدخال وسجل المنتجات'!$U$5:$U$590,$I51)=0,1,INDEX('إدخال وسجل المنتجات'!$U$5:$U$590,$I51))))
A52: =IF($I52=0,"",49) -> 49 | B52: =IF($I52=0,"",INDEX('إدخال وسجل المنتجات'!$F$5:$F$590,$I52)) -> TRN-CHL-021 | C52: =IF($I52=0,"",INDEX('إدخال وسجل المنتجات'!$B$5:$B$590,$I52)) -> ريسبي لازانيا | D52: =IF($I52=0,"",INDEX('إدخال وسجل المنتجات'!$C$5:$C$590,$I52)) -> Recipe Lasagna | E52: =IF($I52=0,"",INDEX('إدخال وسجل المنتجات'!$D$5:$D$590,$I52)) -> مواد تحويلية | F52: =IF($I52=0,"",INDEX('إدخال وسجل المنتجات'!$G$5:$G$590,$I52)) -> كيلو | I52: =SUMPRODUCT(('إدخال وسجل المنتجات'!$I$5:$I$590="CHL")*('إدخال وسجل المنتجات'!$M$5:$M$590=49)*(ROW('إدخال وسجل المنتجات'!$I$5:$I$590)-4)) -> 389 | J52: =IF($I52=0,"",IF($G52="","",$G52*IF(INDEX('إدخال وسجل المنتجات'!$U$5:$U$590,$I52)=0,1,INDEX('إدخال وسجل المنتجات'!$U$5:$U$590,$I52))))
A53: =IF($I53=0,"",50) -> 50 | B53: =IF($I53=0,"",INDEX('إدخال وسجل المنتجات'!$F$5:$F$590,$I53)) -> RAW-CHL-029 | C53: =IF($I53=0,"",INDEX('إدخال وسجل المنتجات'!$B$5:$B$590,$I53)) -> زبادي | D53: =IF($I53=0,"",INDEX('إدخال وسجل المنتجات'!$C$5:$C$590,$I53)) -> Yogurt | E53: =IF($I53=0,"",INDEX('إدخال وسجل المنتجات'!$D$5:$D$590,$I53)) -> مواد خام | F53: =IF($I53=0,"",INDEX('إدخال وسجل المنتجات'!$G$5:$G$590,$I53)) -> كيلو | I53: =SUMPRODUCT(('إدخال وسجل المنتجات'!$I$5:$I$590="CHL")*('إدخال وسجل المنتجات'!$M$5:$M$590=50)*(ROW('إدخال وسجل المنتجات'!$I$5:$I$590)-4)) -> 391 | J53: =IF($I53=0,"",IF($G53="","",$G53*IF(INDEX('إدخال وسجل المنتجات'!$U$5:$U$590,$I53)=0,1,INDEX('إدخال وسجل المنتجات'!$U$5:$U$590,$I53))))
A54: =IF($I54=0,"",51) -> 51 | B54: =IF($I54=0,"",INDEX('إدخال وسجل المنتجات'!$F$5:$F$590,$I54)) -> RAW-CHL-030 | C54: =IF($I54=0,"",INDEX('إدخال وسجل المنتجات'!$B$5:$B$590,$I54)) -> زبدة | D54: =IF($I54=0,"",INDEX('إدخال وسجل المنتجات'!$C$5:$C$590,$I54)) -> Butter | E54: =IF($I54=0,"",INDEX('إدخال وسجل المنتجات'!$D$5:$D$590,$I54)) -> مواد خام | F54: =IF($I54=0,"",INDEX('إدخال وسجل المنتجات'!$G$5:$G$590,$I54)) -> كيلو | I54: =SUMPRODUCT(('إدخال وسجل المنتجات'!$I$5:$I$590="CHL")*('إدخال وسجل المنتجات'!$M$5:$M$590=51)*(ROW('إدخال وسجل المنتجات'!$I$5:$I$590)-4)) -> 392 | J54: =IF($I54=0,"",IF($G54="","",$G54*IF(INDEX('إدخال وسجل المنتجات'!$U$5:$U$590,$I54)=0,1,INDEX('إدخال وسجل المنتجات'!$U$5:$U$590,$I54))))
A55: =IF($I55=0,"",52) -> 52 | B55: =IF($I55=0,"",INDEX('إدخال وسجل المنتجات'!$F$5:$F$590,$I55)) -> RAW-CHL-031 | C55: =IF($I55=0,"",INDEX('إدخال وسجل المنتجات'!$B$5:$B$590,$I55)) -> زبدة ترافل | D55: =IF($I55=0,"",INDEX('إدخال وسجل المنتجات'!$C$5:$C$590,$I55)) -> Truffle Butter | E55: =IF($I55=0,"",INDEX('إدخال وسجل المنتجات'!$D$5:$D$590,$I55)) -> مواد خام | F55: =IF($I55=0,"",INDEX('إدخال وسجل المنتجات'!$G$5:$G$590,$I55)) -> كيلو | I55: =SUMPRODUCT(('إدخال وسجل المنتجات'!$I$5:$I$590="CHL")*('إدخال وسجل المنتجات'!$M$5:$M$590=52)*(ROW('إدخال وسجل المنتجات'!$I$5:$I$590)-4)) -> 393 | J55: =IF($I55=0,"",IF($G55="","",$G55*IF(INDEX('إدخال وسجل المنتجات'!$U$5:$U$590,$I55)=0,1,INDEX('إدخال وسجل المنتجات'!$U$5:$U$590,$I55))))
A56: =IF($I56=0,"",53) -> 53 | B56: =IF($I56=0,"",INDEX('إدخال وسجل المنتجات'!$F$5:$F$590,$I56)) -> RAW-CHL-032 | C56: =IF($I56=0,"",INDEX('إدخال وسجل المنتجات'!$B$5:$B$590,$I56)) -> سبانخ | D56: =IF($I56=0,"",INDEX('إدخال وسجل المنتجات'!$C$5:$C$590,$I56)) -> Spinach | E56: =IF($I56=0,"",INDEX('إدخال وسجل المنتجات'!$D$5:$D$590,$I56)) -> مواد خام | F56: =IF($I56=0,"",INDEX('إدخال وسجل المنتجات'!$G$5:$G$590,$I56)) -> كيلو | I56: =SUMPRODUCT(('إدخال وسجل المنتجات'!$I$5:$I$590="CHL")*('إدخال وسجل المنتجات'!$M$5:$M$590=53)*(ROW('إدخال وسجل المنتجات'!$I$5:$I$590)-4)) -> 405 | J56: =IF($I56=0,"",IF($G56="","",$G56*IF(INDEX('إدخال وسجل المنتجات'!$U$5:$U$590,$I56)=0,1,INDEX('إدخال وسجل المنتجات'!$U$5:$U$590,$I56))))
A57: =IF($I57=0,"",54) -> 54 | B57: =IF($I57=0,"",INDEX('إدخال وسجل المنتجات'!$F$5:$F$590,$I57)) -> RAW-CHL-033 | C57: =IF($I57=0,"",INDEX('إدخال وسجل المنتجات'!$B$5:$B$590,$I57)) -> شبيه زبدة | D57: =IF($I57=0,"",INDEX('إدخال وسجل المنتجات'!$C$5:$C$590,$I57)) -> Butter | E57: =IF($I57=0,"",INDEX('إدخال وسجل المنتجات'!$D$5:$D$590,$I57)) -> مواد خام | F57: =IF($I57=0,"",INDEX('إدخال وسجل المنتجات'!$G$5:$G$590,$I57)) -> كيلو | I57: =SUMPRODUCT(('إدخال وسجل المنتجات'!$I$5:$I$590="CHL")*('إدخال وسجل المنتجات'!$M$5:$M$590=54)*(ROW('إدخال وسجل المنتجات'!$I$5:$I$590)-4)) -> 419 | J57: =IF($I57=0,"",IF($G57="","",$G57*IF(INDEX('إدخال وسجل المنتجات'!$U$5:$U$590,$I57)=0,1,INDEX('إدخال وسجل المنتجات'!$U$5:$U$590,$I57))))
A58: =IF($I58=0,"",55) -> 55 | B58: =IF($I58=0,"",INDEX('إدخال وسجل المنتجات'!$F$5:$F$590,$I58)) -> RAW-CHL-034 | C58: =IF($I58=0,"",INDEX('إدخال وسجل المنتجات'!$B$5:$B$590,$I58)) -> شيدر ابيض | D58: =IF($I58=0,"",INDEX('إدخال وسجل المنتجات'!$C$5:$C$590,$I58)) -> Cheddar | E58: =IF($I58=0,"",INDEX('إدخال وسجل المنتجات'!$D$5:$D$590,$I58)) -> مواد خام | F58: =IF($I58=0,"",INDEX('إدخال وسجل المنتجات'!$G$5:$G$590,$I58)) -> كيلو | I58: =SUMPRODUCT(('إدخال وسجل المنتجات'!$I$5:$I$590="CHL")*('إدخال وسجل المنتجات'!$M$5:$M$590=55)*(ROW('إدخال وسجل المنتجات'!$I$5:$I$590)-4)) -> 430 | J58: =IF($I58=0,"",IF($G58="","",$G58*IF(INDEX('إدخال وسجل المنتجات'!$U$5:$U$590,$I58)=0,1,INDEX('إدخال وسجل المنتجات'!$U$5:$U$590,$I58))))
A59: =IF($I59=0,"",56) -> 56 | B59: =IF($I59=0,"",INDEX('إدخال وسجل المنتجات'!$F$5:$F$590,$I59)) -> RAW-CHL-035 | C59: =IF($I59=0,"",INDEX('إدخال وسجل المنتجات'!$B$5:$B$590,$I59)) -> شيدر اصفر | D59: =IF($I59=0,"",INDEX('إدخال وسجل المنتجات'!$C$5:$C$590,$I59)) -> Cheddar | E59: =IF($I59=0,"",INDEX('إدخال وسجل المنتجات'!$D$5:$D$590,$I59)) -> مواد خام | F59: =IF($I59=0,"",INDEX('إدخال وسجل المنتجات'!$G$5:$G$590,$I59)) -> كيلو | I59: =SUMPRODUCT(('إدخال وسجل المنتجات'!$I$5:$I$590="CHL")*('إدخال وسجل المنتجات'!$M$5:$M$590=56)*(ROW('إدخال وسجل المنتجات'!$I$5:$I$590)-4)) -> 431 | J59: =IF($I59=0,"",IF($G59="","",$G59*IF(INDEX('إدخال وسجل المنتجات'!$U$5:$U$590,$I59)=0,1,INDEX('إدخال وسجل المنتجات'!$U$5:$U$590,$I59))))
A60: =IF($I60=0,"",57) -> 57 | B60: =IF($I60=0,"",INDEX('إدخال وسجل المنتجات'!$F$5:$F$590,$I60)) -> RAW-CHL-036 | C60: =IF($I60=0,"",INDEX('إدخال وسجل المنتجات'!$B$5:$B$590,$I60)) -> صفار بيض | D60: =IF($I60=0,"",INDEX('إدخال وسجل المنتجات'!$C$5:$C$590,$I60)) -> Yolk Eggs | E60: =IF($I60=0,"",INDEX('إدخال وسجل المنتجات'!$D$5:$D$590,$I60)) -> مواد خام | F60: =IF($I60=0,"",INDEX('إدخال وسجل المنتجات'!$G$5:$G$590,$I60)) -> كيلو | I60: =SUMPRODUCT(('إدخال وسجل المنتجات'!$I$5:$I$590="CHL")*('إدخال وسجل المنتجات'!$M$5:$M$590=57)*(ROW('إدخال وسجل المنتجات'!$I$5:$I$590)-4)) -> 438 | J60: =IF($I60=0,"",IF($G60="","",$G60*IF(INDEX('إدخال وسجل المنتجات'!$U$5:$U$590,$I60)=0,1,INDEX('إدخال وسجل المنتجات'!$U$5:$U$590,$I60))))
A61: =IF($I61=0,"",58) -> 58 | B61: =IF($I61=0,"",INDEX('إدخال وسجل المنتجات'!$F$5:$F$590,$I61)) -> TRN-CHL-022 | C61: =IF($I61=0,"",INDEX('إدخال وسجل المنتجات'!$B$5:$B$590,$I61)) -> صوص البريسكت | D61: =IF($I61=0,"",INDEX('إدخال وسجل المنتجات'!$C$5:$C$590,$I61)) -> Brisket Sauce | E61: =IF($I61=0,"",INDEX('إدخال وسجل المنتجات'!$D$5:$D$590,$I61)) -> مواد تحويلية | F61: =IF($I61=0,"",INDEX('إدخال وسجل المنتجات'!$G$5:$G$590,$I61)) -> كيلو | I61: =SUMPRODUCT(('إدخال وسجل المنتجات'!$I$5:$I$590="CHL")*('إدخال وسجل المنتجات'!$M$5:$M$590=58)*(ROW('إدخال وسجل المنتجات'!$I$5:$I$590)-4)) -> 444 | J61: =IF($I61=0,"",IF($G61="","",$G61*IF(INDEX('إدخال وسجل المنتجات'!$U$5:$U$590,$I61)=0,1,INDEX('إدخال وسجل المنتجات'!$U$5:$U$590,$I61))))
A62: =IF($I62=0,"",59) -> 59 | B62: =IF($I62=0,"",INDEX('إدخال وسجل المنتجات'!$F$5:$F$590,$I62)) -> TRN-CHL-023 | C62: =IF($I62=0,"",INDEX('إدخال وسجل المنتجات'!$B$5:$B$590,$I62)) -> صوص البشاميل | D62: =IF($I62=0,"",INDEX('إدخال وسجل المنتجات'!$C$5:$C$590,$I62)) -> Sauce | E62: =IF($I62=0,"",INDEX('إدخال وسجل المنتجات'!$D$5:$D$590,$I62)) -> مواد تحويلية | F62: =IF($I62=0,"",INDEX('إدخال وسجل المنتجات'!$G$5:$G$590,$I62)) -> كيلو | I62: =SUMPRODUCT(('إدخال وسجل المنتجات'!$I$5:$I$590="CHL")*('إدخال وسجل المنتجات'!$M$5:$M$590=59)*(ROW('إدخال وسجل المنتجات'!$I$5:$I$590)-4)) -> 445 | J62: =IF($I62=0,"",IF($G62="","",$G62*IF(INDEX('إدخال وسجل المنتجات'!$U$5:$U$590,$I62)=0,1,INDEX('إدخال وسجل المنتجات'!$U$5:$U$590,$I62))))
A63: =IF($I63=0,"",60) -> 60 | B63: =IF($I63=0,"",INDEX('إدخال وسجل المنتجات'!$F$5:$F$590,$I63)) -> TRN-CHL-024 | C63: =IF($I63=0,"",INDEX('إدخال وسجل المنتجات'!$B$5:$B$590,$I63)) -> صوص البطاطس الخارجي | D63: =IF($I63=0,"",INDEX('إدخال وسجل المنتجات'!$C$5:$C$590,$I63)) -> External Fries Sauce | E63: =IF($I63=0,"",INDEX('إدخال وسجل المنتجات'!$D$5:$D$590,$I63)) -> مواد تحويلية | F63: =IF($I63=0,"",INDEX('إدخال وسجل المنتجات'!$G$5:$G$590,$I63)) -> كيلو | I63: =SUMPRODUCT(('إدخال وسجل المنتجات'!$I$5:$I$590="CHL")*('إدخال وسجل المنتجات'!$M$5:$M$590=60)*(ROW('إدخال وسجل المنتجات'!$I$5:$I$590)-4)) -> 446 | J63: =IF($I63=0,"",IF($G63="","",$G63*IF(INDEX('إدخال وسجل المنتجات'!$U$5:$U$590,$I63)=0,1,INDEX('إدخال وسجل المنتجات'!$U$5:$U$590,$I63))))
A64: =IF($I64=0,"",61) -> 61 | B64: =IF($I64=0,"",INDEX('إدخال وسجل المنتجات'!$F$5:$F$590,$I64)) -> TRN-CHL-025 | C64: =IF($I64=0,"",INDEX('إدخال وسجل المنتجات'!$B$5:$B$590,$I64)) -> صوص الترافل | D64: =IF($I64=0,"",INDEX('إدخال وسجل المنتجات'!$C$5:$C$590,$I64)) -> Truffle Sauce | E64: =IF($I64=0,"",INDEX('إدخال وسجل المنتجات'!$D$5:$D$590,$I64)) -> مواد تحويلية | F64: =IF($I64=0,"",INDEX('إدخال وسجل المنتجات'!$G$5:$G$590,$I64)) -> كيلو | I64: =SUMPRODUCT(('إدخال وسجل المنتجات'!$I$5:$I$590="CHL")*('إدخال وسجل المنتجات'!$M$5:$M$590=61)*(ROW('إدخال وسجل المنتجات'!$I$5:$I$590)-4)) -> 447 | J64: =IF($I64=0,"",IF($G64="","",$G64*IF(INDEX('إدخال وسجل المنتجات'!$U$5:$U$590,$I64)=0,1,INDEX('إدخال وسجل المنتجات'!$U$5:$U$590,$I64))))
A65: =IF($I65=0,"",62) -> 62 | B65: =IF($I65=0,"",INDEX('إدخال وسجل المنتجات'!$F$5:$F$590,$I65)) -> TRN-CHL-026 | C65: =IF($I65=0,"",INDEX('إدخال وسجل المنتجات'!$B$5:$B$590,$I65)) -> صوص الروكا | D65: =IF($I65=0,"",INDEX('إدخال وسجل المنتجات'!$C$5:$C$590,$I65)) -> Arugula Sauce | E65: =IF($I65=0,"",INDEX('إدخال وسجل المنتجات'!$D$5:$D$590,$I65)) -> مواد تحويلية | F65: =IF($I65=0,"",INDEX('إدخال وسجل المنتجات'!$G$5:$G$590,$I65)) -> كيلو | I65: =SUMPRODUCT(('إدخال وسجل المنتجات'!$I$5:$I$590="CHL")*('إدخال وسجل المنتجات'!$M$5:$M$590=62)*(ROW('إدخال وسجل المنتجات'!$I$5:$I$590)-4)) -> 448 | J65: =IF($I65=0,"",IF($G65="","",$G65*IF(INDEX('إدخال وسجل المنتجات'!$U$5:$U$590,$I65)=0,1,INDEX('إدخال وسجل المنتجات'!$U$5:$U$590,$I65))))
